Workbook
Name Chave: 'Banco de Dados'!$B$2:$B$2123
Name DataCompra: OFFSET('Banco de Dados'!$E$2, 0, 0, COUNTA('Banco de Dados'!$E:$E) - 1, 1)
Name DataPedido: OFFSET('Banco de Dados'!$D$2, 0, 0, COUNTA('Banco de Dados'!$D:$D) - 1, 1)
Name DataReembolso: OFFSET('Banco de Dados'!$AK$2, 0, 0, COUNTA('Banco de Dados'!$AK:$AK) - 1, 1)
Name ELiquido: OFFSET('Banco de Dados'!$U$2, 0, 0, COUNTA('Banco de Dados'!$U:$U) - 1, 1)
Name Loja: OFFSET('Banco de Dados'!$A$2, 0, 0, COUNTA('Banco de Dados'!$A:$A) - 1, 1)
Name PedidosClientes: OFFSET('Banco de Dados'!$C$2, 0, 0, COUNTA('Banco de Dados'!$C:$C) - 1, 1)
Name PrazoEntrega: OFFSET('Banco de Dados'!$Q$2, 0, 0, COUNTA('Banco de Dados'!$Q:$Q) - 1, 1)
Name Proxy: 'Banco de Dados'!$X$2:$X$2123
Name QtdItens: OFFSET('Banco de Dados'!$H$2, 0, 0, COUNTA('Banco de Dados'!$H:$H) - 1, 1)
Name Sku: OFFSET('Banco de Dados'!$P$2, 0, 0, COUNTA('Banco de Dados'!$P:$P) - 1, 1)
Name SMS: 'Banco de Dados'!$W$2:$W$2123
Name TaxaE: OFFSET('Banco de Dados'!$T$2, 0, 0, COUNTA('Banco de Dados'!$T:$T) - 1, 1)
Name ValorBruto: OFFSET('Banco de Dados'!$S$2, 0, 0, COUNTA('Banco de Dados'!$S:$S) - 1, 1)
Name ValorLiquido: OFFSET('Banco de Dados'!$Z$2, 0, 0, COUNTA('Banco de Dados'!$Z:$Z) - 1, 1)
Name ValorPedido: OFFSET('Banco de Dados'!$R$2, 0, 0, COUNTA('Banco de Dados'!$R:$R) - 1, 1)

Sheet OBS
A1: Sobre a planilha.
A2: Essa planilha foi estruturada para automatizar cálculos e análises a partir de entradas controladas pelo usuário, garantindo mais segurança e evitando que fórmulas sejam alteradas ou quebradas.
A4: Motor da planilha (Banco de Dados).
A5: A aba Banco de Dados é o motor do sistema.
A6: Ela concentra toda a lógica, cálculos e tratamento dos dados.
A8: Os dados inseridos pelo usuário são processados nessa aba, que por sua vez alimenta automaticamente todas as outras áreas da planilha.
A10: 👉 Ou seja:
A11: O usuário não trabalha diretamente no motor, apenas fornece os inputs.
A13: Separação entre input e cálculo.
A14: A planilha foi pensada com separação clara entre:
A16: Entradas (input humano) → onde o usuário preenche informações
A17: Processamento (Banco de Dados) → onde tudo é calculado automaticamente
... A52: Criar um sistema confiável, automatizado e resistente a erros humanos, facilitando o controle e a tomada de decisão.

Sheet Controle Pedido
A4: Loja | B4: Número Pedido Cliente | C4: Data Pedido | D4: Data Compra | E4: Pedido Fornecedor | F4: Cód Rastreamento | G4: Nome Produto | H4: Qtd | I4: CPF | J4: NOME | K4: Telefone | L4: Cep | M4: Rua | N4: Complemento | O4: SKU | P4: Prazo Entrega | Q4: Valor Pedido | R4: Valor Compra | S4: Frete
A5: BV | B5: Pedido 1 | C5: 45627 | D5: - | E5: - | F5: - | G5: Suporte de Celular Branco | H5: 1 | I5: CPF 1 | J5: Nome 1 | K5: Tel 1 | L5: Cep 1 | M5: Rua 1 | N5: Comp 1 | O5: 16-4EDB-WMZF | P5: 45639 | Q5: 14.8 | R5: 0 | S5: 0
A6: BV | B6: Pedido 2 | C6: 45627 | D6: - | E6: - | F6: - | G6: Suporte de Celular Branco | H6: 1 | I6: CPF 2 | J6: Nome 2 | K6: Tel 2 | L6: Cep 2 | M6: Rua 2 | N6: Comp 2 | O6: 16-4EDB-WMZF | P6: 45638 | Q6: 14.8 | R6: 0 | S6: 0
A7: BV | B7: Pedido 3 | C7: 45627 | D7: - | E7: - | F7: - | G7: Mini Liquidificador | H7: 1 | I7: CPF 3 | J7: Nome 3 | K7: Tel 3 | L7: Cep 3 | M7: Rua 3 | N7: Comp 3 | O7: CK-YL6M-P5Y6 | P7: 45622 | Q7: 30.99 | R7: 0 | S7: 0
A8: BV | B8: Pedido 4 | C8: 45627 | D8: - | E8: - | F8: - | G8: Bomba d'agua | H8: 1 | I8: CPF 4 | J8: Nome 4 | K8: Tel 4 | L8: Cep 4 | M8: Rua 4 | N8: Comp 4 | O8: DJ-RO5O-43GF | P8: 45626 | Q8: 16.5 | R8: 0 | S8: 0
A9: BV | B9: Pedido 5 | C9: 45627 | D9: - | E9: - | F9: - | G9: Bomba d'agua | H9: 1 | I9: CPF 5 | J9: Nome 5 | K9: Tel 5 | L9: Cep 5 | M9: Rua 5 | N9: Comp 5 | O9: DJ-RO5O-43GF | P9: 45605 | Q9: 16.99 | R9: 0 | S9: 0
A10: BV | B10: Pedido 6 | C10: 45627 | D10: - | E10: - | F10: - | G10: Mini Liquidificador | H10: 1 | I10: CPF 6 | J10: Nome 6 | K10: Tel 6 | L10: Cep 6 | M10: Rua 6 | N10: Comp 6 | O10: CK-YL6M-P5Y6 | P10: 45610 | Q10: 31.99 | R10: 0 | S10: 0
A11: BV | B11: Pedido 7 | C11: 45627 | D11: - | E11: - | F11: - | G11: Ventilador Rosa | H11: 1 | I11: CPF 7 | J11: Nome 7 | K11: Tel 7 | L11: Cep 7 | M11: Rua 7 | N11: Comp 7 | O11: IF-G2ZQ-79FO | P11: 45610 | Q11: 59.99 | R11: 0 | S11: 0
A12: BV | B12: Pedido 8 | C12: 45627 | D12: - | E12: - | F12: - | G12: Mini Liquidificador | H12: 1 | I12: CPF 8 | J12: Nome 8 | K12: Tel 8 | L12: Cep 8 | M12: Rua 8 | N12: Comp 8 | O12: CK-YL6M-P5Y6 | P12: 45602 | Q12: 26.99 | R12: 0 | S12: 0
A13: BV | B13: Pedido 9 | C13: 45627 | D13: - | E13: - | F13: - | G13: Suporte de Celular Branco | H13: 1 | I13: CPF 9 | J13: Nome 9 | K13: Tel 9 | L13: Cep 9 | M13: Rua 9 | N13: Comp 9 | O13: 16-4EDB-WMZF | P13: 45611 | Q13: 14.99 | R13: 0 | S13: 0
A14: BV | B14: Pedido 10 | C14: =Controle_Pedidos[[#This Row],[Data Compra]] -> 45585 | D14: 45585 | E14: PedidoF1 | F14: CódRastreio1 | G14: Suporte de Celular Branco | H14: 1 | I14: CPF 10 | J14: Nome 10 | K14: Tel 10 | L14: Cep 10 | M14: Rua 10 | N14: Comp 10 | O14: 16-4EDB-WMZF | P14: 45601 | Q14: 14.99 | R14: 4.99 | S14: 0
A15: BV | B15: Pedido 11 | C15: =Controle_Pedidos[[#This Row],[Data Compra]] -> 45586 | D15: 45586 | E15: PedidoF2 | F15: CódRastreio2 | G15: Suporte de Celular Preto | H15: 1 | I15: CPF 11 | J15: Nome 11 | K15: Tel 11 | L15: Cep 11 | M15: Rua 11 | N15: Comp 11 | O15: 9G-BN48-QAPH | P15: 45598 | Q15: 14.99 | R15: 4.99 | S15: 0
A16: BV | B16: Pedido 12 | C16: =Controle_Pedidos[[#This Row],[Data Compra]] -> 45586 | D16: 45586 | E16: PedidoF3 | F16: CódRastreio3 | G16: Suporte de Celular Branco | H16: 1 | I16: CPF 12 | J16: Nome 12 | K16: Tel 12 | L16: Cep 12 | M16: Rua 12 | N16: Comp 12 | O16: 16-4EDB-WMZF | P16: 45604 | Q16: 14.99 | R16: 4.99 | S16: 0
A17: BV | B17: Pedido 13 | C17: =Controle_Pedidos[[#This Row],[Data Compra]] -> 45586 | D17: 45586 | E17: PedidoF4 | F17: CódRastreio4 | G17: Suporte de Celular Preto | H17: 1 | I17: CPF 13 | J17: Nome 13 | K17: Tel 13 | L17: Cep 13 | M17: Rua 13 | N17: Comp 13 | O17: 9G-BN48-QAPH | P17: 45598 | Q17: 14.99 | R17: 4.99 | S17: 0
A18: BV | B18: Pedido 14 | C18: =Controle_Pedidos[[#This Row],[Data Compra]] -> 45586 | D18: 45586 | E18: PedidoF5 | F18: CódRastreio5 | G18: Suporte de Celular Preto | H18: 1 | I18: CPF 14 | J18: Nome 14 | K18: Tel 14 | L18: Cep 14 | M18: Rua 14 | N18: Comp 14 | O18: 9G-BN48-QAPH | P18: 45610 | Q18: 14.99 | R18: 4.99 | S18: 0
A19: BV | B19: Pedido 15 | C19: =Controle_Pedidos[[#This Row],[Data Compra]] -> 45586 | D19: 45586 | E19: PedidoF6 | F19: CódRastreio6 | G19: Bomba d'agua | H19: 1 | I19: CPF 15 | J19: Nome 15 | K19: Tel 15 | L19: Cep 15 | M19: Rua 15 | N19: Comp 15 | O19: DJ-RO5O-43GF | P19: 45610 | Q19: 17.33 | R19: 6.46 | S19: 0
A20: BV | B20: Pedido 16 | C20: =Controle_Pedidos[[#This Row],[Data Compra]] -> 45586 | D20: 45586 | E20: PedidoF7 | F20: CódRastreio7 | G20: Bomba d'agua | H20: 1 | I20: CPF 16 | J20: Nome 16 | K20: Tel 16 | L20: Cep 16 | M20: Rua 16 | N20: Comp 16 | O20: DJ-RO5O-43GF | P20: 45610 | Q20: 17.33 | R20: 6.46 | S20: 0
A21: BV | B21: Pedido 17 | C21: =Controle_Pedidos[[#This Row],[Data Compra]] -> 45586 | D21: 45586 | E21: PedidoF8 | F21: CódRastreio8 | G21: Bomba d'agua | H21: 1 | I21: CPF 17 | J21: Nome 17 | K21: Tel 17 | L21: Cep 17 | M21: Rua 17 | N21: Comp 17 | O21: DJ-RO5O-43GF | P21: 45604 | Q21: 17.33 | R21: 6.46 | S21: 0
A22: BV | B22: Pedido 18 | C22: =Controle_Pedidos[[#This Row],[Data Compra]] -> 45586 | D22: 45586 | E22: PedidoF9 | F22: CódRastreio9 | G22: Suporte de Celular Branco | H22: 1 | I22: CPF 18 | J22: Nome 18 | K22: Tel 18 | L22: Cep 18 | M22: Rua 18 | N22: Comp 18 | O22: 16-4EDB-WMZF | P22: 45610 | Q22: 14.99 | R22: 4.99 | S22: 0
A23: BV | B23: Pedido 19 | C23: =Controle_Pedidos[[#This Row],[Data Compra]] -> 45587 | D23: 45587 | E23: PedidoF10 | F23: CódRastreio10 | G23: Bomba d'agua | H23: 1 | I23: CPF 19 | J23: Nome 19 | K23: Tel 19 | L23: Cep 19 | M23: Rua 19 | N23: Comp 19 | O23: DJ-RO5O-43GF | P23: 45605 | Q23: 17.33 | R23: 6.46 | S23: 0
A24: BV | B24: Pedido 20 | C24: =Controle_Pedidos[[#This Row],[Data Compra]] -> 45587 | D24: 45587 | E24: PedidoF11 | F24: CódRastreio11 | G24: Balança | H24: 1 | I24: CPF 20 | J24: Nome 20 | K24: Tel 20 | L24: Cep 20 | M24: Rua 20 | N24: Comp 20 | O24: P4-K63S-8KOM | P24: 45605 | Q24: 17.99 | R24: 7.99 | S24: 0
A25: BV | B25: Pedido 21 | C25: =Controle_Pedidos[[#This Row],[Data Compra]] -> 45587 | D25: 45587 | E25: PedidoF12 | F25: CódRastreio12 | G25: Suporte de Celular Preto | H25: 1 | I25: CPF 21 | J25: Nome 21 | K25: Tel 21 | L25: Cep 21 | M25: Rua 21 | N25: Comp 21 | O25: 9G-BN48-QAPH | P25: 45605 | Q25: 14.99 | R25: 4.99 | S25: 0
... A365: BV | B365: Pedido 358 | C365: =Controle_Pedidos[[#This Row],[Data Compra]] -> 45608 | D365: 45608 | E365: PedidoF351 | F365: CódRastreio351 | G365: Suporte de Celular Branco | H365: 1 | I365: CPF 351 | J365: Nome 351 | K365: Tel 351 | L365: Cep 351 | M365: Rua 351 | N365: Comp 351 | O365: 16-4EDB-WMZF | P365: 45625 | Q365: 15.5 | R365: 4.99 | S365: 0
A366: BV | B366: Pedido 359 | C366: 45627 | D366: - | E366: - | F366: - | G366: Copo Termico | H366: 1 | I366: CPF 339 | J366: Nome 339 | K366: Tel 339 | L366: Cep 339 | M366: Rua 339 | N366: Comp 339 | O366: KN-TBQL-K2MM | P366: 45638 | Q366: 17.4 | R366: 0 | S366: 0
A367: BV | B367: Pedido 360 | C367: 45627 | D367: - | E367: - | F367: - | G367: Copo Termico | H367: 1 | I367: CPF 339 | J367: Nome 339 | K367: Tel 339 | L367: Cep 339 | M367: Rua 339 | N367: Comp 339 | O367: KN-TBQL-K2MM | P367: 45638 | Q367: 17.4 | R367: 0 | S367: 0
A368: BV | B368: Pedido 361 | C368: 45627 | D368: - | E368: - | F368: - | G368: Copo Termico | H368: 1 | I368: CPF 339 | J368: Nome 339 | K368: Tel 339 | L368: Cep 339 | M368: Rua 339 | N368: Comp 339 | O368: KN-TBQL-K2MM | P368: 45638 | Q368: 17.4 | R368: 0 | S368: 0
A369: BV | B369: Pedido 362 | C369: 45627 | D369: - | E369: - | F369: - | G369: Copo Termico | H369: 1 | I369: CPF 339 | J369: Nome 339 | K369: Tel 339 | L369: Cep 339 | M369: Rua 339 | N369: Comp 339 | O369: KN-TBQL-K2MM | P369: 45638 | Q369: 17.4 | R369: 0 | S369: 0
A370: BV | B370: Pedido 363 | C370: =Controle_Pedidos[[#This Row],[Data Compra]] -> 45610 | D370: 45610 | E370: PedidoF352 | F370: CódRastreio352 | G370: Ventilador Preto | H370: 1 | I370: CPF 352 | J370: Nome 352 | K370: Tel 352 | L370: Cep 352 | M370: Rua 352 | N370: Comp 352 | O370: MU-J80P-95WF | P370: 45645 | Q370: 59.5 | R370: 0 | S370: 0
A371: BV | B371: Pedido 363 | C371: =Controle_Pedidos[[#This Row],[Data Compra]] -> 45609 | D371: 45609 | E371: PedidoF353 | F371: CódRastreio353 | G371: Ventilador Rosa | H371: 1 | I371: CPF 352 | J371: Nome 352 | K371: Tel 352 | L371: Cep 352 | M371: Rua 352 | N371: Comp 352 | O371: IF-G2ZQ-79FO | P371: 45645 | Q371: 59.5 | R371: 0 | S371: 0
A372: BV | B372: Pedido 364 | C372: =Controle_Pedidos[[#This Row],[Data Compra]] -> 45609 | D372: 45609 | E372: PedidoF354 | F372: CódRastreio354 | G372: Suporte de Celular Preto | H372: 1 | I372: CPF 353 | J372: Nome 353 | K372: Tel 353 | L372: Cep 353 | M372: Rua 353 | N372: Comp 353 | O372: 9G-BN48-QAPH | P372: 45638 | Q372: 17.99 | R372: 0 | S372: 0
A373: BV | B373: Pedido 365 | C373: =Controle_Pedidos[[#This Row],[Data Compra]] -> 45609 | D373: 45609 | E373: PedidoF355 | F373: CódRastreio355 | G373: Mini Liquidificador | H373: 1 | I373: CPF 354 | J373: Nome 354 | K373: Tel 354 | L373: Cep 354 | M373: Rua 354 | N373: Comp 354 | O373: CK-YL6M-P5Y6 | P373: 45638 | Q373: 31.5 | R373: 11.99 | S373: 0
A374: BV | B374: Pedido 366 | C374: =Controle_Pedidos[[#This Row],[Data Compra]] -> 45609 | D374: 45609 | E374: PedidoF356 | F374: CódRastreio356 | G374: Suporte de Celular Preto | H374: 1 | I374: CPF 355 | J374: Nome 355 | K374: Tel 355 | L374: Cep 355 | M374: Rua 355 | N374: Comp 355 | O374: 9G-BN48-QAPH | P374: 45632 | Q374: 17.99 | R374: 6.99 | S374: 0
A375: BV | B375: Pedido 367 | C375: =Controle_Pedidos[[#This Row],[Data Compra]] -> 45609 | D375: 45609 | E375: PedidoF357 | F375: CódRastreio357 | G375: Ventilador de teto | H375: 1 | I375: CPF 356 | J375: Nome 356 | K375: Tel 356 | L375: Cep 356 | M375: Rua 356 | N375: Comp 356 | O375: BP-NHG2-B8C1 | P375: 45638 | Q375: 49.5 | R375: 10.71 | S375: 0
A376: BV | B376: Pedido 368 | C376: =Controle_Pedidos[[#This Row],[Data Compra]] -> 45609 | D376: 45609 | E376: PedidoF358 | F376: CódRastreio358 | G376: Copo Termico | H376: 1 | I376: CPF 357 | J376: Nome 357 | K376: Tel 357 | L376: Cep 357 | M376: Rua 357 | N376: Comp 357 | O376: KN-TBQL-K2MM | P376: 45638 | Q376: 17.4 | R376: 6.99 | S376: 0
A377: BV | B377: Pedido 369 | C377: =Controle_Pedidos[[#This Row],[Data Compra]] -> 45609 | D377: 45609 | E377: PedidoF359 | F377: CódRastreio359 | G377: Mini Liquidificador | H377: 1 | I377: CPF 358 | J377: Nome 358 | K377: Tel 358 | L377: Cep 358 | M377: Rua 358 | N377: Comp 358 | O377: CK-YL6M-P5Y6 | P377: 45638 | Q377: 31.5 | R377: 11.99 | S377: 0
A378: BV | B378: Pedido 370 | C378: =Controle_Pedidos[[#This Row],[Data Compra]] -> 45609 | D378: 45609 | E378: PedidoF360 | F378: CódRastreio360 | G378: Ventilador Azul | H378: 1 | I378: CPF 359 | J378: Nome 359 | K378: Tel 359 | L378: Cep 359 | M378: Rua 359 | N378: Comp 359 | O378: U8-2VWS-OB6M | P378: 45638 | Q378: 59.5 | R378: 10.18 | S378: 0
A379: BV | B379: Pedido 371 | C379: =Controle_Pedidos[[#This Row],[Data Compra]] -> 45610 | D379: 45610 | E379: PedidoF361 | F379: CódRastreio361 | G379: Suporte de Celular Preto | H379: 1 | I379: CPF 360 | J379: Nome 360 | K379: Tel 360 | L379: Cep 360 | M379: Rua 360 | N379: Comp 360 | O379: 9G-BN48-QAPH | P379: 45639 | Q379: 18.5 | R379: 6.99 | S379: 0
A380: BV | B380: Pedido 372 | C380: =Controle_Pedidos[[#This Row],[Data Compra]] -> 45610 | D380: 45610 | E380: PedidoF362 | F380: CódRastreio362 | G380: Ventilador Preto | H380: 1 | I380: CPF 361 | J380: Nome 361 | K380: Tel 361 | L380: Cep 361 | M380: Rua 361 | N380: Comp 361 | O380: MU-J80P-95WF | P380: 45639 | Q380: 59.5 | R380: 10.23 | S380: 0
A381: BV | B381: Pedido 373 | C381: =Controle_Pedidos[[#This Row],[Data Compra]] -> 45610 | D381: 45610 | E381: PedidoF363 | F381: CódRastreio363 | G381: Mini Liquidificador | H381: 1 | I381: CPF 362 | J381: Nome 362 | K381: Tel 362 | L381: Cep 362 | M381: Rua 362 | N381: Comp 362 | O381: CK-YL6M-P5Y6 | P381: 45633 | Q381: 29.5 | R381: 11.99 | S381: 0
... A412: BV | B412: Pedido 404 | C412: =Controle_Pedidos[[#This Row],[Data Compra]] -> 45616 | D412: 45616 | E412: PedidoF394 | F412: CódRastreio394 | G412: Ventilador Umidificador Branco | H412: 1 | I412: CPF 391 | J412: Nome 391 | K412: Tel 391 | L412: Cep 391 | M412: Rua 391 | N412: Comp 391 | O412: IA-LLX9-MRV1 | P412: 45643 | Q412: 52.99 | R412: 10.18 | S412: 0
A413: BV | B413: Pedido 405 | C413: 45627 | D413: - | E413: - | F413: - | G413: Ventilador de teto | H413: 1 | I413: CPF 392 | J413: Nome 392 | K413: Tel 392 | L413: Cep 392 | M413: Rua 392 | N413: Comp 392 | O413: BP-NHG2-B8C1 | P413: 45637 | Q413: 48.99 | R413: 0 | S413: 0
A414: BV | B414: Pedido 406 | C414: =Controle_Pedidos[[#This Row],[Data Compra]] -> 45616 | D414: 45616 | E414: PedidoF395 | F414: CódRastreio395 | G414: Ventilador Preto | H414: 1 | I414: CPF 393 | J414: Nome 393 | K414: Tel 393 | L414: Cep 393 | M414: Rua 393 | N414: Comp 393 | O414: MU-J80P-95WF | P414: 45637 | Q414: 59.2 | R414: 10.81 | S414: 0
A415: BV | B415: Pedido 407 | C415: =Controle_Pedidos[[#This Row],[Data Compra]] -> 45616 | D415: 45616 | E415: PedidoF396 | F415: CódRastreio396 | G415: Ventilador Preto | H415: 1 | I415: CPF 394 | J415: Nome 394 | K415: Tel 394 | L415: Cep 394 | M415: Rua 394 | N415: Comp 394 | O415: MU-J80P-95WF | P415: 45637 | Q415: 59.2 | R415: 11.14 | S415: 0
A416: BV | B416: Pedido 408 | C416: =Controle_Pedidos[[#This Row],[Data Compra]] -> 45616 | D416: 45616 | E416: PedidoF397 | F416: CódRastreio397 | G416: Ventilador Preto | H416: 1 | I416: CPF 395 | J416: Nome 395 | K416: Tel 395 | L416: Cep 395 | M416: Rua 395 | N416: Comp 395 | O416: MU-J80P-95WF | P416: 45637 | Q416: 59.2 | R416: 11.14 | S416: 0
A417: BV | B417: Pedido 409 | C417: =Controle_Pedidos[[#This Row],[Data Compra]] -> 45616 | D417: 45616 | E417: PedidoF398 | F417: CódRastreio398 | G417: Garrafa Termica | H417: 1 | I417: CPF 396 | J417: Nome 396 | K417: Tel 396 | L417: Cep 396 | M417: Rua 396 | N417: Comp 396 | O417: FM-QQ8Y-RZT4 | P417: 45631 | Q417: 22.5 | R417: 10.18 | S417: 0
A418: BV | B418: Pedido 410 | C418: =Controle_Pedidos[[#This Row],[Data Compra]] -> 45616 | D418: 45616 | E418: PedidoF399 | F418: CódRastreio399 | G418: Suporte de Celular Preto | H418: 1 | I418: CPF 397 | J418: Nome 397 | K418: Tel 397 | L418: Cep 397 | M418: Rua 397 | N418: Comp 397 | O418: 9G-BN48-QAPH | P418: 45637 | Q418: 18.1 | R418: 6.99 | S418: 0
A419: BV | B419: Pedido 411 | C419: =Controle_Pedidos[[#This Row],[Data Compra]] -> 45616 | D419: 45616 | E419: PedidoF400 | F419: CódRastreio400 | G419: Mini Mixer Misturador | H419: 1 | I419: CPF 398 | J419: Nome 398 | K419: Tel 398 | L419: Cep 398 | M419: Rua 398 | N419: Comp 398 | O419: FK-T01D-KZC5 | P419: 45643 | Q419: 18.99 | R419: 6.99 | S419: 0
A420: BV | B420: Pedido 412 | C420: =Controle_Pedidos[[#This Row],[Data Compra]] -> 45616 | D420: 45616 | E420: PedidoF401 | F420: CódRastreio401 | G420: Mini Liquidificador | H420: 1 | I420: CPF 399 | J420: Nome 399 | K420: Tel 399 | L420: Cep 399 | M420: Rua 399 | N420: Comp 399 | O420: CK-YL6M-P5Y6 | P420: 45637 | Q420: 31.5 | R420: 13.99 | S420: 0
A421: BV | B421: Pedido 413 | C421: =Controle_Pedidos[[#This Row],[Data Compra]] -> 45616 | D421: 45616 | E421: PedidoF402 | F421: CódRastreio402 | G421: Ventilador Rosa | H421: 1 | I421: CPF 400 | J421: Nome 400 | K421: Tel 400 | L421: Cep 400 | M421: Rua 400 | N421: Comp 400 | O421: IF-G2ZQ-79FO | P421: 45643 | Q421: 59.2 | R421: 10.59 | S421: 0
A422: BV | B422: Pedido 414 | C422: =Controle_Pedidos[[#This Row],[Data Compra]] -> 45616 | D422: 45616 | E422: PedidoF403 | F422: CódRastreio403 | G422: Mini Mixer Misturador | H422: 1 | I422: CPF 401 | J422: Nome 401 | K422: Tel 401 | L422: Cep 401 | M422: Rua 401 | N422: Comp 401 | O422: FK-T01D-KZC5 | P422: 45643 | Q422: 18.99 | R422: 6.99 | S422: 0
A423: BV | B423: Pedido 415 | C423: =Controle_Pedidos[[#This Row],[Data Compra]] -> 45617 | D423: 45617 | E423: PedidoF404 | F423: CódRastreio404 | G423: Adaptador Bluetooph | H423: 1 | I423: CPF 402 | J423: Nome 402 | K423: Tel 402 | L423: Cep 402 | M423: Rua 402 | N423: Comp 402 | O423: YA-AG3H-SPUK | P423: 45644 | Q423: 16.99 | R423: 6.99 | S423: 0
A424: BV | B424: Pedido 415 | C424: 45627 | D424: - | E424: - | F424: - | G424: Adaptador Bluetooph | H424: 1 | I424: CPF 402 | J424: Nome 402 | K424: Tel 402 | L424: Cep 402 | M424: Rua 402 | N424: Comp 402 | O424: YA-AG3H-SPUK | P424: 45644 | Q424: 16.99 | R424: 0 | S424: 0
A425: BV | B425: Pedido 416 | C425: =Controle_Pedidos[[#This Row],[Data Compra]] -> 45617 | D425: 45617 | E425: PedidoF405 | F425: CódRastreio405 | G425: Suporte de Celular Preto | H425: 1 | I425: CPF 403 | J425: Nome 403 | K425: Tel 403 | L425: Cep 403 | M425: Rua 403 | N425: Comp 403 | O425: 9G-BN48-QAPH | P425: 45632 | Q425: 18.1 | R425: 6.99 | S425: 0
A426: BV | B426: Pedido 417 | C426: =Controle_Pedidos[[#This Row],[Data Compra]] -> 45617 | D426: 45617 | E426: PedidoF406 | F426: CódRastreio406 | G426: Ventilador Preto | H426: 1 | I426: CPF 404 | J426: Nome 404 | K426: Tel 404 | L426: Cep 404 | M426: Rua 404 | N426: Comp 404 | O426: MU-J80P-95WF | P426: 45638 | Q426: 59.2 | R426: 16.01 | S426: 0
A427: BV | B427: Pedido 418 | C427: =Controle_Pedidos[[#This Row],[Data Compra]] -> 45617 | D427: 45617 | E427: PedidoF407 | F427: CódRastreio407 | G427: Ventilador Preto | H427: 1 | I427: CPF 404 | J427: Nome 404 | K427: Tel 404 | L427: Cep 404 | M427: Rua 404 | N427: Comp 404 | O427: MU-J80P-95WF | P427: 45638 | Q427: 59.2 | R427: 16.01 | S427: 0
A428: BV | B428: Pedido 419 | C428: =Controle_Pedidos[[#This Row],[Data Compra]] -> 45617 | D428: 45617 | E428: PedidoF408 | F428: CódRastreio408 | G428: Ventilador Rosa | H428: 1 | I428: CPF 405 | J428: Nome 405 | K428: Tel 405 | L428: Cep 405 | M428: Rua 405 | N428: Comp 405 | O428: IF-G2ZQ-79FO | P428: 45653 | Q428: 59.2 | R428: 15.36 | S428: 0
A429: BV | B429: Pedido 420 | C429: =Controle_Pedidos[[#This Row],[Data Compra]] -> 45617 | D429: 45617 | E429: PedidoF409 | F429: CódRastreio409 | G429: Ventilador Azul | H429: 1 | I429: CPF 406 | J429: Nome 406 | K429: Tel 406 | L429: Cep 406 | M429: Rua 406 | N429: Comp 406 | O429: U8-2VWS-OB6M | P429: 45653 | Q429: 59.2 | R429: 15.36 | S429: 0
A430: BV | B430: Pedido 421 | C430: =Controle_Pedidos[[#This Row],[Data Compra]] -> 45617 | D430: 45617 | E430: PedidoF410 | F430: CódRastreio410 | G430: Ventilador Rosa | H430: 1 | I430: CPF 407 | J430: Nome 407 | K430: Tel 407 | L430: Cep 407 | M430: Rua 407 | N430: Comp 407 | O430: IF-G2ZQ-79FO | P430: 45653 | Q430: 59.2 | R430: 15.36 | S430: 0
A431: BV | B431: Pedido 422 | C431: =Controle_Pedidos[[#This Row],[Data Compra]] -> 45617 | D431: 45617 | E431: PedidoF411 | F431: CódRastreio411 | G431: Ventilador Preto | H431: 1 | I431: CPF 408 | J431: Nome 408 | K431: Tel 408 | L431: Cep 408 | M431: Rua 408 | N431: Comp 408 | O431: MU-J80P-95WF | P431: 45638 | Q431: 59.2 | R431: 16.01 | S431: 0
A432: BV | B432: Pedido 423 | C432: 45627 | D432: - | E432: - | F432: - | G432: Bomba d'agua | H432: 1 | I432: CPF 409 | J432: Nome 409 | K432: Tel 409 | L432: Cep 409 | M432: Rua 409 | N432: Comp 409 | O432: DJ-RO5O-43GF | P432: 45632 | Q432: 18.5 | R432: 0 | S432: 0
A433: BV | B433: Pedido 424 | C433: 45627 | D433: - | E433: - | F433: - | G433: Garrafa Termica | H433: 1 | I433: CPF 410 | J433: Nome 410 | K433: Tel 410 | L433: Cep 410 | M433: Rua 410 | N433: Comp 410 | O433: FM-QQ8Y-RZT4 | P433: 45644 | Q433: 22.5 | R433: 0 | S433: 0
A434: BV | B434: Pedido 425 | C434: =Controle_Pedidos[[#This Row],[Data Compra]] -> 45617 | D434: 45617 | E434: PedidoF412 | F434: CódRastreio412 | G434: Adaptador Bluetooph | H434: 1 | I434: CPF 411 | J434: Nome 411 | K434: Tel 411 | L434: Cep 411 | M434: Rua 411 | N434: Comp 411 | O434: YA-AG3H-SPUK | P434: 45632 | Q434: 16.99 | R434: 6.99 | S434: 0
A435: BV | B435: Pedido 426 | C435: =Controle_Pedidos[[#This Row],[Data Compra]] -> 45618 | D435: 45618 | E435: PedidoF413 | F435: CódRastreio413 | G435: Adaptador Bluetooph | H435: 1 | I435: CPF 412 | J435: Nome 412 | K435: Tel 412 | L435: Cep 412 | M435: Rua 412 | N435: Comp 412 | O435: YA-AG3H-SPUK | P435: 45645 | Q435: 16.99 | R435: 0 | S435: 0
A436: BV | B436: Pedido 426 | C436: =Controle_Pedidos[[#This Row],[Data Compra]] -> 45621 | D436: 45621 | E436: PedidoF414 | F436: CódRastreio414 | G436: Adaptador Bluetooph | H436: 1 | I436: CPF 412 | J436: Nome 412 | K436: Tel 412 | L436: Cep 412 | M436: Rua 412 | N436: Comp 412 | O436: YA-AG3H-SPUK | P436: 45645 | Q436: 16.99 | R436: 0 | S436: 0
A437: BV | B437: Pedido 426 | C437: =Controle_Pedidos[[#This Row],[Data Compra]] -> 45622 | D437: 45622 | E437: PedidoF415 | F437: CódRastreio415 | G437: Adaptador Bluetooph | H437: 1 | I437: CPF 412 | J437: Nome 412 | K437: Tel 412 | L437: Cep 412 | M437: Rua 412 | N437: Comp 412 | O437: YA-AG3H-SPUK | P437: 45645 | Q437: 16.99 | R437: 0 | S437: 0
A438: BV | B438: Pedido 426 | C438: 45627 | D438: - | E438: - | F438: - | G438: Adaptador Bluetooph | H438: 1 | I438: CPF 412 | J438: Nome 412 | K438: Tel 412 | L438: Cep 412 | M438: Rua 412 | N438: Comp 412 | O438: YA-AG3H-SPUK | P438: 45645 | Q438: 16.99 | R438: 0 | S438: 0
A439: BV | B439: Pedido 426 | C439: 45627 | D439: - | E439: - | F439: - | G439: Adaptador Bluetooph | H439: 1 | I439: CPF 412 | J439: Nome 412 | K439: Tel 412 | L439: Cep 412 | M439: Rua 412 | N439: Comp 412 | O439: YA-AG3H-SPUK | P439: 45645 | Q439: 16.99 | R439: 0 | S439: 0
A440: BV | B440: Pedido 427 | C440: 45627 | D440: - | E440: - | F440: - | G440: Ventilador Preto | H440: 1 | I440: CPF 413 | J440: Nome 413 | K440: Tel 413 | L440: Cep 413 | M440: Rua 413 | N440: Comp 413 | O440: MU-J80P-95WF | P440: 45645 | Q440: 65.99 | R440: 0 | S440: 0
A441: BV | B441: Pedido 428 | C441: 45627 | D441: - | E441: - | F441: - | G441: Copo Termico | H441: 1 | I441: CPF 414 | J441: Nome 414 | K441: Tel 414 | L441: Cep 414 | M441: Rua 414 | N441: Comp 414 | O441: KN-TBQL-K2MM | P441: 45654 | Q441: 28.2 | R441: 0 | S441: 0
A442: BV | B442: Pedido 429 | C442: 45627 | D442: - | E442: - | F442: - | G442: Copo Termico | H442: 1 | I442: CPF 414 | J442: Nome 414 | K442: Tel 414 | L442: Cep 414 | M442: Rua 414 | N442: Comp 414 | O442: KN-TBQL-K2MM | P442: 45654 | Q442: 28.2 | R442: 0 | S442: 0
A443: BV | B443: Pedido 430 | C443: =Controle_Pedidos[[#This Row],[Data Compra]] -> 45618 | D443: 45618 | E443: PedidoF416 | F443: CódRastreio416 | G443: Ventilador Preto | H443: 1 | I443: CPF 415 | J443: Nome 415 | K443: Tel 415 | L443: Cep 415 | M443: Rua 415 | N443: Comp 415 | O443: MU-J80P-95WF | P443: 45639 | Q443: 65.99 | R443: 10.21 | S443: 0
A444: BV | B444: Pedido 431 | C444: =Controle_Pedidos[[#This Row],[Data Compra]] -> 45621 | D444: 45621 | E444: PedidoF417 | F444: CódRastreio417 | G444: Ventilador Preto | H444: 1 | I444: CPF 416 | J444: Nome 416 | K444: Tel 416 | L444: Cep 416 | M444: Rua 416 | N444: Comp 416 | O444: MU-J80P-95WF | P444: 45646 | Q444: 65.99 | R444: 10.22 | S444: 0
A445: BV | B445: Pedido 432 | C445: =Controle_Pedidos[[#This Row],[Data Compra]] -> 45621 | D445: 45621 | E445: PedidoF418 | F445: CódRastreio418 | G445: Ventilador Preto | H445: 1 | I445: CPF 417 | J445: Nome 417 | K445: Tel 417 | L445: Cep 417 | M445: Rua 417 | N445: Comp 417 | O445: MU-J80P-95WF | P445: 45646 | Q445: 65.99 | R445: 10.22 | S445: 0
A446: BV | B446: Pedido 433 | C446: =Controle_Pedidos[[#This Row],[Data Compra]] -> 45621 | D446: 45621 | E446: PedidoF419 | F446: CódRastreio419 | G446: Mini Liquidificador | H446: 1 | I446: CPF 418 | J446: Nome 418 | K446: Tel 418 | L446: Cep 418 | M446: Rua 418 | N446: Comp 418 | O446: CK-YL6M-P5Y6 | P446: 45640 | Q446: 39.99 | R446: 14.99 | S446: 0
A447: BV | B447: Pedido 434 | C447: =Controle_Pedidos[[#This Row],[Data Compra]] -> 45621 | D447: 45621 | E447: PedidoF420 | F447: CódRastreio420 | G447: Ventilador Preto | H447: 1 | I447: CPF 419 | J447: Nome 419 | K447: Tel 419 | L447: Cep 419 | M447: Rua 419 | N447: Comp 419 | O447: MU-J80P-95WF | P447: 45646 | Q447: 65.99 | R447: 10.22 | S447: 0
A448: BV | B448: Pedido 435 | C448: =Controle_Pedidos[[#This Row],[Data Compra]] -> 45622 | D448: 45622 | E448: PedidoF421 | F448: CódRastreio421 | G448: Copo Termico | H448: 1 | I448: CPF 420 | J448: Nome 420 | K448: Tel 420 | L448: Cep 420 | M448: Rua 420 | N448: Comp 420 | O448: KN-TBQL-K2MM | P448: 45636 | Q448: 27.99 | R448: 10.12 | S448: 0
A449: BV | B449: Pedido 436 | C449: =Controle_Pedidos[[#This Row],[Data Compra]] -> 45622 | D449: 45622 | E449: PedidoF422 | F449: CódRastreio422 | G449: Ventilador Preto | H449: 1 | I449: CPF 421 | J449: Nome 421 | K449: Tel 421 | L449: Cep 421 | M449: Rua 421 | N449: Comp 421 | O449: MU-J80P-95WF | P449: 45646 | Q449: 65.99 | R449: 10.21 | S449: 0
A450: BV | B450: Pedido 437 | C450: =Controle_Pedidos[[#This Row],[Data Compra]] -> 45622 | D450: 45622 | E450: PedidoF423 | F450: - | G450: Copo Termico | H450: 1 | I450: CPF 422 | J450: Nome 422 | K450: Tel 422 | L450: Cep 422 | M450: Rua 422 | N450: Comp 422 | O450: KN-TBQL-K2MM | P450: 45647 | Q450: 27.99 | R450: 0 | S450: 0
A451: BV | B451: Pedido 438 | C451: =Controle_Pedidos[[#This Row],[Data Compra]] -> 45622 | D451: 45622 | E451: PedidoF424 | F451: CódRastreio423 | G451: Ventilador Preto | H451: 1 | I451: CPF 423 | J451: Nome 423 | K451: Tel 423 | L451: Cep 423 | M451: Rua 423 | N451: Comp 423 | O451: MU-J80P-95WF | P451: 45647 | Q451: 65.99 | R451: 10.21 | S451: 0
A452: BV | B452: Pedido 439 | C452: =Controle_Pedidos[[#This Row],[Data Compra]] -> 45622 | D452: 45622 | E452: PedidoF425 | F452: CódRastreio424 | G452: Ventilador Azul | H452: 1 | I452: CPF 424 | J452: Nome 424 | K452: Tel 424 | L452: Cep 424 | M452: Rua 424 | N452: Comp 424 | O452: U8-2VWS-OB6M | P452: 45660 | Q452: 65.99 | R452: 10.21 | S452: 0
A453: BV | B453: Pedido 440 | C453: =Controle_Pedidos[[#This Row],[Data Compra]] -> 45622 | D453: 45622 | E453: PedidoF426 | F453: CódRastreio425 | G453: Ventilador Rosa | H453: 1 | I453: CPF 425 | J453: Nome 425 | K453: Tel 425 | L453: Cep 425 | M453: Rua 425 | N453: Comp 425 | O453: IF-G2ZQ-79FO | P453: 45647 | Q453: 65.99 | R453: 11.19 | S453: 0
A454: BV | B454: Pedido 441 | C454: =Controle_Pedidos[[#This Row],[Data Compra]] -> 45622 | D454: 45622 | E454: PedidoF427 | F454: CódRastreio426 | G454: Copo Termico | H454: 1 | I454: CPF 426 | J454: Nome 426 | K454: Tel 426 | L454: Cep 426 | M454: Rua 426 | N454: Comp 426 | O454: KN-TBQL-K2MM | P454: 45647 | Q454: 27.99 | R454: 8.2 | S454: 0
... A464: BV | B464: Pedido 450 | C464: =Controle_Pedidos[[#This Row],[Data Compra]] -> 45623 | D464: 45623 | E464: PedidoF437 | F464: CódRastreio436 | G464: Ventilador Rosa | H464: 1 | I464: CPF 435 | J464: Nome 435 | K464: Tel 435 | L464: Cep 435 | M464: Rua 435 | N464: Comp 435 | O464: IF-G2ZQ-79FO | P464: 45644 | Q464: 65.99 | R464: 12.89 | S464: 0
A465: BV | B465: Pedido 451 | C465: 45627 | D465: - | E465: - | F465: - | G465: Copo Termico | H465: 1 | I465: CPF 436 | J465: Nome 436 | K465: Tel 436 | L465: Cep 436 | M465: Rua 436 | N465: Comp 436 | O465: KN-TBQL-K2MM | P465: 45644 | Q465: 27.99 | R465: 0 | S465: 0
A466: BV | B466: Pedido 452 | C466: =Controle_Pedidos[[#This Row],[Data Compra]] -> 45623 | D466: 45623 | E466: PedidoF438 | F466: CódRastreio437 | G466: Ventilador Umidificador Branco | H466: 1 | I466: CPF 437 | J466: Nome 437 | K466: Tel 437 | L466: Cep 437 | M466: Rua 437 | N466: Comp 437 | O466: IA-LLX9-MRV1 | P466: 45644 | Q466: 54.5 | R466: 10.17 | S466: 0
A467: BV | B467: Pedido 453 | C467: =Controle_Pedidos[[#This Row],[Data Compra]] -> 45623 | D467: 45623 | E467: PedidoF439 | F467: CódRastreio438 | G467: Mini Mixer Misturador | H467: 1 | I467: CPF 438 | J467: Nome 438 | K467: Tel 438 | L467: Cep 438 | M467: Rua 438 | N467: Comp 438 | O467: FK-T01D-KZC5 | P467: 45644 | Q467: 18.99 | R467: 6.99 | S467: 0
A468: BV | B468: Pedido 454 | C468: =Controle_Pedidos[[#This Row],[Data Compra]] -> 45624 | D468: 45624 | E468: PedidoF440 | F468: CódRastreio439 | G468: Ventilador Umidificador Branco | H468: 1 | I468: CPF 439 | J468: Nome 439 | K468: Tel 439 | L468: Cep 439 | M468: Rua 439 | N468: Comp 439 | O468: IA-LLX9-MRV1 | P468: 45645 | Q468: 54.5 | R468: 10.38 | S468: 0
A469: BV | B469: Pedido 455 | C469: =Controle_Pedidos[[#This Row],[Data Compra]] -> 45624 | D469: 45624 | E469: PedidoF441 | F469: CódRastreio440 | G469: Ventilador Preto | H469: 1 | I469: CPF 440 | J469: Nome 440 | K469: Tel 440 | L469: Cep 440 | M469: Rua 440 | N469: Comp 440 | O469: MU-J80P-95WF | P469: 45645 | Q469: 65.99 | R469: 14.67 | S469: 0
A470: BV | B470: Pedido 456 | C470: =Controle_Pedidos[[#This Row],[Data Compra]] -> 45624 | D470: 45624 | E470: PedidoF442 | F470: CódRastreio441 | G470: Ventilador Preto | H470: 1 | I470: CPF 441 | J470: Nome 441 | K470: Tel 441 | L470: Cep 441 | M470: Rua 441 | N470: Comp 441 | O470: MU-J80P-95WF | P470: 45645 | Q470: 65.99 | R470: 14.67 | S470: 0
A471: BV | B471: Pedido 457 | C471: =Controle_Pedidos[[#This Row],[Data Compra]] -> 45624 | D471: 45624 | E471: PedidoF443 | F471: CódRastreio442 | G471: Mini Liquidificador | H471: 1 | I471: CPF 442 | J471: Nome 442 | K471: Tel 442 | L471: Cep 442 | M471: Rua 442 | N471: Comp 442 | O471: CK-YL6M-P5Y6 | P471: 45653 | Q471: 39.99 | R471: 17.99 | S471: 0
A472: BV | B472: Pedido 458 | C472: =Controle_Pedidos[[#This Row],[Data Compra]] -> 45624 | D472: 45624 | E472: PedidoF444 | F472: CódRastreio443 | G472: Ventilador Preto | H472: 1 | I472: CPF 443 | J472: Nome 443 | K472: Tel 443 | L472: Cep 443 | M472: Rua 443 | N472: Comp 443 | O472: MU-J80P-95WF | P472: 45645 | Q472: 65.99 | R472: 14.67 | S472: 0
A473: BV | B473: Pedido 459 | C473: =Controle_Pedidos[[#This Row],[Data Compra]] -> 45624 | D473: 45624 | E473: PedidoF445 | F473: CódRastreio444 | G473: Adaptador Bluetooph | H473: 1 | I473: CPF 444 | J473: Nome 444 | K473: Tel 444 | L473: Cep 444 | M473: Rua 444 | N473: Comp 444 | O473: YA-AG3H-SPUK | P473: 45643 | Q473: 18.5 | R473: 8.58 | S473: 0
A474: BV | B474: Pedido 460 | C474: =Controle_Pedidos[[#This Row],[Data Compra]] -> 45624 | D474: 45624 | E474: PedidoF446 | F474: CódRastreio445 | G474: Adaptador Bluetooph | H474: 1 | I474: CPF 445 | J474: Nome 445 | K474: Tel 445 | L474: Cep 445 | M474: Rua 445 | N474: Comp 445 | O474: YA-AG3H-SPUK | P474: 45645 | Q474: 18.5 | R474: 8.58 | S474: 0
A475: BV | B475: Pedido 461 | C475: =Controle_Pedidos[[#This Row],[Data Compra]] -> 45624 | D475: 45624 | E475: PedidoF447 | F475: CódRastreio446 | G475: Ventilador Umidificador Branco | H475: 1 | I475: CPF 446 | J475: Nome 446 | K475: Tel 446 | L475: Cep 446 | M475: Rua 446 | N475: Comp 446 | O475: IA-LLX9-MRV1 | P475: 45653 | Q475: 54.5 | R475: 10.38 | S475: 0
A476: BV | B476: Pedido 462 | C476: =Controle_Pedidos[[#This Row],[Data Compra]] -> 45625 | D476: 45625 | E476: PedidoF448 | F476: CódRastreio447 | G476: Bomba d'agua | H476: 1 | I476: CPF 447 | J476: Nome 447 | K476: Tel 447 | L476: Cep 447 | M476: Rua 447 | N476: Comp 447 | O476: DJ-RO5O-43GF | P476: 45643 | Q476: 25.99 | R476: 14.4 | S476: 0
A477: BV | B477: Pedido 463 | C477: =Controle_Pedidos[[#This Row],[Data Compra]] -> 45624 | D477: 45624 | E477: PedidoF449 | F477: CódRastreio448 | G477: Mini Liquidificador | H477: 1 | I477: CPF 448 | J477: Nome 448 | K477: Tel 448 | L477: Cep 448 | M477: Rua 448 | N477: Comp 448 | O477: CK-YL6M-P5Y6 | P477: 45653 | Q477: 39.99 | R477: 17.99 | S477: 0
... A618: BV | B618: Pedido 603 | C618: =Controle_Pedidos[[#This Row],[Data Compra]] -> 45653 | D618: 45653 | E618: PedidoF590 | F618: CódRastreio588 | G618: Ventilador Preto | H618: 1 | I618: CPF 585 | J618: Nome 585 | K618: Tel 585 | L618: Cep 585 | M618: Rua 585 | N618: Comp 585 | O618: MU-J80P-95WF | P618: 45673 | Q618: 65.6 | R618: 17.4 | S618: 0
A619: BV | B619: Pedido 604 | C619: 45627 | D619: - | E619: - | F619: - | G619: Ventilador Azul | H619: 1 | I619: CPF 586 | J619: Nome 586 | K619: Tel 586 | L619: Cep 586 | M619: Rua 586 | N619: Comp 586 | O619: U8-2VWS-OB6M | P619: 45679 | Q619: 65.6 | R619: 0 | S619: 0
A620: BV | B620: Pedido 604 | C620: 45627 | D620: - | E620: - | F620: - | G620: Ventilador Rosa | H620: 1 | I620: CPF 586 | J620: Nome 586 | K620: Tel 586 | L620: Cep 586 | M620: Rua 586 | N620: Comp 586 | O620: IF-G2ZQ-79FO | P620: 45679 | Q620: 49.4 | R620: 0 | S620: 0
A621: BV | B621: Pedido 605 | C621: =Controle_Pedidos[[#This Row],[Data Compra]] -> 45648 | D621: 45648 | E621: PedidoF591 | F621: CódRastreio589 | G621: Ventilador Preto | H621: 1 | I621: CPF 481 | J621: Nome 481 | K621: Tel 481 | L621: Cep 481 | M621: Rua 481 | N621: Comp 481 | O621: MU-J80P-95WF | P621: 45673 | Q621: 65.6 | R621: 16.7 | S621: 0
...

Sheet Follow Up
A2: Contagem de Id Pedido | B2: Rótulos de Coluna | F2: Rótulos de Linha | G2: Contagem de CODRASTREIO
A3: Rótulos de Linha | B3: Brasil | C3: China | D3: Total Geral | F3: Dentro do Prazo | G3: 1801 | H3: =G3/$G$5 -> 0.91097623
A4: EM SEPARAÇÃO | B4: 3 | C4: 11 | D4: 14 | F4: Fora do Prazo | G4: 176 | H4: =G4/$G$5 -> 0.089023773
A5: RETORNANDO | C5: 2 | D5: 2 | F5: Total Geral | G5: 1977
A6: EM TRÂNSITO | B6: 9 | C6: 2 | D6: 11
A7: Total Geral | B7: 12 | C7: 15 | D7: 27
A11: Id Pedido | B11: CODRASTREIO | C11: CODRASTREIO2 | D11: Loja | E11: Prev Entrega | F11: Transp | G11: Novo Cód de Rastreio | H11: PAISORIGEM | I11: PAISDESTINO | J11: DATAATUALIZAÇÃO | K11: - | L11: STATUS | M11: Obs | N11: Prazo | O11: MSG
A12: Pedido 363 | B12: CódRastreio352 1 envio | C12: =Follow[[#This Row],[CODRASTREIO]]&" B" -> CódRastreio352 1 envio B | D12: BV | E12: 45645 | F12: Transp 1 | G12: - | H12: China | I12: Brasil | J12: 45644 | K12: Entregue | L12: ENTREGUE | M12: Fornecedor não vai Reembolsar | N12: =IF(Follow[[#This Row],[DATAATUALIZAÇÃO]]<=Follow[[#This Row],[Prev Entrega]],"Dentro do Prazo","Fora do Prazo") -> Dentro do Prazo | O12: =_xlfn.CONCAT("Olá ",PROPER(LOWER(TRIM(LEFT(SUBSTITUTE(_xlfn.XLOOKUP(Follow[[#This Row],[Id Pedido]],Controle_Pedidos[Número Pedido Cliente],Controle_Pedidos[NOME])," ",REPT(" ",100)),100)))),", Identificamos que o Item ",_xlfn.XLOOKUP(Follow[[#This Row],[Id Pedido]],Controle_Pedidos[Número Pedido Cliente],Controle_Pedidos[Nome Produto])," foi entregue no dia ",TEXT(Follow[[#This Row],[DATAATUALIZAÇÃO]],"dd/mm/aaaa"),", referente ao pedido Nº ",Follow[[#This Row],[Id Pedido]]," Rastreio ",IF(Follow[[#This Row],[Novo Cód de Rastreio]]="-",Follow[[#This Row],[Id Pedido]],Follow[[#This Row],[Novo Cód de Rastreio]]),", agradecemos a preferência e adoraríamos receber sua avaliação, tendo qualquer dúvida estamos à disposição.",_xlfn.IFS(Follow[[#This Row],[Loja]]="bv"," Att Tem tudo Shop",Follow[[#This Row],[Loja]]="mei"," Att NTA Variedades",Follow[[#This Row],[Loja]]="go"," Att Sec Variedades")) -> Olá Nome, Identificamos que o Item Ventilador Preto foi entregue no dia 18/12/2024, referente ao pedido Nº Pedido 363 Rastreio Pedido 363, agradecemos a preferência e adoraríamos receber sua avaliação, tendo qualquer dúvida estamos à disposição. Att Tem tudo Shop
A13: =_xlfn.XLOOKUP(Follow[[#This Row],[CODRASTREIO]],Controle_Pedidos[Cód Rastreamento],Controle_Pedidos[Número Pedido Cliente]) -> Pedido 363 | B13: CódRastreio352 | C13: =Follow[[#This Row],[CODRASTREIO]]&" B" -> CódRastreio352 B | D13: =_xlfn.XLOOKUP(Follow[[#This Row],[Id Pedido]],Controle_Pedidos[Número Pedido Cliente],Controle_Pedidos[Loja]) -> BV | E13: =_xlfn.XLOOKUP(Follow[[#This Row],[Id Pedido]],Controle_Pedidos[Número Pedido Cliente],Controle_Pedidos[Prazo Entrega]) -> 45645 | F13: Transp 1 | G13: - | H13: China | I13: Brasil | J13: 45644 | K13: Entregue | L13: ENTREGUE | M13: Cliente Notificado | N13: =IF(Follow[[#This Row],[DATAATUALIZAÇÃO]]<=Follow[[#This Row],[Prev Entrega]],"Dentro do Prazo","Fora do Prazo") -> Dentro do Prazo | O13: =_xlfn.CONCAT("Olá ",PROPER(LOWER(TRIM(LEFT(SUBSTITUTE(_xlfn.XLOOKUP(Follow[[#This Row],[Id Pedido]],Controle_Pedidos[Número Pedido Cliente],Controle_Pedidos[NOME])," ",REPT(" ",100)),100)))),", Identificamos que o Item ",_xlfn.XLOOKUP(Follow[[#This Row],[Id Pedido]],Controle_Pedidos[Número Pedido Cliente],Controle_Pedidos[Nome Produto])," foi entregue no dia ",TEXT(Follow[[#This Row],[DATAATUALIZAÇÃO]],"dd/mm/aaaa"),", referente ao pedido Nº ",Follow[[#This Row],[Id Pedido]]," Rastreio ",IF(Follow[[#This Row],[Novo Cód de Rastreio]]="-",Follow[[#This Row],[Id Pedido]],Follow[[#This Row],[Novo Cód de Rastreio]]),", agradecemos a preferência e adoraríamos receber sua avaliação, tendo qualquer dúvida estamos à disposição.",_xlfn.IFS(Follow[[#This Row],[Loja]]="bv"," Att Tem tudo Shop",Follow[[#This Row],[Loja]]="mei"," Att NTA Variedades",Follow[[#This Row],[Loja]]="go"," Att Sec Variedades")) -> Olá Nome, Identificamos que o Item Ventilador Preto foi entregue no dia 18/12/2024, referente ao pedido Nº Pedido 363 Rastreio Pedido 363, agradecemos a preferência e adoraríamos receber sua avaliação, tendo qualquer dúvida estamos à disposição. Att Tem tudo Shop
A14: =_xlfn.XLOOKUP(Follow[[#This Row],[CODRASTREIO]],Controle_Pedidos[Cód Rastreamento],Controle_Pedidos[Número Pedido Cliente]) -> Pedido 543 | B14: CódRastreio528 | C14: =Follow[[#This Row],[CODRASTREIO]]&" B" -> CódRastreio528 B | D14: =_xlfn.XLOOKUP(Follow[[#This Row],[Id Pedido]],Controle_Pedidos[Número Pedido Cliente],Controle_Pedidos[Loja]) -> BV | E14: =_xlfn.XLOOKUP(Follow[[#This Row],[Id Pedido]],Controle_Pedidos[Número Pedido Cliente],Controle_Pedidos[Prazo Entrega]) -> 45665 | F14: Transp 1 | G14: - | H14: Brasil | I14: Brasil | J14: 45679 | K14: Entregue | L14: ENTREGUE | M14: - | N14: =IF(Follow[[#This Row],[DATAATUALIZAÇÃO]]<=Follow[[#This Row],[Prev Entrega]],"Dentro do Prazo","Fora do Prazo") -> Fora do Prazo | O14: =_xlfn.CONCAT("Olá ",PROPER(LOWER(TRIM(LEFT(SUBSTITUTE(_xlfn.XLOOKUP(Follow[[#This Row],[Id Pedido]],Controle_Pedidos[Número Pedido Cliente],Controle_Pedidos[NOME])," ",REPT(" ",100)),100)))),", Identificamos que o Item ",_xlfn.XLOOKUP(Follow[[#This Row],[Id Pedido]],Controle_Pedidos[Número Pedido Cliente],Controle_Pedidos[Nome Produto])," foi entregue no dia ",TEXT(Follow[[#This Row],[DATAATUALIZAÇÃO]],"dd/mm/aaaa"),", referente ao pedido Nº ",Follow[[#This Row],[Id Pedido]]," Rastreio ",IF(Follow[[#This Row],[Novo Cód de Rastreio]]="-",Follow[[#This Row],[Id Pedido]],Follow[[#This Row],[Novo Cód de Rastreio]]),", agradecemos a preferência e adoraríamos receber sua avaliação, tendo qualquer dúvida estamos à disposição.",_xlfn.IFS(Follow[[#This Row],[Loja]]="bv"," Att Tem tudo Shop",Follow[[#This Row],[Loja]]="mei"," Att NTA Variedades",Follow[[#This Row],[Loja]]="go"," Att Sec Variedades")) -> Olá Nome, Identificamos que o Item Suporte de Celular Branco foi entregue no dia 22/01/2025, referente ao pedido Nº Pedido 543 Rastreio Pedido 543, agradecemos a preferência e adoraríamos receber sua avaliação, tendo qualquer dúvida estamos à disposição. Att Tem tudo Shop
A15: =_xlfn.XLOOKUP(Follow[[#This Row],[CODRASTREIO]],Controle_Pedidos[Cód Rastreamento],Controle_Pedidos[Número Pedido Cliente]) -> Pedido 560 | B15: CódRastreio545 | C15: =Follow[[#This Row],[CODRASTREIO]]&" B" -> CódRastreio545 B | D15: =_xlfn.XLOOKUP(Follow[[#This Row],[Id Pedido]],Controle_Pedidos[Número Pedido Cliente],Controle_Pedidos[Loja]) -> BV | E15: =_xlfn.XLOOKUP(Follow[[#This Row],[Id Pedido]],Controle_Pedidos[Número Pedido Cliente],Controle_Pedidos[Prazo Entrega]) -> 45666 | F15: Transp 1 | G15: - | H15: China | I15: Brasil | J15: 45645 | K15: Entregue | L15: ENTREGUE | M15: Aguardando reembolso | N15: =IF(Follow[[#This Row],[DATAATUALIZAÇÃO]]<=Follow[[#This Row],[Prev Entrega]],"Dentro do Prazo","Fora do Prazo") -> Dentro do Prazo | O15: =_xlfn.CONCAT("Olá ",PROPER(LOWER(TRIM(LEFT(SUBSTITUTE(_xlfn.XLOOKUP(Follow[[#This Row],[Id Pedido]],Controle_Pedidos[Número Pedido Cliente],Controle_Pedidos[NOME])," ",REPT(" ",100)),100)))),", Identificamos que o Item ",_xlfn.XLOOKUP(Follow[[#This Row],[Id Pedido]],Controle_Pedidos[Número Pedido Cliente],Controle_Pedidos[Nome Produto])," foi entregue no dia ",TEXT(Follow[[#This Row],[DATAATUALIZAÇÃO]],"dd/mm/aaaa"),", referente ao pedido Nº ",Follow[[#This Row],[Id Pedido]]," Rastreio ",IF(Follow[[#This Row],[Novo Cód de Rastreio]]="-",Follow[[#This Row],[Id Pedido]],Follow[[#This Row],[Novo Cód de Rastreio]]),", agradecemos a preferência e adoraríamos receber sua avaliação, tendo qualquer dúvida estamos à disposição.",_xlfn.IFS(Follow[[#This Row],[Loja]]="bv"," Att Tem tudo Shop",Follow[[#This Row],[Loja]]="mei"," Att NTA Variedades",Follow[[#This Row],[Loja]]="go"," Att Sec Variedades")) -> Olá Nome, Identificamos que o Item Ventilador Rosa foi entregue no dia 19/12/2024, referente ao pedido Nº Pedido 560 Rastreio Pedido 560, agradecemos a preferência e adoraríamos receber sua avaliação, tendo qualquer dúvida estamos à disposição. Att Tem tudo Shop
A16: =_xlfn.XLOOKUP(Follow[[#This Row],[CODRASTREIO]],Controle_Pedidos[Cód Rastreamento],Controle_Pedidos[Número Pedido Cliente]) -> Pedido 574 | B16: CódRastreio559 | C16: =Follow[[#This Row],[CODRASTREIO]]&" B" -> CódRastreio559 B | D16: =_xlfn.XLOOKUP(Follow[[#This Row],[Id Pedido]],Controle_Pedidos[Número Pedido Cliente],Controle_Pedidos[Loja]) -> BV | E16: =_xlfn.XLOOKUP(Follow[[#This Row],[Id Pedido]],Controle_Pedidos[Número Pedido Cliente],Controle_Pedidos[Prazo Entrega]) -> 45666 | F16: Transp 1 | G16: - | H16: China | I16: Brasil | J16: 45646 | K16: Entregue | L16: ENTREGUE | M16: - | N16: =IF(Follow[[#This Row],[DATAATUALIZAÇÃO]]<=Follow[[#This Row],[Prev Entrega]],"Dentro do Prazo","Fora do Prazo") -> Dentro do Prazo | O16: =_xlfn.CONCAT("Olá ",PROPER(LOWER(TRIM(LEFT(SUBSTITUTE(_xlfn.XLOOKUP(Follow[[#This Row],[Id Pedido]],Controle_Pedidos[Número Pedido Cliente],Controle_Pedidos[NOME])," ",REPT(" ",100)),100)))),", Identificamos que o Item ",_xlfn.XLOOKUP(Follow[[#This Row],[Id Pedido]],Controle_Pedidos[Número Pedido Cliente],Controle_Pedidos[Nome Produto])," foi entregue no dia ",TEXT(Follow[[#This Row],[DATAATUALIZAÇÃO]],"dd/mm/aaaa"),", referente ao pedido Nº ",Follow[[#This Row],[Id Pedido]]," Rastreio ",IF(Follow[[#This Row],[Novo Cód de Rastreio]]="-",Follow[[#This Row],[Id Pedido]],Follow[[#This Row],[Novo Cód de Rastreio]]),", agradecemos a preferência e adoraríamos receber sua avaliação, tendo qualquer dúvida estamos à disposição.",_xlfn.IFS(Follow[[#This Row],[Loja]]="bv"," Att Tem tudo Shop",Follow[[#This Row],[Loja]]="mei"," Att NTA Variedades",Follow[[#This Row],[Loja]]="go"," Att Sec Variedades")) -> Olá Nome, Identificamos que o Item Ventilador Preto foi entregue no dia 20/12/2024, referente ao pedido Nº Pedido 574 Rastreio Pedido 574, agradecemos a preferência e adoraríamos receber sua avaliação, tendo qualquer dúvida estamos à disposição. Att Tem tudo Shop
A17: =_xlfn.XLOOKUP(Follow[[#This Row],[CODRASTREIO]],Controle_Pedidos[Cód Rastreamento],Controle_Pedidos[Número Pedido Cliente]) -> Pedido 555 | B17: CódRastreio540 | C17: =Follow[[#This Row],[CODRASTREIO]]&" B" -> CódRastreio540 B | D17: =_xlfn.XLOOKUP(Follow[[#This Row],[Id Pedido]],Controle_Pedidos[Número Pedido Cliente],Controle_Pedidos[Loja]) -> BV | E17: =_xlfn.XLOOKUP(Follow[[#This Row],[Id Pedido]],Controle_Pedidos[Número Pedido Cliente],Controle_Pedidos[Prazo Entrega]) -> 45666 | F17: Transp 1 | G17: - | H17: China | I17: Brasil | J17: 45664 | K17: Entregue | L17: ENTREGUE | M17: Aguardando reembolso | N17: =IF(Follow[[#This Row],[DATAATUALIZAÇÃO]]<=Follow[[#This Row],[Prev Entrega]],"Dentro do Prazo","Fora do Prazo") -> Dentro do Prazo | O17: =_xlfn.CONCAT("Olá ",PROPER(LOWER(TRIM(LEFT(SUBSTITUTE(_xlfn.XLOOKUP(Follow[[#This Row],[Id Pedido]],Controle_Pedidos[Número Pedido Cliente],Controle_Pedidos[NOME])," ",REPT(" ",100)),100)))),", Identificamos que o Item ",_xlfn.XLOOKUP(Follow[[#This Row],[Id Pedido]],Controle_Pedidos[Número Pedido Cliente],Controle_Pedidos[Nome Produto])," foi entregue no dia ",TEXT(Follow[[#This Row],[DATAATUALIZAÇÃO]],"dd/mm/aaaa"),", referente ao pedido Nº ",Follow[[#This Row],[Id Pedido]]," Rastreio ",IF(Follow[[#This Row],[Novo Cód de Rastreio]]="-",Follow[[#This Row],[Id Pedido]],Follow[[#This Row],[Novo Cód de Rastreio]]),", agradecemos a preferência e adoraríamos receber sua avaliação, tendo qualquer dúvida estamos à disposição.",_xlfn.IFS(Follow[[#This Row],[Loja]]="bv"," Att Tem tudo Shop",Follow[[#This Row],[Loja]]="mei"," Att NTA Variedades",Follow[[#This Row],[Loja]]="go"," Att Sec Variedades")) -> Olá Nome, Identificamos que o Item Ventilador de teto foi entregue no dia 07/01/2025, referente ao pedido Nº Pedido 555 Rastreio Pedido 555, agradecemos a preferência e adoraríamos receber sua avaliação, tendo qualquer dúvida estamos à disposição. Att Tem tudo Shop
A18: =_xlfn.XLOOKUP(Follow[[#This Row],[CODRASTREIO]],Controle_Pedidos[Cód Rastreamento],Controle_Pedidos[Número Pedido Cliente]) -> Pedido 597 | B18: CódRastreio582 | C18: =Follow[[#This Row],[CODRASTREIO]]&" B" -> CódRastreio582 B | D18: =_xlfn.XLOOKUP(Follow[[#This Row],[Id Pedido]],Controle_Pedidos[Número Pedido Cliente],Controle_Pedidos[Loja]) -> BV | E18: =_xlfn.XLOOKUP(Follow[[#This Row],[Id Pedido]],Controle_Pedidos[Número Pedido Cliente],Controle_Pedidos[Prazo Entrega]) -> 45686 | F18: Transp 1 | G18: - | H18: China | I18: Brasil | J18: 45692 | K18: Entregue | L18: ENTREGUE | M18: - | N18: =IF(Follow[[#This Row],[DATAATUALIZAÇÃO]]<=Follow[[#This Row],[Prev Entrega]],"Dentro do Prazo","Fora do Prazo") -> Fora do Prazo | O18: =_xlfn.CONCAT("Olá ",PROPER(LOWER(TRIM(LEFT(SUBSTITUTE(_xlfn.XLOOKUP(Follow[[#This Row],[Id Pedido]],Controle_Pedidos[Número Pedido Cliente],Controle_Pedidos[NOME])," ",REPT(" ",100)),100)))),", Identificamos que o Item ",_xlfn.XLOOKUP(Follow[[#This Row],[Id Pedido]],Controle_Pedidos[Número Pedido Cliente],Controle_Pedidos[Nome Produto])," foi entregue no dia ",TEXT(Follow[[#This Row],[DATAATUALIZAÇÃO]],"dd/mm/aaaa"),", referente ao pedido Nº ",Follow[[#This Row],[Id Pedido]]," Rastreio ",IF(Follow[[#This Row],[Novo Cód de Rastreio]]="-",Follow[[#This Row],[Id Pedido]],Follow[[#This Row],[Novo Cód de Rastreio]]),", agradecemos a preferência e adoraríamos receber sua avaliação, tendo qualquer dúvida estamos à disposição.",_xlfn.IFS(Follow[[#This Row],[Loja]]="bv"," Att Tem tudo Shop",Follow[[#This Row],[Loja]]="mei"," Att NTA Variedades",Follow[[#This Row],[Loja]]="go"," Att Sec Variedades")) -> Olá Nome, Identificamos que o Item Ventilador Preto foi entregue no dia 04/02/2025, referente ao pedido Nº Pedido 597 Rastreio Pedido 597, agradecemos a preferência e adoraríamos receber sua avaliação, tendo qualquer dúvida estamos à disposição. Att Tem tudo Shop | R18: Olá Nome, Identificamos que o Item Ventilador Preto foi entregue no dia 18/12/2024, referente ao pedido Nº Pedido 363 Rastreio CódRastreio352, agradecemos a preferência e adoraríamos receber sua avaliação, tendo qualquer dúvida estamos à disposição. Att Tem tudo Shop
A19: =_xlfn.XLOOKUP(Follow[[#This Row],[CODRASTREIO]],Controle_Pedidos[Cód Rastreamento],Controle_Pedidos[Número Pedido Cliente]) -> Pedido 611 | B19: CódRastreio594 | C19: =Follow[[#This Row],[CODRASTREIO]]&" B" -> CódRastreio594 B | D19: =_xlfn.XLOOKUP(Follow[[#This Row],[Id Pedido]],Controle_Pedidos[Número Pedido Cliente],Controle_Pedidos[Loja]) -> BV | E19: =_xlfn.XLOOKUP(Follow[[#This Row],[Id Pedido]],Controle_Pedidos[Número Pedido Cliente],Controle_Pedidos[Prazo Entrega]) -> 45686 | F19: Transp 1 | G19: - | H19: China | I19: Brasil | J19: 45686 | K19: Entregue | L19: ENTREGUE | M19: - | N19: =IF(Follow[[#This Row],[DATAATUALIZAÇÃO]]<=Follow[[#This Row],[Prev Entrega]],"Dentro do Prazo","Fora do Prazo") -> Dentro do Prazo | O19: =_xlfn.CONCAT("Olá ",PROPER(LOWER(TRIM(LEFT(SUBSTITUTE(_xlfn.XLOOKUP(Follow[[#This Row],[Id Pedido]],Controle_Pedidos[Número Pedido Cliente],Controle_Pedidos[NOME])," ",REPT(" ",100)),100)))),", Identificamos que o Item ",_xlfn.XLOOKUP(Follow[[#This Row],[Id Pedido]],Controle_Pedidos[Número Pedido Cliente],Controle_Pedidos[Nome Produto])," foi entregue no dia ",TEXT(Follow[[#This Row],[DATAATUALIZAÇÃO]],"dd/mm/aaaa"),", referente ao pedido Nº ",Follow[[#This Row],[Id Pedido]]," Rastreio ",IF(Follow[[#This Row],[Novo Cód de Rastreio]]="-",Follow[[#This Row],[Id Pedido]],Follow[[#This Row],[Novo Cód de Rastreio]]),", agradecemos a preferência e adoraríamos receber sua avaliação, tendo qualquer dúvida estamos à disposição.",_xlfn.IFS(Follow[[#This Row],[Loja]]="bv"," Att Tem tudo Shop",Follow[[#This Row],[Loja]]="mei"," Att NTA Variedades",Follow[[#This Row],[Loja]]="go"," Att Sec Variedades")) -> Olá Nome, Identificamos que o Item Ventilador Preto foi entregue no dia 29/01/2025, referente ao pedido Nº Pedido 611 Rastreio Pedido 611, agradecemos a preferência e adoraríamos receber sua avaliação, tendo qualquer dúvida estamos à disposição. Att Tem tudo Shop
A20: =_xlfn.XLOOKUP(Follow[[#This Row],[CODRASTREIO]],Controle_Pedidos[Cód Rastreamento],Controle_Pedidos[Número Pedido Cliente]) -> Pedido 632 | B20: CódRastreio614 | C20: =Follow[[#This Row],[CODRASTREIO]]&" B" -> CódRastreio614 B | D20: =_xlfn.XLOOKUP(Follow[[#This Row],[Id Pedido]],Controle_Pedidos[Número Pedido Cliente],Controle_Pedidos[Loja]) -> BV | E20: =_xlfn.XLOOKUP(Follow[[#This Row],[Id Pedido]],Controle_Pedidos[Número Pedido Cliente],Controle_Pedidos[Prazo Entrega]) -> 45688 | F20: Transp 1 | G20: - | H20: China | I20: Brasil | J20: 45674 | K20: Entregue | L20: ENTREGUE | M20: - | N20: =IF(Follow[[#This Row],[DATAATUALIZAÇÃO]]<=Follow[[#This Row],[Prev Entrega]],"Dentro do Prazo","Fora do Prazo") -> Dentro do Prazo | O20: =_xlfn.CONCAT("Olá ",PROPER(LOWER(TRIM(LEFT(SUBSTITUTE(_xlfn.XLOOKUP(Follow[[#This Row],[Id Pedido]],Controle_Pedidos[Número Pedido Cliente],Controle_Pedidos[NOME])," ",REPT(" ",100)),100)))),", Identificamos que o Item ",_xlfn.XLOOKUP(Follow[[#This Row],[Id Pedido]],Controle_Pedidos[Número Pedido Cliente],Controle_Pedidos[Nome Produto])," foi entregue no dia ",TEXT(Follow[[#This Row],[DATAATUALIZAÇÃO]],"dd/mm/aaaa"),", referente ao pedido Nº ",Follow[[#This Row],[Id Pedido]]," Rastreio ",IF(Follow[[#This Row],[Novo Cód de Rastreio]]="-",Follow[[#This Row],[Id Pedido]],Follow[[#This Row],[Novo Cód de Rastreio]]),", agradecemos a preferência e adoraríamos receber sua avaliação, tendo qualquer dúvida estamos à disposição.",_xlfn.IFS(Follow[[#This Row],[Loja]]="bv"," Att Tem tudo Shop",Follow[[#This Row],[Loja]]="mei"," Att NTA Variedades",Follow[[#This Row],[Loja]]="go"," Att Sec Variedades")) -> Olá Nome, Identificamos que o Item Ventilador Rosa foi entregue no dia 17/01/2025, referente ao pedido Nº Pedido 632 Rastreio Pedido 632, agradecemos a preferência e adoraríamos receber sua avaliação, tendo qualquer dúvida estamos à disposição. Att Tem tudo Shop
A21: =_xlfn.XLOOKUP(Follow[[#This Row],[CODRASTREIO]],Controle_Pedidos[Cód Rastreamento],Controle_Pedidos[Número Pedido Cliente]) -> Pedido 644 | B21: CódRastreio625 | C21: =Follow[[#This Row],[CODRASTREIO]]&" B" -> CódRastreio625 B | D21: =_xlfn.XLOOKUP(Follow[[#This Row],[Id Pedido]],Controle_Pedidos[Número Pedido Cliente],Controle_Pedidos[Loja]) -> BV | E21: =_xlfn.XLOOKUP(Follow[[#This Row],[Id Pedido]],Controle_Pedidos[Número Pedido Cliente],Controle_Pedidos[Prazo Entrega]) -> 45682 | F21: Transp 1 | G21: - | H21: Brasil | I21: Brasil | J21: 45673 | K21: Entregue | L21: ENTREGUE | M21: - | N21: =IF(Follow[[#This Row],[DATAATUALIZAÇÃO]]<=Follow[[#This Row],[Prev Entrega]],"Dentro do Prazo","Fora do Prazo") -> Dentro do Prazo | O21: =_xlfn.CONCAT("Olá ",PROPER(LOWER(TRIM(LEFT(SUBSTITUTE(_xlfn.XLOOKUP(Follow[[#This Row],[Id Pedido]],Controle_Pedidos[Número Pedido Cliente],Controle_Pedidos[NOME])," ",REPT(" ",100)),100)))),", Identificamos que o Item ",_xlfn.XLOOKUP(Follow[[#This Row],[Id Pedido]],Controle_Pedidos[Número Pedido Cliente],Controle_Pedidos[Nome Produto])," foi entregue no dia ",TEXT(Follow[[#This Row],[DATAATUALIZAÇÃO]],"dd/mm/aaaa"),", referente ao pedido Nº ",Follow[[#This Row],[Id Pedido]]," Rastreio ",IF(Follow[[#This Row],[Novo Cód de Rastreio]]="-",Follow[[#This Row],[Id Pedido]],Follow[[#This Row],[Novo Cód de Rastreio]]),", agradecemos a preferência e adoraríamos receber sua avaliação, tendo qualquer dúvida estamos à disposição.",_xlfn.IFS(Follow[[#This Row],[Loja]]="bv"," Att Tem tudo Shop",Follow[[#This Row],[Loja]]="mei"," Att NTA Variedades",Follow[[#This Row],[Loja]]="go"," Att Sec Variedades")) -> Olá Nome, Identificamos que o Item Adaptador Bluetooph foi entregue no dia 16/01/2025, referente ao pedido Nº Pedido 644 Rastreio Pedido 644, agradecemos a preferência e adoraríamos receber sua avaliação, tendo qualquer dúvida estamos à disposição. Att Tem tudo Shop
A22: =_xlfn.XLOOKUP(Follow[[#This Row],[CODRASTREIO]],Controle_Pedidos[Cód Rastreamento],Controle_Pedidos[Número Pedido Cliente]) -> Pedido 665 | B22: CódRastreio645 | C22: =Follow[[#This Row],[CODRASTREIO]]&" B" -> CódRastreio645 B | D22: =_xlfn.XLOOKUP(Follow[[#This Row],[Id Pedido]],Controle_Pedidos[Número Pedido Cliente],Controle_Pedidos[Loja]) -> BV | E22: =_xlfn.XLOOKUP(Follow[[#This Row],[Id Pedido]],Controle_Pedidos[Número Pedido Cliente],Controle_Pedidos[Prazo Entrega]) -> 45685 | F22: Transp 1 | G22: - | H22: China | I22: Brasil | J22: 45679 | K22: Entregue | L22: ENTREGUE | M22: - | N22: =IF(Follow[[#This Row],[DATAATUALIZAÇÃO]]<=Follow[[#This Row],[Prev Entrega]],"Dentro do Prazo","Fora do Prazo") -> Dentro do Prazo | O22: =_xlfn.CONCAT("Olá ",PROPER(LOWER(TRIM(LEFT(SUBSTITUTE(_xlfn.XLOOKUP(Follow[[#This Row],[Id Pedido]],Controle_Pedidos[Número Pedido Cliente],Controle_Pedidos[NOME])," ",REPT(" ",100)),100)))),", Identificamos que o Item ",_xlfn.XLOOKUP(Follow[[#This Row],[Id Pedido]],Controle_Pedidos[Número Pedido Cliente],Controle_Pedidos[Nome Produto])," foi entregue no dia ",TEXT(Follow[[#This Row],[DATAATUALIZAÇÃO]],"dd/mm/aaaa"),", referente ao pedido Nº ",Follow[[#This Row],[Id Pedido]]," Rastreio ",IF(Follow[[#This Row],[Novo Cód de Rastreio]]="-",Follow[[#This Row],[Id Pedido]],Follow[[#This Row],[Novo Cód de Rastreio]]),", agradecemos a preferência e adoraríamos receber sua avaliação, tendo qualquer dúvida estamos à disposição.",_xlfn.IFS(Follow[[#This Row],[Loja]]="bv"," Att Tem tudo Shop",Follow[[#This Row],[Loja]]="mei"," Att NTA Variedades",Follow[[#This Row],[Loja]]="go"," Att Sec Variedades")) -> Olá Nome, Identificamos que o Item Karaoke portátil foi entregue no dia 22/01/2025, referente ao pedido Nº Pedido 665 Rastreio Pedido 665, agradecemos a preferência e adoraríamos receber sua avaliação, tendo qualquer dúvida estamos à disposição. Att Tem tudo Shop
A23: =_xlfn.XLOOKUP(Follow[[#This Row],[CODRASTREIO]],Controle_Pedidos[Cód Rastreamento],Controle_Pedidos[Número Pedido Cliente]) -> Pedido 677 | B23: CódRastreio657 | C23: =Follow[[#This Row],[CODRASTREIO]]&" B" -> CódRastreio657 B | D23: =_xlfn.XLOOKUP(Follow[[#This Row],[Id Pedido]],Controle_Pedidos[Número Pedido Cliente],Controle_Pedidos[Loja]) -> BV | E23: =_xlfn.XLOOKUP(Follow[[#This Row],[Id Pedido]],Controle_Pedidos[Número Pedido Cliente],Controle_Pedidos[Prazo Entrega]) -> 45686 | F23: Transp 1 | G23: - | H23: Brasil | I23: Brasil | J23: 45673 | K23: Entregue | L23: ENTREGUE | M23: - | N23: =IF(Follow[[#This Row],[DATAATUALIZAÇÃO]]<=Follow[[#This Row],[Prev Entrega]],"Dentro do Prazo","Fora do Prazo") -> Dentro do Prazo | O23: =_xlfn.CONCAT("Olá ",PROPER(LOWER(TRIM(LEFT(SUBSTITUTE(_xlfn.XLOOKUP(Follow[[#This Row],[Id Pedido]],Controle_Pedidos[Número Pedido Cliente],Controle_Pedidos[NOME])," ",REPT(" ",100)),100)))),", Identificamos que o Item ",_xlfn.XLOOKUP(Follow[[#This Row],[Id Pedido]],Controle_Pedidos[Número Pedido Cliente],Controle_Pedidos[Nome Produto])," foi entregue no dia ",TEXT(Follow[[#This Row],[DATAATUALIZAÇÃO]],"dd/mm/aaaa"),", referente ao pedido Nº ",Follow[[#This Row],[Id Pedido]]," Rastreio ",IF(Follow[[#This Row],[Novo Cód de Rastreio]]="-",Follow[[#This Row],[Id Pedido]],Follow[[#This Row],[Novo Cód de Rastreio]]),", agradecemos a preferência e adoraríamos receber sua avaliação, tendo qualquer dúvida estamos à disposição.",_xlfn.IFS(Follow[[#This Row],[Loja]]="bv"," Att Tem tudo Shop",Follow[[#This Row],[Loja]]="mei"," Att NTA Variedades",Follow[[#This Row],[Loja]]="go"," Att Sec Variedades")) -> Olá Nome, Identificamos que o Item Adaptador Bluetooph foi entregue no dia 16/01/2025, referente ao pedido Nº Pedido 677 Rastreio Pedido 677, agradecemos a preferência e adoraríamos receber sua avaliação, tendo qualquer dúvida estamos à disposição. Att Tem tudo Shop
A24: =_xlfn.XLOOKUP(Follow[[#This Row],[CODRASTREIO]],Controle_Pedidos[Cód Rastreamento],Controle_Pedidos[Número Pedido Cliente]) -> Pedido 680 | B24: CódRastreio660 | C24: =Follow[[#This Row],[CODRASTREIO]]&" B" -> CódRastreio660 B | D24: =_xlfn.XLOOKUP(Follow[[#This Row],[Id Pedido]],Controle_Pedidos[Número Pedido Cliente],Controle_Pedidos[Loja]) -> BV | E24: =_xlfn.XLOOKUP(Follow[[#This Row],[Id Pedido]],Controle_Pedidos[Número Pedido Cliente],Controle_Pedidos[Prazo Entrega]) -> 45686 | F24: Transp 1 | G24: - | H24: China | I24: Brasil | J24: 45673 | K24: Entregue | L24: ENTREGUE | M24: - | N24: =IF(Follow[[#This Row],[DATAATUALIZAÇÃO]]<=Follow[[#This Row],[Prev Entrega]],"Dentro do Prazo","Fora do Prazo") -> Dentro do Prazo | O24: =_xlfn.CONCAT("Olá ",PROPER(LOWER(TRIM(LEFT(SUBSTITUTE(_xlfn.XLOOKUP(Follow[[#This Row],[Id Pedido]],Controle_Pedidos[Número Pedido Cliente],Controle_Pedidos[NOME])," ",REPT(" ",100)),100)))),", Identificamos que o Item ",_xlfn.XLOOKUP(Follow[[#This Row],[Id Pedido]],Controle_Pedidos[Número Pedido Cliente],Controle_Pedidos[Nome Produto])," foi entregue no dia ",TEXT(Follow[[#This Row],[DATAATUALIZAÇÃO]],"dd/mm/aaaa"),", referente ao pedido Nº ",Follow[[#This Row],[Id Pedido]]," Rastreio ",IF(Follow[[#This Row],[Novo Cód de Rastreio]]="-",Follow[[#This Row],[Id Pedido]],Follow[[#This Row],[Novo Cód de Rastreio]]),", agradecemos a preferência e adoraríamos receber sua avaliação, tendo qualquer dúvida estamos à disposição.",_xlfn.IFS(Follow[[#This Row],[Loja]]="bv"," Att Tem tudo Shop",Follow[[#This Row],[Loja]]="mei"," Att NTA Variedades",Follow[[#This Row],[Loja]]="go"," Att Sec Variedades")) -> Olá Nome, Identificamos que o Item Ventilador Rosa foi entregue no dia 16/01/2025, referente ao pedido Nº Pedido 680 Rastreio Pedido 680, agradecemos a preferência e adoraríamos receber sua avaliação, tendo qualquer dúvida estamos à disposição. Att Tem tudo Shop
A25: =_xlfn.XLOOKUP(Follow[[#This Row],[CODRASTREIO]],Controle_Pedidos[Cód Rastreamento],Controle_Pedidos[Número Pedido Cliente]) -> Pedido 681 | B25: CódRastreio661 | C25: =Follow[[#This Row],[CODRASTREIO]]&" B" -> CódRastreio661 B | D25: =_xlfn.XLOOKUP(Follow[[#This Row],[Id Pedido]],Controle_Pedidos[Número Pedido Cliente],Controle_Pedidos[Loja]) -> BV | E25: =_xlfn.XLOOKUP(Follow[[#This Row],[Id Pedido]],Controle_Pedidos[Número Pedido Cliente],Controle_Pedidos[Prazo Entrega]) -> 45693 | F25: Transp 1 | G25: - | H25: China | I25: Brasil | J25: 45682 | K25: Entregue | L25: ENTREGUE | M25: - | N25: =IF(Follow[[#This Row],[DATAATUALIZAÇÃO]]<=Follow[[#This Row],[Prev Entrega]],"Dentro do Prazo","Fora do Prazo") -> Dentro do Prazo | O25: =_xlfn.CONCAT("Olá ",PROPER(LOWER(TRIM(LEFT(SUBSTITUTE(_xlfn.XLOOKUP(Follow[[#This Row],[Id Pedido]],Controle_Pedidos[Número Pedido Cliente],Controle_Pedidos[NOME])," ",REPT(" ",100)),100)))),", Identificamos que o Item ",_xlfn.XLOOKUP(Follow[[#This Row],[Id Pedido]],Controle_Pedidos[Número Pedido Cliente],Controle_Pedidos[Nome Produto])," foi entregue no dia ",TEXT(Follow[[#This Row],[DATAATUALIZAÇÃO]],"dd/mm/aaaa"),", referente ao pedido Nº ",Follow[[#This Row],[Id Pedido]]," Rastreio ",IF(Follow[[#This Row],[Novo Cód de Rastreio]]="-",Follow[[#This Row],[Id Pedido]],Follow[[#This Row],[Novo Cód de Rastreio]]),", agradecemos a preferência e adoraríamos receber sua avaliação, tendo qualquer dúvida estamos à disposição.",_xlfn.IFS(Follow[[#This Row],[Loja]]="bv"," Att Tem tudo Shop",Follow[[#This Row],[Loja]]="mei"," Att NTA Variedades",Follow[[#This Row],[Loja]]="go"," Att Sec Variedades")) -> Olá Nome, Identificamos que o Item Ventilador Preto foi entregue no dia 25/01/2025, referente ao pedido Nº Pedido 681 Rastreio Pedido 681, agradecemos a preferência e adoraríamos receber sua avaliação, tendo qualquer dúvida estamos à disposição. Att Tem tudo Shop
A26: =_xlfn.XLOOKUP(Follow[[#This Row],[CODRASTREIO]],Controle_Pedidos[Cód Rastreamento],Controle_Pedidos[Número Pedido Cliente]) -> Pedido 684 | B26: CódRastreio664 | C26: =Follow[[#This Row],[CODRASTREIO]]&" B" -> CódRastreio664 B | D26: =_xlfn.XLOOKUP(Follow[[#This Row],[Id Pedido]],Controle_Pedidos[Número Pedido Cliente],Controle_Pedidos[Loja]) -> BV | E26: =_xlfn.XLOOKUP(Follow[[#This Row],[Id Pedido]],Controle_Pedidos[Número Pedido Cliente],Controle_Pedidos[Prazo Entrega]) -> 45693 | F26: Transp 1 | G26: - | H26: China | I26: Brasil | J26: 45687 | K26: Entregue | L26: ENTREGUE | M26: - | N26: =IF(Follow[[#This Row],[DATAATUALIZAÇÃO]]<=Follow[[#This Row],[Prev Entrega]],"Dentro do Prazo","Fora do Prazo") -> Dentro do Prazo | O26: =_xlfn.CONCAT("Olá ",PROPER(LOWER(TRIM(LEFT(SUBSTITUTE(_xlfn.XLOOKUP(Follow[[#This Row],[Id Pedido]],Controle_Pedidos[Número Pedido Cliente],Controle_Pedidos[NOME])," ",REPT(" ",100)),100)))),", Identificamos que o Item ",_xlfn.XLOOKUP(Follow[[#This Row],[Id Pedido]],Controle_Pedidos[Número Pedido Cliente],Controle_Pedidos[Nome Produto])," foi entregue no dia ",TEXT(Follow[[#This Row],[DATAATUALIZAÇÃO]],"dd/mm/aaaa"),", referente ao pedido Nº ",Follow[[#This Row],[Id Pedido]]," Rastreio ",IF(Follow[[#This Row],[Novo Cód de Rastreio]]="-",Follow[[#This Row],[Id Pedido]],Follow[[#This Row],[Novo Cód de Rastreio]]),", agradecemos a preferência e adoraríamos receber sua avaliação, tendo qualquer dúvida estamos à disposição.",_xlfn.IFS(Follow[[#This Row],[Loja]]="bv"," Att Tem tudo Shop",Follow[[#This Row],[Loja]]="mei"," Att NTA Variedades",Follow[[#This Row],[Loja]]="go"," Att Sec Variedades")) -> Olá Nome, Identificamos que o Item Ventilador Preto foi entregue no dia 30/01/2025, referente ao pedido Nº Pedido 684 Rastreio Pedido 684, agradecemos a preferência e adoraríamos receber sua avaliação, tendo qualquer dúvida estamos à disposição. Att Tem tudo Shop
A27: =_xlfn.XLOOKUP(Follow[[#This Row],[CODRASTREIO]],Controle_Pedidos[Cód Rastreamento],Controle_Pedidos[Número Pedido Cliente]) -> Pedido 682 | B27: CódRastreio662 | C27: =Follow[[#This Row],[CODRASTREIO]]&" B" -> CódRastreio662 B | D27: =_xlfn.XLOOKUP(Follow[[#This Row],[Id Pedido]],Controle_Pedidos[Número Pedido Cliente],Controle_Pedidos[Loja]) -> BV | E27: =_xlfn.XLOOKUP(Follow[[#This Row],[Id Pedido]],Controle_Pedidos[Número Pedido Cliente],Controle_Pedidos[Prazo Entrega]) -> 45686 | F27: Transp 1 | G27: - | H27: China | I27: Brasil | J27: 45674 | K27: Entregue | L27: ENTREGUE | M27: - | N27: =IF(Follow[[#This Row],[DATAATUALIZAÇÃO]]<=Follow[[#This Row],[Prev Entrega]],"Dentro do Prazo","Fora do Prazo") -> Dentro do Prazo | O27: =_xlfn.CONCAT("Olá ",PROPER(LOWER(TRIM(LEFT(SUBSTITUTE(_xlfn.XLOOKUP(Follow[[#This Row],[Id Pedido]],Controle_Pedidos[Número Pedido Cliente],Controle_Pedidos[NOME])," ",REPT(" ",100)),100)))),", Identificamos que o Item ",_xlfn.XLOOKUP(Follow[[#This Row],[Id Pedido]],Controle_Pedidos[Número Pedido Cliente],Controle_Pedidos[Nome Produto])," foi entregue no dia ",TEXT(Follow[[#This Row],[DATAATUALIZAÇÃO]],"dd/mm/aaaa"),", referente ao pedido Nº ",Follow[[#This Row],[Id Pedido]]," Rastreio ",IF(Follow[[#This Row],[Novo Cód de Rastreio]]="-",Follow[[#This Row],[Id Pedido]],Follow[[#This Row],[Novo Cód de Rastreio]]),", agradecemos a preferência e adoraríamos receber sua avaliação, tendo qualquer dúvida estamos à disposição.",_xlfn.IFS(Follow[[#This Row],[Loja]]="bv"," Att Tem tudo Shop",Follow[[#This Row],[Loja]]="mei"," Att NTA Variedades",Follow[[#This Row],[Loja]]="go"," Att Sec Variedades")) -> Olá Nome, Identificamos que o Item Karaoke portátil foi entregue no dia 17/01/2025, referente ao pedido Nº Pedido 682 Rastreio Pedido 682, agradecemos a preferência e adoraríamos receber sua avaliação, tendo qualquer dúvida estamos à disposição. Att Tem tudo Shop
A28: =_xlfn.XLOOKUP(Follow[[#This Row],[CODRASTREIO]],Controle_Pedidos[Cód Rastreamento],Controle_Pedidos[Número Pedido Cliente]) -> Pedido 686 | B28: CódRastreio666 | C28: =Follow[[#This Row],[CODRASTREIO]]&" B" -> CódRastreio666 B | D28: =_xlfn.XLOOKUP(Follow[[#This Row],[Id Pedido]],Controle_Pedidos[Número Pedido Cliente],Controle_Pedidos[Loja]) -> BV | E28: =_xlfn.XLOOKUP(Follow[[#This Row],[Id Pedido]],Controle_Pedidos[Número Pedido Cliente],Controle_Pedidos[Prazo Entrega]) -> 45686 | F28: Transp 1 | G28: - | H28: China | I28: Brasil | J28: 45677 | K28: Entregue | L28: ENTREGUE | M28: - | N28: =IF(Follow[[#This Row],[DATAATUALIZAÇÃO]]<=Follow[[#This Row],[Prev Entrega]],"Dentro do Prazo","Fora do Prazo") -> Dentro do Prazo | O28: =_xlfn.CONCAT("Olá ",PROPER(LOWER(TRIM(LEFT(SUBSTITUTE(_xlfn.XLOOKUP(Follow[[#This Row],[Id Pedido]],Controle_Pedidos[Número Pedido Cliente],Controle_Pedidos[NOME])," ",REPT(" ",100)),100)))),", Identificamos que o Item ",_xlfn.XLOOKUP(Follow[[#This Row],[Id Pedido]],Controle_Pedidos[Número Pedido Cliente],Controle_Pedidos[Nome Produto])," foi entregue no dia ",TEXT(Follow[[#This Row],[DATAATUALIZAÇÃO]],"dd/mm/aaaa"),", referente ao pedido Nº ",Follow[[#This Row],[Id Pedido]]," Rastreio ",IF(Follow[[#This Row],[Novo Cód de Rastreio]]="-",Follow[[#This Row],[Id Pedido]],Follow[[#This Row],[Novo Cód de Rastreio]]),", agradecemos a preferência e adoraríamos receber sua avaliação, tendo qualquer dúvida estamos à disposição.",_xlfn.IFS(Follow[[#This Row],[Loja]]="bv"," Att Tem tudo Shop",Follow[[#This Row],[Loja]]="mei"," Att NTA Variedades",Follow[[#This Row],[Loja]]="go"," Att Sec Variedades")) -> Olá Nome, Identificamos que o Item Ventilador Rosa foi entregue no dia 20/01/2025, referente ao pedido Nº Pedido 686 Rastreio Pedido 686, agradecemos a preferência e adoraríamos receber sua avaliação, tendo qualquer dúvida estamos à disposição. Att Tem tudo Shop
A29: =_xlfn.XLOOKUP(Follow[[#This Row],[CODRASTREIO]],Controle_Pedidos[Cód Rastreamento],Controle_Pedidos[Número Pedido Cliente]) -> Pedido 687 | B29: CódRastreio667 | C29: =Follow[[#This Row],[CODRASTREIO]]&" B" -> CódRastreio667 B | D29: =_xlfn.XLOOKUP(Follow[[#This Row],[Id Pedido]],Controle_Pedidos[Número Pedido Cliente],Controle_Pedidos[Loja]) -> BV | E29: =_xlfn.XLOOKUP(Follow[[#This Row],[Id Pedido]],Controle_Pedidos[Número Pedido Cliente],Controle_Pedidos[Prazo Entrega]) -> 45687 | F29: Transp 1 | G29: - | H29: China | I29: Brasil | J29: 45677 | K29: Entregue | L29: ENTREGUE | M29: - | N29: =IF(Follow[[#This Row],[DATAATUALIZAÇÃO]]<=Follow[[#This Row],[Prev Entrega]],"Dentro do Prazo","Fora do Prazo") -> Dentro do Prazo | O29: =_xlfn.CONCAT("Olá ",PROPER(LOWER(TRIM(LEFT(SUBSTITUTE(_xlfn.XLOOKUP(Follow[[#This Row],[Id Pedido]],Controle_Pedidos[Número Pedido Cliente],Controle_Pedidos[NOME])," ",REPT(" ",100)),100)))),", Identificamos que o Item ",_xlfn.XLOOKUP(Follow[[#This Row],[Id Pedido]],Controle_Pedidos[Número Pedido Cliente],Controle_Pedidos[Nome Produto])," foi entregue no dia ",TEXT(Follow[[#This Row],[DATAATUALIZAÇÃO]],"dd/mm/aaaa"),", referente ao pedido Nº ",Follow[[#This Row],[Id Pedido]]," Rastreio ",IF(Follow[[#This Row],[Novo Cód de Rastreio]]="-",Follow[[#This Row],[Id Pedido]],Follow[[#This Row],[Novo Cód de Rastreio]]),", agradecemos a preferência e adoraríamos receber sua avaliação, tendo qualquer dúvida estamos à disposição.",_xlfn.IFS(Follow[[#This Row],[Loja]]="bv"," Att Tem tudo Shop",Follow[[#This Row],[Loja]]="mei"," Att NTA Variedades",Follow[[#This Row],[Loja]]="go"," Att Sec Variedades")) -> Olá Nome, Identificamos que o Item Ventilador Preto foi entregue no dia 20/01/2025, referente ao pedido Nº Pedido 687 Rastreio Pedido 687, agradecemos a preferência e adoraríamos receber sua avaliação, tendo qualquer dúvida estamos à disposição. Att Tem tudo Shop
A30: =_xlfn.XLOOKUP(Follow[[#This Row],[CODRASTREIO]],Controle_Pedidos[Cód Rastreamento],Controle_Pedidos[Número Pedido Cliente]) -> Pedido 691 | B30: CódRastreio671 | C30: =Follow[[#This Row],[CODRASTREIO]]&" B" -> CódRastreio671 B | D30: =_xlfn.XLOOKUP(Follow[[#This Row],[Id Pedido]],Controle_Pedidos[Número Pedido Cliente],Controle_Pedidos[Loja]) -> BV | E30: =_xlfn.XLOOKUP(Follow[[#This Row],[Id Pedido]],Controle_Pedidos[Número Pedido Cliente],Controle_Pedidos[Prazo Entrega]) -> 45687 | F30: Transp 1 | G30: - | H30: China | I30: Brasil | J30: 45678 | K30: Entregue | L30: ENTREGUE | M30: Cliente Notificado | N30: =IF(Follow[[#This Row],[DATAATUALIZAÇÃO]]<=Follow[[#This Row],[Prev Entrega]],"Dentro do Prazo","Fora do Prazo") -> Dentro do Prazo | O30: =_xlfn.CONCAT("Olá ",PROPER(LOWER(TRIM(LEFT(SUBSTITUTE(_xlfn.XLOOKUP(Follow[[#This Row],[Id Pedido]],Controle_Pedidos[Número Pedido Cliente],Controle_Pedidos[NOME])," ",REPT(" ",100)),100)))),", Identificamos que o Item ",_xlfn.XLOOKUP(Follow[[#This Row],[Id Pedido]],Controle_Pedidos[Número Pedido Cliente],Controle_Pedidos[Nome Produto])," foi entregue no dia ",TEXT(Follow[[#This Row],[DATAATUALIZAÇÃO]],"dd/mm/aaaa"),", referente ao pedido Nº ",Follow[[#This Row],[Id Pedido]]," Rastreio ",IF(Follow[[#This Row],[Novo Cód de Rastreio]]="-",Follow[[#This Row],[Id Pedido]],Follow[[#This Row],[Novo Cód de Rastreio]]),", agradecemos a preferência e adoraríamos receber sua avaliação, tendo qualquer dúvida estamos à disposição.",_xlfn.IFS(Follow[[#This Row],[Loja]]="bv"," Att Tem tudo Shop",Follow[[#This Row],[Loja]]="mei"," Att NTA Variedades",Follow[[#This Row],[Loja]]="go"," Att Sec Variedades")) -> Olá Nome, Identificamos que o Item Ventilador Rosa foi entregue no dia 21/01/2025, referente ao pedido Nº Pedido 691 Rastreio Pedido 691, agradecemos a preferência e adoraríamos receber sua avaliação, tendo qualquer dúvida estamos à disposição. Att Tem tudo Shop
... A252: =_xlfn.XLOOKUP(Follow[[#This Row],[CODRASTREIO]],Controle_Pedidos[Cód Rastreamento],Controle_Pedidos[Número Pedido Cliente]) -> Pedido 70 | B252: CódRastreio61 | C252: =Follow[[#This Row],[CODRASTREIO]]&" B" -> CódRastreio61 B | D252: =_xlfn.XLOOKUP(Follow[[#This Row],[Id Pedido]],Controle_Pedidos[Número Pedido Cliente],Controle_Pedidos[Loja]) -> BV | E252: =_xlfn.XLOOKUP(Follow[[#This Row],[Id Pedido]],Controle_Pedidos[Número Pedido Cliente],Controle_Pedidos[Prazo Entrega]) -> 45603 | F252: Transp 1 | G252: - | H252: Brasil | I252: Brasil | J252: 45594 | K252: Entregue | L252: ENTREGUE | M252: - | N252: =IF(Follow[[#This Row],[DATAATUALIZAÇÃO]]<=Follow[[#This Row],[Prev Entrega]],"Dentro do Prazo","Fora do Prazo") -> Dentro do Prazo | O252: =_xlfn.CONCAT("Olá ",PROPER(LOWER(TRIM(LEFT(SUBSTITUTE(_xlfn.XLOOKUP(Follow[[#This Row],[Id Pedido]],Controle_Pedidos[Número Pedido Cliente],Controle_Pedidos[NOME])," ",REPT(" ",100)),100)))),", Identificamos que o Item ",_xlfn.XLOOKUP(Follow[[#This Row],[Id Pedido]],Controle_Pedidos[Número Pedido Cliente],Controle_Pedidos[Nome Produto])," foi entregue no dia ",TEXT(Follow[[#This Row],[DATAATUALIZAÇÃO]],"dd/mm/aaaa"),", referente ao pedido Nº ",Follow[[#This Row],[Id Pedido]]," Rastreio ",IF(Follow[[#This Row],[Novo Cód de Rastreio]]="-",Follow[[#This Row],[Id Pedido]],Follow[[#This Row],[Novo Cód de Rastreio]]),", agradecemos a preferência e adoraríamos receber sua avaliação, tendo qualquer dúvida estamos à disposição.",_xlfn.IFS(Follow[[#This Row],[Loja]]="bv"," Att Tem tudo Shop",Follow[[#This Row],[Loja]]="mei"," Att NTA Variedades",Follow[[#This Row],[Loja]]="go"," Att Sec Variedades")) -> Olá Nome, Identificamos que o Item Suporte de Celular Branco foi entregue no dia 29/10/2024, referente ao pedido Nº Pedido 70 Rastreio Pedido 70, agradecemos a preferência e adoraríamos receber sua avaliação, tendo qualquer dúvida estamos à disposição. Att Tem tudo Shop
A253: Pedido 426 | B253: CódRastreio413 1 envio | C253: =Follow[[#This Row],[CODRASTREIO]]&" B" -> CódRastreio413 1 envio B | D253: BV | E253: 45645 | F253: Transp 1 | G253: - | H253: Brasil | I253: Brasil | J253: 45629 | K253: Entregue | L253: ENTREGUE | M253: - | N253: =IF(Follow[[#This Row],[DATAATUALIZAÇÃO]]<=Follow[[#This Row],[Prev Entrega]],"Dentro do Prazo","Fora do Prazo") -> Dentro do Prazo | O253: =_xlfn.CONCAT("Olá ",PROPER(LOWER(TRIM(LEFT(SUBSTITUTE(_xlfn.XLOOKUP(Follow[[#This Row],[Id Pedido]],Controle_Pedidos[Número Pedido Cliente],Controle_Pedidos[NOME])," ",REPT(" ",100)),100)))),", Identificamos que o Item ",_xlfn.XLOOKUP(Follow[[#This Row],[Id Pedido]],Controle_Pedidos[Número Pedido Cliente],Controle_Pedidos[Nome Produto])," foi entregue no dia ",TEXT(Follow[[#This Row],[DATAATUALIZAÇÃO]],"dd/mm/aaaa"),", referente ao pedido Nº ",Follow[[#This Row],[Id Pedido]]," Rastreio ",IF(Follow[[#This Row],[Novo Cód de Rastreio]]="-",Follow[[#This Row],[Id Pedido]],Follow[[#This Row],[Novo Cód de Rastreio]]),", agradecemos a preferência e adoraríamos receber sua avaliação, tendo qualquer dúvida estamos à disposição.",_xlfn.IFS(Follow[[#This Row],[Loja]]="bv"," Att Tem tudo Shop",Follow[[#This Row],[Loja]]="mei"," Att NTA Variedades",Follow[[#This Row],[Loja]]="go"," Att Sec Variedades")) -> Olá Nome, Identificamos que o Item Adaptador Bluetooph foi entregue no dia 03/12/2024, referente ao pedido Nº Pedido 426 Rastreio Pedido 426, agradecemos a preferência e adoraríamos receber sua avaliação, tendo qualquer dúvida estamos à disposição. Att Tem tudo Shop
A254: Pedido 426 | B254: CódRastreio413 2 Envio | C254: =Follow[[#This Row],[CODRASTREIO]]&" B" -> CódRastreio413 2 Envio B | D254: BV | E254: 45645 | F254: Transp 1 | G254: - | H254: Brasil | I254: Brasil | J254: 45629 | K254: Entregue | L254: ENTREGUE | M254: - | N254: =IF(Follow[[#This Row],[DATAATUALIZAÇÃO]]<=Follow[[#This Row],[Prev Entrega]],"Dentro do Prazo","Fora do Prazo") -> Dentro do Prazo | O254: =_xlfn.CONCAT("Olá ",PROPER(LOWER(TRIM(LEFT(SUBSTITUTE(_xlfn.XLOOKUP(Follow[[#This Row],[Id Pedido]],Controle_Pedidos[Número Pedido Cliente],Controle_Pedidos[NOME])," ",REPT(" ",100)),100)))),", Identificamos que o Item ",_xlfn.XLOOKUP(Follow[[#This Row],[Id Pedido]],Controle_Pedidos[Número Pedido Cliente],Controle_Pedidos[Nome Produto])," foi entregue no dia ",TEXT(Follow[[#This Row],[DATAATUALIZAÇÃO]],"dd/mm/aaaa"),", referente ao pedido Nº ",Follow[[#This Row],[Id Pedido]]," Rastreio ",IF(Follow[[#This Row],[Novo Cód de Rastreio]]="-",Follow[[#This Row],[Id Pedido]],Follow[[#This Row],[Novo Cód de Rastreio]]),", agradecemos a preferência e adoraríamos receber sua avaliação, tendo qualquer dúvida estamos à disposição.",_xlfn.IFS(Follow[[#This Row],[Loja]]="bv"," Att Tem tudo Shop",Follow[[#This Row],[Loja]]="mei"," Att NTA Variedades",Follow[[#This Row],[Loja]]="go"," Att Sec Variedades")) -> Olá Nome, Identificamos que o Item Adaptador Bluetooph foi entregue no dia 03/12/2024, referente ao pedido Nº Pedido 426 Rastreio Pedido 426, agradecemos a preferência e adoraríamos receber sua avaliação, tendo qualquer dúvida estamos à disposição. Att Tem tudo Shop
A255: =_xlfn.XLOOKUP(Follow[[#This Row],[CODRASTREIO]],Controle_Pedidos[Cód Rastreamento],Controle_Pedidos[Número Pedido Cliente]) -> Pedido 426 | B255: CódRastreio413 | C255: =Follow[[#This Row],[CODRASTREIO]]&" B" -> CódRastreio413 B | D255: =_xlfn.XLOOKUP(Follow[[#This Row],[Id Pedido]],Controle_Pedidos[Número Pedido Cliente],Controle_Pedidos[Loja]) -> BV | E255: =_xlfn.XLOOKUP(Follow[[#This Row],[Id Pedido]],Controle_Pedidos[Número Pedido Cliente],Controle_Pedidos[Prazo Entrega]) -> 45645 | F255: Transp 1 | G255: - | H255: Brasil | I255: Brasil | J255: 45630 | K255: Entregue | L255: ENTREGUE | M255: - | N255: =IF(Follow[[#This Row],[DATAATUALIZAÇÃO]]<=Follow[[#This Row],[Prev Entrega]],"Dentro do Prazo","Fora do Prazo") -> Dentro do Prazo | O255: =_xlfn.CONCAT("Olá ",PROPER(LOWER(TRIM(LEFT(SUBSTITUTE(_xlfn.XLOOKUP(Follow[[#This Row],[Id Pedido]],Controle_Pedidos[Número Pedido Cliente],Controle_Pedidos[NOME])," ",REPT(" ",100)),100)))),", Identificamos que o Item ",_xlfn.XLOOKUP(Follow[[#This Row],[Id Pedido]],Controle_Pedidos[Número Pedido Cliente],Controle_Pedidos[Nome Produto])," foi entregue no dia ",TEXT(Follow[[#This Row],[DATAATUALIZAÇÃO]],"dd/mm/aaaa"),", referente ao pedido Nº ",Follow[[#This Row],[Id Pedido]]," Rastreio ",IF(Follow[[#This Row],[Novo Cód de Rastreio]]="-",Follow[[#This Row],[Id Pedido]],Follow[[#This Row],[Novo Cód de Rastreio]]),", agradecemos a preferência e adoraríamos receber sua avaliação, tendo qualquer dúvida estamos à disposição.",_xlfn.IFS(Follow[[#This Row],[Loja]]="bv"," Att Tem tudo Shop",Follow[[#This Row],[Loja]]="mei"," Att NTA Variedades",Follow[[#This Row],[Loja]]="go"," Att Sec Variedades")) -> Olá Nome, Identificamos que o Item Adaptador Bluetooph foi entregue no dia 04/12/2024, referente ao pedido Nº Pedido 426 Rastreio Pedido 426, agradecemos a preferência e adoraríamos receber sua avaliação, tendo qualquer dúvida estamos à disposição. Att Tem tudo Shop
A256: =_xlfn.XLOOKUP(Follow[[#This Row],[CODRASTREIO]],Controle_Pedidos[Cód Rastreamento],Controle_Pedidos[Número Pedido Cliente]) -> Pedido 177 | B256: CódRastreio170 | C256: =Follow[[#This Row],[CODRASTREIO]]&" B" -> CódRastreio170 B | D256: =_xlfn.XLOOKUP(Follow[[#This Row],[Id Pedido]],Controle_Pedidos[Número Pedido Cliente],Controle_Pedidos[Loja]) -> BV | E256: =_xlfn.XLOOKUP(Follow[[#This Row],[Id Pedido]],Controle_Pedidos[Número Pedido Cliente],Controle_Pedidos[Prazo Entrega]) -> 45618 | F256: Transp 1 | G256: - | H256: Brasil | I256: Brasil | J256: 45602 | K256: Entregue | L256: ENTREGUE | M256: - | N256: =IF(Follow[[#This Row],[DATAATUALIZAÇÃO]]<=Follow[[#This Row],[Prev Entrega]],"Dentro do Prazo","Fora do Prazo") -> Dentro do Prazo | O256: =_xlfn.CONCAT("Olá ",PROPER(LOWER(TRIM(LEFT(SUBSTITUTE(_xlfn.XLOOKUP(Follow[[#This Row],[Id Pedido]],Controle_Pedidos[Número Pedido Cliente],Controle_Pedidos[NOME])," ",REPT(" ",100)),100)))),", Identificamos que o Item ",_xlfn.XLOOKUP(Follow[[#This Row],[Id Pedido]],Controle_Pedidos[Número Pedido Cliente],Controle_Pedidos[Nome Produto])," foi entregue no dia ",TEXT(Follow[[#This Row],[DATAATUALIZAÇÃO]],"dd/mm/aaaa"),", referente ao pedido Nº ",Follow[[#This Row],[Id Pedido]]," Rastreio ",IF(Follow[[#This Row],[Novo Cód de Rastreio]]="-",Follow[[#This Row],[Id Pedido]],Follow[[#This Row],[Novo Cód de Rastreio]]),", agradecemos a preferência e adoraríamos receber sua avaliação, tendo qualquer dúvida estamos à disposição.",_xlfn.IFS(Follow[[#This Row],[Loja]]="bv"," Att Tem tudo Shop",Follow[[#This Row],[Loja]]="mei"," Att NTA Variedades",Follow[[#This Row],[Loja]]="go"," Att Sec Variedades")) -> Olá Nome, Identificamos que o Item Suporte de Celular Branco foi entregue no dia 06/11/2024, referente ao pedido Nº Pedido 177 Rastreio Pedido 177, agradecemos a preferência e adoraríamos receber sua avaliação, tendo qualquer dúvida estamos à disposição. Att Tem tudo Shop
A257: =_xlfn.XLOOKUP(Follow[[#This Row],[CODRASTREIO]],Controle_Pedidos[Cód Rastreamento],Controle_Pedidos[Número Pedido Cliente]) -> Pedido 232 | B257: CódRastreio225 | C257: =Follow[[#This Row],[CODRASTREIO]]&" B" -> CódRastreio225 B | D257: =_xlfn.XLOOKUP(Follow[[#This Row],[Id Pedido]],Controle_Pedidos[Número Pedido Cliente],Controle_Pedidos[Loja]) -> BV | E257: =_xlfn.XLOOKUP(Follow[[#This Row],[Id Pedido]],Controle_Pedidos[Número Pedido Cliente],Controle_Pedidos[Prazo Entrega]) -> 45626 | F257: Transp 1 | G257: - | H257: Brasil | I257: Brasil | J257: 45611 | K257: Entregue | L257: ENTREGUE | M257: Cliente Notificado | N257: =IF(Follow[[#This Row],[DATAATUALIZAÇÃO]]<=Follow[[#This Row],[Prev Entrega]],"Dentro do Prazo","Fora do Prazo") -> Dentro do Prazo | O257: =_xlfn.CONCAT("Olá ",PROPER(LOWER(TRIM(LEFT(SUBSTITUTE(_xlfn.XLOOKUP(Follow[[#This Row],[Id Pedido]],Controle_Pedidos[Número Pedido Cliente],Controle_Pedidos[NOME])," ",REPT(" ",100)),100)))),", Identificamos que o Item ",_xlfn.XLOOKUP(Follow[[#This Row],[Id Pedido]],Controle_Pedidos[Número Pedido Cliente],Controle_Pedidos[Nome Produto])," foi entregue no dia ",TEXT(Follow[[#This Row],[DATAATUALIZAÇÃO]],"dd/mm/aaaa"),", referente ao pedido Nº ",Follow[[#This Row],[Id Pedido]]," Rastreio ",IF(Follow[[#This Row],[Novo Cód de Rastreio]]="-",Follow[[#This Row],[Id Pedido]],Follow[[#This Row],[Novo Cód de Rastreio]]),", agradecemos a preferência e adoraríamos receber sua avaliação, tendo qualquer dúvida estamos à disposição.",_xlfn.IFS(Follow[[#This Row],[Loja]]="bv"," Att Tem tudo Shop",Follow[[#This Row],[Loja]]="mei"," Att NTA Variedades",Follow[[#This Row],[Loja]]="go"," Att Sec Variedades")) -> Olá Nome, Identificamos que o Item Mini Liquidificador foi entregue no dia 15/11/2024, referente ao pedido Nº Pedido 232 Rastreio Pedido 232, agradecemos a preferência e adoraríamos receber sua avaliação, tendo qualquer dúvida estamos à disposição. Att Tem tudo Shop
A258: =_xlfn.XLOOKUP(Follow[[#This Row],[CODRASTREIO]],Controle_Pedidos[Cód Rastreamento],Controle_Pedidos[Número Pedido Cliente]) -> Pedido 383 | B258: CódRastreio373 | C258: =Follow[[#This Row],[CODRASTREIO]]&" B" -> CódRastreio373 B | D258: =_xlfn.XLOOKUP(Follow[[#This Row],[Id Pedido]],Controle_Pedidos[Número Pedido Cliente],Controle_Pedidos[Loja]) -> BV | E258: =_xlfn.XLOOKUP(Follow[[#This Row],[Id Pedido]],Controle_Pedidos[Número Pedido Cliente],Controle_Pedidos[Prazo Entrega]) -> 45630 | F258: Transp 1 | G258: - | H258: Brasil | I258: Brasil | J258: 45618 | K258: Entregue | L258: ENTREGUE | M258: - | N258: =IF(Follow[[#This Row],[DATAATUALIZAÇÃO]]<=Follow[[#This Row],[Prev Entrega]],"Dentro do Prazo","Fora do Prazo") -> Dentro do Prazo | O258: =_xlfn.CONCAT("Olá ",PROPER(LOWER(TRIM(LEFT(SUBSTITUTE(_xlfn.XLOOKUP(Follow[[#This Row],[Id Pedido]],Controle_Pedidos[Número Pedido Cliente],Controle_Pedidos[NOME])," ",REPT(" ",100)),100)))),", Identificamos que o Item ",_xlfn.XLOOKUP(Follow[[#This Row],[Id Pedido]],Controle_Pedidos[Número Pedido Cliente],Controle_Pedidos[Nome Produto])," foi entregue no dia ",TEXT(Follow[[#This Row],[DATAATUALIZAÇÃO]],"dd/mm/aaaa"),", referente ao pedido Nº ",Follow[[#This Row],[Id Pedido]]," Rastreio ",IF(Follow[[#This Row],[Novo Cód de Rastreio]]="-",Follow[[#This Row],[Id Pedido]],Follow[[#This Row],[Novo Cód de Rastreio]]),", agradecemos a preferência e adoraríamos receber sua avaliação, tendo qualquer dúvida estamos à disposição.",_xlfn.IFS(Follow[[#This Row],[Loja]]="bv"," Att Tem tudo Shop",Follow[[#This Row],[Loja]]="mei"," Att NTA Variedades",Follow[[#This Row],[Loja]]="go"," Att Sec Variedades")) -> Olá Nome, Identificamos que o Item Adaptador Bluetooph foi entregue no dia 22/11/2024, referente ao pedido Nº Pedido 383 Rastreio Pedido 383, agradecemos a preferência e adoraríamos receber sua avaliação, tendo qualquer dúvida estamos à disposição. Att Tem tudo Shop
A259: =_xlfn.XLOOKUP(Follow[[#This Row],[CODRASTREIO]],Controle_Pedidos[Cód Rastreamento],Controle_Pedidos[Número Pedido Cliente]) -> Pedido 93 | B259: CódRastreio86 | C259: =Follow[[#This Row],[CODRASTREIO]]&" B" -> CódRastreio86 B | D259: =_xlfn.XLOOKUP(Follow[[#This Row],[Id Pedido]],Controle_Pedidos[Número Pedido Cliente],Controle_Pedidos[Loja]) -> BV | E259: =_xlfn.XLOOKUP(Follow[[#This Row],[Id Pedido]],Controle_Pedidos[Número Pedido Cliente],Controle_Pedidos[Prazo Entrega]) -> 45617 | F259: Transp 1 | G259: - | H259: Brasil | I259: Brasil | J259: 45597 | K259: Entregue | L259: ENTREGUE | M259: - | N259: =IF(Follow[[#This Row],[DATAATUALIZAÇÃO]]<=Follow[[#This Row],[Prev Entrega]],"Dentro do Prazo","Fora do Prazo") -> Dentro do Prazo | O259: =_xlfn.CONCAT("Olá ",PROPER(LOWER(TRIM(LEFT(SUBSTITUTE(_xlfn.XLOOKUP(Follow[[#This Row],[Id Pedido]],Controle_Pedidos[Número Pedido Cliente],Controle_Pedidos[NOME])," ",REPT(" ",100)),100)))),", Identificamos que o Item ",_xlfn.XLOOKUP(Follow[[#This Row],[Id Pedido]],Controle_Pedidos[Número Pedido Cliente],Controle_Pedidos[Nome Produto])," foi entregue no dia ",TEXT(Follow[[#This Row],[DATAATUALIZAÇÃO]],"dd/mm/aaaa"),", referente ao pedido Nº ",Follow[[#This Row],[Id Pedido]]," Rastreio ",IF(Follow[[#This Row],[Novo Cód de Rastreio]]="-",Follow[[#This Row],[Id Pedido]],Follow[[#This Row],[Novo Cód de Rastreio]]),", agradecemos a preferência e adoraríamos receber sua avaliação, tendo qualquer dúvida estamos à disposição.",_xlfn.IFS(Follow[[#This Row],[Loja]]="bv"," Att Tem tudo Shop",Follow[[#This Row],[Loja]]="mei"," Att NTA Variedades",Follow[[#This Row],[Loja]]="go"," Att Sec Variedades")) -> Olá Nome, Identificamos que o Item Bomba d'agua foi entregue no dia 01/11/2024, referente ao pedido Nº Pedido 93 Rastreio Pedido 93, agradecemos a preferência e adoraríamos receber sua avaliação, tendo qualquer dúvida estamos à disposição. Att Tem tudo Shop
A260: =_xlfn.XLOOKUP(Follow[[#This Row],[CODRASTREIO]],Controle_Pedidos[Cód Rastreamento],Controle_Pedidos[Número Pedido Cliente]) -> Pedido 18 | B260: CódRastreio9 | C260: =Follow[[#This Row],[CODRASTREIO]]&" B" -> CódRastreio9 B | D260: =_xlfn.XLOOKUP(Follow[[#This Row],[Id Pedido]],Controle_Pedidos[Número Pedido Cliente],Controle_Pedidos[Loja]) -> BV | E260: =_xlfn.XLOOKUP(Follow[[#This Row],[Id Pedido]],Controle_Pedidos[Número Pedido Cliente],Controle_Pedidos[Prazo Entrega]) -> 45610 | F260: Transp 1 | G260: - | H260: Brasil | I260: Brasil | J260: 45595 | K260: Entregue | L260: ENTREGUE | M260: - | N260: =IF(Follow[[#This Row],[DATAATUALIZAÇÃO]]<=Follow[[#This Row],[Prev Entrega]],"Dentro do Prazo","Fora do Prazo") -> Dentro do Prazo | O260: =_xlfn.CONCAT("Olá ",PROPER(LOWER(TRIM(LEFT(SUBSTITUTE(_xlfn.XLOOKUP(Follow[[#This Row],[Id Pedido]],Controle_Pedidos[Número Pedido Cliente],Controle_Pedidos[NOME])," ",REPT(" ",100)),100)))),", Identificamos que o Item ",_xlfn.XLOOKUP(Follow[[#This Row],[Id Pedido]],Controle_Pedidos[Número Pedido Cliente],Controle_Pedidos[Nome Produto])," foi entregue no dia ",TEXT(Follow[[#This Row],[DATAATUALIZAÇÃO]],"dd/mm/aaaa"),", referente ao pedido Nº ",Follow[[#This Row],[Id Pedido]]," Rastreio ",IF(Follow[[#This Row],[Novo Cód de Rastreio]]="-",Follow[[#This Row],[Id Pedido]],Follow[[#This Row],[Novo Cód de Rastreio]]),", agradecemos a preferência e adoraríamos receber sua avaliação, tendo qualquer dúvida estamos à disposição.",_xlfn.IFS(Follow[[#This Row],[Loja]]="bv"," Att Tem tudo Shop",Follow[[#This Row],[Loja]]="mei"," Att NTA Variedades",Follow[[#This Row],[Loja]]="go"," Att Sec Variedades")) -> Olá Nome, Identificamos que o Item Suporte de Celular Branco foi entregue no dia 30/10/2024, referente ao pedido Nº Pedido 18 Rastreio Pedido 18, agradecemos a preferência e adoraríamos receber sua avaliação, tendo qualquer dúvida estamos à disposição. Att Tem tudo Shop
A261: =_xlfn.XLOOKUP(Follow[[#This Row],[CODRASTREIO]],Controle_Pedidos[Cód Rastreamento],Controle_Pedidos[Número Pedido Cliente]) -> Pedido 661 | B261: CódRastreio641 | C261: =Follow[[#This Row],[CODRASTREIO]]&" B" -> CódRastreio641 B | D261: =_xlfn.XLOOKUP(Follow[[#This Row],[Id Pedido]],Controle_Pedidos[Número Pedido Cliente],Controle_Pedidos[Loja]) -> BV | E261: =_xlfn.XLOOKUP(Follow[[#This Row],[Id Pedido]],Controle_Pedidos[Número Pedido Cliente],Controle_Pedidos[Prazo Entrega]) -> 45679 | F261: Transp 1 | G261: - | H261: China | I261: Brasil | J261: 45665 | K261: Entregue | L261: ENTREGUE | M261: - | N261: =IF(Follow[[#This Row],[DATAATUALIZAÇÃO]]<=Follow[[#This Row],[Prev Entrega]],"Dentro do Prazo","Fora do Prazo") -> Dentro do Prazo | O261: =_xlfn.CONCAT("Olá ",PROPER(LOWER(TRIM(LEFT(SUBSTITUTE(_xlfn.XLOOKUP(Follow[[#This Row],[Id Pedido]],Controle_Pedidos[Número Pedido Cliente],Controle_Pedidos[NOME])," ",REPT(" ",100)),100)))),", Identificamos que o Item ",_xlfn.XLOOKUP(Follow[[#This Row],[Id Pedido]],Controle_Pedidos[Número Pedido Cliente],Controle_Pedidos[Nome Produto])," foi entregue no dia ",TEXT(Follow[[#This Row],[DATAATUALIZAÇÃO]],"dd/mm/aaaa"),", referente ao pedido Nº ",Follow[[#This Row],[Id Pedido]]," Rastreio ",IF(Follow[[#This Row],[Novo Cód de Rastreio]]="-",Follow[[#This Row],[Id Pedido]],Follow[[#This Row],[Novo Cód de Rastreio]]),", agradecemos a preferência e adoraríamos receber sua avaliação, tendo qualquer dúvida estamos à disposição.",_xlfn.IFS(Follow[[#This Row],[Loja]]="bv"," Att Tem tudo Shop",Follow[[#This Row],[Loja]]="mei"," Att NTA Variedades",Follow[[#This Row],[Loja]]="go"," Att Sec Variedades")) -> Olá Nome, Identificamos que o Item Lampada Led foi entregue no dia 08/01/2025, referente ao pedido Nº Pedido 661 Rastreio Pedido 661, agradecemos a preferência e adoraríamos receber sua avaliação, tendo qualquer dúvida estamos à disposição. Att Tem tudo Shop
A262: =_xlfn.XLOOKUP(Follow[[#This Row],[CODRASTREIO]],Controle_Pedidos[Cód Rastreamento],Controle_Pedidos[Número Pedido Cliente]) -> Pedido 500 | B262: CódRastreio486 | C262: =Follow[[#This Row],[CODRASTREIO]]&" B" -> CódRastreio486 B | D262: =_xlfn.XLOOKUP(Follow[[#This Row],[Id Pedido]],Controle_Pedidos[Número Pedido Cliente],Controle_Pedidos[Loja]) -> BV | E262: =_xlfn.XLOOKUP(Follow[[#This Row],[Id Pedido]],Controle_Pedidos[Número Pedido Cliente],Controle_Pedidos[Prazo Entrega]) -> 45650 | F262: Transp 1 | G262: - | H262: China | I262: Brasil | J262: 45645 | K262: Entregue | L262: ENTREGUE | M262: - | N262: =IF(Follow[[#This Row],[DATAATUALIZAÇÃO]]<=Follow[[#This Row],[Prev Entrega]],"Dentro do Prazo","Fora do Prazo") -> Dentro do Prazo | O262: =_xlfn.CONCAT("Olá ",PROPER(LOWER(TRIM(LEFT(SUBSTITUTE(_xlfn.XLOOKUP(Follow[[#This Row],[Id Pedido]],Controle_Pedidos[Número Pedido Cliente],Controle_Pedidos[NOME])," ",REPT(" ",100)),100)))),", Identificamos que o Item ",_xlfn.XLOOKUP(Follow[[#This Row],[Id Pedido]],Controle_Pedidos[Número Pedido Cliente],Controle_Pedidos[Nome Produto])," foi entregue no dia ",TEXT(Follow[[#This Row],[DATAATUALIZAÇÃO]],"dd/mm/aaaa"),", referente ao pedido Nº ",Follow[[#This Row],[Id Pedido]]," Rastreio ",IF(Follow[[#This Row],[Novo Cód de Rastreio]]="-",Follow[[#This Row],[Id Pedido]],Follow[[#This Row],[Novo Cód de Rastreio]]),", agradecemos a preferência e adoraríamos receber sua avaliação, tendo qualquer dúvida estamos à disposição.",_xlfn.IFS(Follow[[#This Row],[Loja]]="bv"," Att Tem tudo Shop",Follow[[#This Row],[Loja]]="mei"," Att NTA Variedades",Follow[[#This Row],[Loja]]="go"," Att Sec Variedades")) -> Olá Nome, Identificamos que o Item Ventilador Azul foi entregue no dia 19/12/2024, referente ao pedido Nº Pedido 500 Rastreio Pedido 500, agradecemos a preferência e adoraríamos receber sua avaliação, tendo qualquer dúvida estamos à disposição. Att Tem tudo Shop
A263: =_xlfn.XLOOKUP(Follow[[#This Row],[CODRASTREIO]],Controle_Pedidos[Cód Rastreamento],Controle_Pedidos[Número Pedido Cliente]) -> Pedido 134 | B263: CódRastreio127 | C263: =Follow[[#This Row],[CODRASTREIO]]&" B" -> CódRastreio127 B | D263: =_xlfn.XLOOKUP(Follow[[#This Row],[Id Pedido]],Controle_Pedidos[Número Pedido Cliente],Controle_Pedidos[Loja]) -> BV | E263: =_xlfn.XLOOKUP(Follow[[#This Row],[Id Pedido]],Controle_Pedidos[Número Pedido Cliente],Controle_Pedidos[Prazo Entrega]) -> 45605 | F263: Transp 1 | G263: - | H263: Brasil | I263: Brasil | J263: 45633 | K263: Entregue | L263: ENTREGUE | M263: Reembolsado | N263: =IF(Follow[[#This Row],[DATAATUALIZAÇÃO]]<=Follow[[#This Row],[Prev Entrega]],"Dentro do Prazo","Fora do Prazo") -> Fora do Prazo | O263: =_xlfn.CONCAT("Olá ",PROPER(LOWER(TRIM(LEFT(SUBSTITUTE(_xlfn.XLOOKUP(Follow[[#This Row],[Id Pedido]],Controle_Pedidos[Número Pedido Cliente],Controle_Pedidos[NOME])," ",REPT(" ",100)),100)))),", Identificamos que o Item ",_xlfn.XLOOKUP(Follow[[#This Row],[Id Pedido]],Controle_Pedidos[Número Pedido Cliente],Controle_Pedidos[Nome Produto])," foi entregue no dia ",TEXT(Follow[[#This Row],[DATAATUALIZAÇÃO]],"dd/mm/aaaa"),", referente ao pedido Nº ",Follow[[#This Row],[Id Pedido]]," Rastreio ",IF(Follow[[#This Row],[Novo Cód de Rastreio]]="-",Follow[[#This Row],[Id Pedido]],Follow[[#This Row],[Novo Cód de Rastreio]]),", agradecemos a preferência e adoraríamos receber sua avaliação, tendo qualquer dúvida estamos à disposição.",_xlfn.IFS(Follow[[#This Row],[Loja]]="bv"," Att Tem tudo Shop",Follow[[#This Row],[Loja]]="mei"," Att NTA Variedades",Follow[[#This Row],[Loja]]="go"," Att Sec Variedades")) -> Olá Nome, Identificamos que o Item Mini Liquidificador foi entregue no dia 07/12/2024, referente ao pedido Nº Pedido 134 Rastreio Pedido 134, agradecemos a preferência e adoraríamos receber sua avaliação, tendo qualquer dúvida estamos à disposição. Att Tem tudo Shop
A264: =_xlfn.XLOOKUP(Follow[[#This Row],[CODRASTREIO]],Controle_Pedidos[Cód Rastreamento],Controle_Pedidos[Número Pedido Cliente]) -> Pedido 31 | B264: CódRastreio22 | C264: =Follow[[#This Row],[CODRASTREIO]]&" B" -> CódRastreio22 B | D264: =_xlfn.XLOOKUP(Follow[[#This Row],[Id Pedido]],Controle_Pedidos[Número Pedido Cliente],Controle_Pedidos[Loja]) -> BV | E264: =_xlfn.XLOOKUP(Follow[[#This Row],[Id Pedido]],Controle_Pedidos[Número Pedido Cliente],Controle_Pedidos[Prazo Entrega]) -> 45601 | F264: Transp 1 | G264: - | H264: Brasil | I264: Brasil | J264: 45591 | K264: Entregue | L264: ENTREGUE | M264: - | N264: =IF(Follow[[#This Row],[DATAATUALIZAÇÃO]]<=Follow[[#This Row],[Prev Entrega]],"Dentro do Prazo","Fora do Prazo") -> Dentro do Prazo | O264: =_xlfn.CONCAT("Olá ",PROPER(LOWER(TRIM(LEFT(SUBSTITUTE(_xlfn.XLOOKUP(Follow[[#This Row],[Id Pedido]],Controle_Pedidos[Número Pedido Cliente],Controle_Pedidos[NOME])," ",REPT(" ",100)),100)))),", Identificamos que o Item ",_xlfn.XLOOKUP(Follow[[#This Row],[Id Pedido]],Controle_Pedidos[Número Pedido Cliente],Controle_Pedidos[Nome Produto])," foi entregue no dia ",TEXT(Follow[[#This Row],[DATAATUALIZAÇÃO]],"dd/mm/aaaa"),", referente ao pedido Nº ",Follow[[#This Row],[Id Pedido]]," Rastreio ",IF(Follow[[#This Row],[Novo Cód de Rastreio]]="-",Follow[[#This Row],[Id Pedido]],Follow[[#This Row],[Novo Cód de Rastreio]]),", agradecemos a preferência e adoraríamos receber sua avaliação, tendo qualquer dúvida estamos à disposição.",_xlfn.IFS(Follow[[#This Row],[Loja]]="bv"," Att Tem tudo Shop",Follow[[#This Row],[Loja]]="mei"," Att NTA Variedades",Follow[[#This Row],[Loja]]="go"," Att Sec Variedades")) -> Olá Nome, Identificamos que o Item Balança foi entregue no dia 26/10/2024, referente ao pedido Nº Pedido 31 Rastreio Pedido 31, agradecemos a preferência e adoraríamos receber sua avaliação, tendo qualquer dúvida estamos à disposição. Att Tem tudo Shop
A265: =_xlfn.XLOOKUP(Follow[[#This Row],[CODRASTREIO]],Controle_Pedidos[Cód Rastreamento],Controle_Pedidos[Número Pedido Cliente]) -> Pedido 108 | B265: CódRastreio101 | C265: =Follow[[#This Row],[CODRASTREIO]]&" B" -> CódRastreio101 B | D265: =_xlfn.XLOOKUP(Follow[[#This Row],[Id Pedido]],Controle_Pedidos[Número Pedido Cliente],Controle_Pedidos[Loja]) -> BV | E265: =_xlfn.XLOOKUP(Follow[[#This Row],[Id Pedido]],Controle_Pedidos[Número Pedido Cliente],Controle_Pedidos[Prazo Entrega]) -> 45617 | F265: Transp 1 | G265: - | H265: Brasil | I265: Brasil | J265: 45603 | K265: Entregue | L265: ENTREGUE | M265: - | N265: =IF(Follow[[#This Row],[DATAATUALIZAÇÃO]]<=Follow[[#This Row],[Prev Entrega]],"Dentro do Prazo","Fora do Prazo") -> Dentro do Prazo | O265: =_xlfn.CONCAT("Olá ",PROPER(LOWER(TRIM(LEFT(SUBSTITUTE(_xlfn.XLOOKUP(Follow[[#This Row],[Id Pedido]],Controle_Pedidos[Número Pedido Cliente],Controle_Pedidos[NOME])," ",REPT(" ",100)),100)))),", Identificamos que o Item ",_xlfn.XLOOKUP(Follow[[#This Row],[Id Pedido]],Controle_Pedidos[Número Pedido Cliente],Controle_Pedidos[Nome Produto])," foi entregue no dia ",TEXT(Follow[[#This Row],[DATAATUALIZAÇÃO]],"dd/mm/aaaa"),", referente ao pedido Nº ",Follow[[#This Row],[Id Pedido]]," Rastreio ",IF(Follow[[#This Row],[Novo Cód de Rastreio]]="-",Follow[[#This Row],[Id Pedido]],Follow[[#This Row],[Novo Cód de Rastreio]]),", agradecemos a preferência e adoraríamos receber sua avaliação, tendo qualquer dúvida estamos à disposição.",_xlfn.IFS(Follow[[#This Row],[Loja]]="bv"," Att Tem tudo Shop",Follow[[#This Row],[Loja]]="mei"," Att NTA Variedades",Follow[[#This Row],[Loja]]="go"," Att Sec Variedades")) -> Olá Nome, Identificamos que o Item Bomba d'agua foi entregue no dia 07/11/2024, referente ao pedido Nº Pedido 108 Rastreio Pedido 108, agradecemos a preferência e adoraríamos receber sua avaliação, tendo qualquer dúvida estamos à disposição. Att Tem tudo Shop
A266: =_xlfn.XLOOKUP(Follow[[#This Row],[CODRASTREIO]],Controle_Pedidos[Cód Rastreamento],Controle_Pedidos[Número Pedido Cliente]) -> Pedido 398 | B266: CódRastreio388 | C266: =Follow[[#This Row],[CODRASTREIO]]&" B" -> CódRastreio388 B | D266: =_xlfn.XLOOKUP(Follow[[#This Row],[Id Pedido]],Controle_Pedidos[Número Pedido Cliente],Controle_Pedidos[Loja]) -> BV | E266: =_xlfn.XLOOKUP(Follow[[#This Row],[Id Pedido]],Controle_Pedidos[Número Pedido Cliente],Controle_Pedidos[Prazo Entrega]) -> 45643 | F266: Transp 1 | G266: - | H266: Brasil | I266: Brasil | J266: 45625 | K266: Entregue | L266: ENTREGUE | M266: - | N266: =IF(Follow[[#This Row],[DATAATUALIZAÇÃO]]<=Follow[[#This Row],[Prev Entrega]],"Dentro do Prazo","Fora do Prazo") -> Dentro do Prazo | O266: =_xlfn.CONCAT("Olá ",PROPER(LOWER(TRIM(LEFT(SUBSTITUTE(_xlfn.XLOOKUP(Follow[[#This Row],[Id Pedido]],Controle_Pedidos[Número Pedido Cliente],Controle_Pedidos[NOME])," ",REPT(" ",100)),100)))),", Identificamos que o Item ",_xlfn.XLOOKUP(Follow[[#This Row],[Id Pedido]],Controle_Pedidos[Número Pedido Cliente],Controle_Pedidos[Nome Produto])," foi entregue no dia ",TEXT(Follow[[#This Row],[DATAATUALIZAÇÃO]],"dd/mm/aaaa"),", referente ao pedido Nº ",Follow[[#This Row],[Id Pedido]]," Rastreio ",IF(Follow[[#This Row],[Novo Cód de Rastreio]]="-",Follow[[#This Row],[Id Pedido]],Follow[[#This Row],[Novo Cód de Rastreio]]),", agradecemos a preferência e adoraríamos receber sua avaliação, tendo qualquer dúvida estamos à disposição.",_xlfn.IFS(Follow[[#This Row],[Loja]]="bv"," Att Tem tudo Shop",Follow[[#This Row],[Loja]]="mei"," Att NTA Variedades",Follow[[#This Row],[Loja]]="go"," Att Sec Variedades")) -> Olá Nome, Identificamos que o Item Mini Liquidificador foi entregue no dia 29/11/2024, referente ao pedido Nº Pedido 398 Rastreio Pedido 398, agradecemos a preferência e adoraríamos receber sua avaliação, tendo qualquer dúvida estamos à disposição. Att Tem tudo Shop
... A421: =_xlfn.XLOOKUP(Follow[[#This Row],[CODRASTREIO]],Controle_Pedidos[Cód Rastreamento],Controle_Pedidos[Número Pedido Cliente]) -> Pedido 260 | B421: CódRastreio253 | C421: =Follow[[#This Row],[CODRASTREIO]]&" B" -> CódRastreio253 B | D421: =_xlfn.XLOOKUP(Follow[[#This Row],[Id Pedido]],Controle_Pedidos[Número Pedido Cliente],Controle_Pedidos[Loja]) -> BV | E421: =_xlfn.XLOOKUP(Follow[[#This Row],[Id Pedido]],Controle_Pedidos[Número Pedido Cliente],Controle_Pedidos[Prazo Entrega]) -> 45623 | F421: Transp 1 | G421: - | H421: Brasil | I421: Brasil | J421: 45611 | K421: Entregue | L421: ENTREGUE | M421: - | N421: =IF(Follow[[#This Row],[DATAATUALIZAÇÃO]]<=Follow[[#This Row],[Prev Entrega]],"Dentro do Prazo","Fora do Prazo") -> Dentro do Prazo | O421: =_xlfn.CONCAT("Olá ",PROPER(LOWER(TRIM(LEFT(SUBSTITUTE(_xlfn.XLOOKUP(Follow[[#This Row],[Id Pedido]],Controle_Pedidos[Número Pedido Cliente],Controle_Pedidos[NOME])," ",REPT(" ",100)),100)))),", Identificamos que o Item ",_xlfn.XLOOKUP(Follow[[#This Row],[Id Pedido]],Controle_Pedidos[Número Pedido Cliente],Controle_Pedidos[Nome Produto])," foi entregue no dia ",TEXT(Follow[[#This Row],[DATAATUALIZAÇÃO]],"dd/mm/aaaa"),", referente ao pedido Nº ",Follow[[#This Row],[Id Pedido]]," Rastreio ",IF(Follow[[#This Row],[Novo Cód de Rastreio]]="-",Follow[[#This Row],[Id Pedido]],Follow[[#This Row],[Novo Cód de Rastreio]]),", agradecemos a preferência e adoraríamos receber sua avaliação, tendo qualquer dúvida estamos à disposição.",_xlfn.IFS(Follow[[#This Row],[Loja]]="bv"," Att Tem tudo Shop",Follow[[#This Row],[Loja]]="mei"," Att NTA Variedades",Follow[[#This Row],[Loja]]="go"," Att Sec Variedades")) -> Olá Nome, Identificamos que o Item Bomba d'agua foi entregue no dia 15/11/2024, referente ao pedido Nº Pedido 260 Rastreio Pedido 260, agradecemos a preferência e adoraríamos receber sua avaliação, tendo qualquer dúvida estamos à disposição. Att Tem tudo Shop
A422: Pedido 81 | B422: CódRastreio72 1 Envio | C422: =Follow[[#This Row],[CODRASTREIO]]&" B" -> CódRastreio72 1 Envio B | D422: BV | E422: 45617 | F422: Transp 1 | G422: - | H422: Brasil | I422: Brasil | J422: 45602 | K422: Entregue | L422: ENTREGUE | M422: - | N422: =IF(Follow[[#This Row],[DATAATUALIZAÇÃO]]<=Follow[[#This Row],[Prev Entrega]],"Dentro do Prazo","Fora do Prazo") -> Dentro do Prazo | O422: =_xlfn.CONCAT("Olá ",PROPER(LOWER(TRIM(LEFT(SUBSTITUTE(_xlfn.XLOOKUP(Follow[[#This Row],[Id Pedido]],Controle_Pedidos[Número Pedido Cliente],Controle_Pedidos[NOME])," ",REPT(" ",100)),100)))),", Identificamos que o Item ",_xlfn.XLOOKUP(Follow[[#This Row],[Id Pedido]],Controle_Pedidos[Número Pedido Cliente],Controle_Pedidos[Nome Produto])," foi entregue no dia ",TEXT(Follow[[#This Row],[DATAATUALIZAÇÃO]],"dd/mm/aaaa"),", referente ao pedido Nº ",Follow[[#This Row],[Id Pedido]]," Rastreio ",IF(Follow[[#This Row],[Novo Cód de Rastreio]]="-",Follow[[#This Row],[Id Pedido]],Follow[[#This Row],[Novo Cód de Rastreio]]),", agradecemos a preferência e adoraríamos receber sua avaliação, tendo qualquer dúvida estamos à disposição.",_xlfn.IFS(Follow[[#This Row],[Loja]]="bv"," Att Tem tudo Shop",Follow[[#This Row],[Loja]]="mei"," Att NTA Variedades",Follow[[#This Row],[Loja]]="go"," Att Sec Variedades")) -> Olá Nome, Identificamos que o Item Copo Termico foi entregue no dia 06/11/2024, referente ao pedido Nº Pedido 81 Rastreio Pedido 81, agradecemos a preferência e adoraríamos receber sua avaliação, tendo qualquer dúvida estamos à disposição. Att Tem tudo Shop
A423: Pedido 81 | B423: CódRastreio72 2 Envio | C423: =Follow[[#This Row],[CODRASTREIO]]&" B" -> CódRastreio72 2 Envio B | D423: BV | E423: 45617 | F423: Transp 1 | G423: - | H423: Brasil | I423: Brasil | J423: 45598 | K423: Entregue | L423: ENTREGUE | M423: - | N423: =IF(Follow[[#This Row],[DATAATUALIZAÇÃO]]<=Follow[[#This Row],[Prev Entrega]],"Dentro do Prazo","Fora do Prazo") -> Dentro do Prazo | O423: =_xlfn.CONCAT("Olá ",PROPER(LOWER(TRIM(LEFT(SUBSTITUTE(_xlfn.XLOOKUP(Follow[[#This Row],[Id Pedido]],Controle_Pedidos[Número Pedido Cliente],Controle_Pedidos[NOME])," ",REPT(" ",100)),100)))),", Identificamos que o Item ",_xlfn.XLOOKUP(Follow[[#This Row],[Id Pedido]],Controle_Pedidos[Número Pedido Cliente],Controle_Pedidos[Nome Produto])," foi entregue no dia ",TEXT(Follow[[#This Row],[DATAATUALIZAÇÃO]],"dd/mm/aaaa"),", referente ao pedido Nº ",Follow[[#This Row],[Id Pedido]]," Rastreio ",IF(Follow[[#This Row],[Novo Cód de Rastreio]]="-",Follow[[#This Row],[Id Pedido]],Follow[[#This Row],[Novo Cód de Rastreio]]),", agradecemos a preferência e adoraríamos receber sua avaliação, tendo qualquer dúvida estamos à disposição.",_xlfn.IFS(Follow[[#This Row],[Loja]]="bv"," Att Tem tudo Shop",Follow[[#This Row],[Loja]]="mei"," Att NTA Variedades",Follow[[#This Row],[Loja]]="go"," Att Sec Variedades")) -> Olá Nome, Identificamos que o Item Copo Termico foi entregue no dia 02/11/2024, referente ao pedido Nº Pedido 81 Rastreio Pedido 81, agradecemos a preferência e adoraríamos receber sua avaliação, tendo qualquer dúvida estamos à disposição. Att Tem tudo Shop
A424: =_xlfn.XLOOKUP(Follow[[#This Row],[CODRASTREIO]],Controle_Pedidos[Cód Rastreamento],Controle_Pedidos[Número Pedido Cliente]) -> Pedido 343 | B424: CódRastreio336 | C424: =Follow[[#This Row],[CODRASTREIO]]&" B" -> CódRastreio336 B | D424: =_xlfn.XLOOKUP(Follow[[#This Row],[Id Pedido]],Controle_Pedidos[Número Pedido Cliente],Controle_Pedidos[Loja]) -> BV | E424: =_xlfn.XLOOKUP(Follow[[#This Row],[Id Pedido]],Controle_Pedidos[Número Pedido Cliente],Controle_Pedidos[Prazo Entrega]) -> 45630 | F424: Transp 1 | G424: - | H424: China | I424: Brasil | J424: 45667 | K424: Entregue | L424: ENTREGUE | M424: Aguardando reembolso | N424: =IF(Follow[[#This Row],[DATAATUALIZAÇÃO]]<=Follow[[#This Row],[Prev Entrega]],"Dentro do Prazo","Fora do Prazo") -> Fora do Prazo | O424: =_xlfn.CONCAT("Olá ",PROPER(LOWER(TRIM(LEFT(SUBSTITUTE(_xlfn.XLOOKUP(Follow[[#This Row],[Id Pedido]],Controle_Pedidos[Número Pedido Cliente],Controle_Pedidos[NOME])," ",REPT(" ",100)),100)))),", Identificamos que o Item ",_xlfn.XLOOKUP(Follow[[#This Row],[Id Pedido]],Controle_Pedidos[Número Pedido Cliente],Controle_Pedidos[Nome Produto])," foi entregue no dia ",TEXT(Follow[[#This Row],[DATAATUALIZAÇÃO]],"dd/mm/aaaa"),", referente ao pedido Nº ",Follow[[#This Row],[Id Pedido]]," Rastreio ",IF(Follow[[#This Row],[Novo Cód de Rastreio]]="-",Follow[[#This Row],[Id Pedido]],Follow[[#This Row],[Novo Cód de Rastreio]]),", agradecemos a preferência e adoraríamos receber sua avaliação, tendo qualquer dúvida estamos à disposição.",_xlfn.IFS(Follow[[#This Row],[Loja]]="bv"," Att Tem tudo Shop",Follow[[#This Row],[Loja]]="mei"," Att NTA Variedades",Follow[[#This Row],[Loja]]="go"," Att Sec Variedades")) -> Olá Nome, Identificamos que o Item Ventilador Umidificador foi entregue no dia 10/01/2025, referente ao pedido Nº Pedido 343 Rastreio Pedido 343, agradecemos a preferência e adoraríamos receber sua avaliação, tendo qualquer dúvida estamos à disposição. Att Tem tudo Shop
A425: =_xlfn.XLOOKUP(Follow[[#This Row],[CODRASTREIO]],Controle_Pedidos[Cód Rastreamento],Controle_Pedidos[Número Pedido Cliente]) -> Pedido 81 | B425: CódRastreio72 | C425: =Follow[[#This Row],[CODRASTREIO]]&" B" -> CódRastreio72 B | D425: =_xlfn.XLOOKUP(Follow[[#This Row],[Id Pedido]],Controle_Pedidos[Número Pedido Cliente],Controle_Pedidos[Loja]) -> BV | E425: =_xlfn.XLOOKUP(Follow[[#This Row],[Id Pedido]],Controle_Pedidos[Número Pedido Cliente],Controle_Pedidos[Prazo Entrega]) -> 45617 | F425: Transp 1 | G425: - | H425: Brasil | I425: Brasil | J425: 45600 | K425: Entregue | L425: ENTREGUE | M425: - | N425: =IF(Follow[[#This Row],[DATAATUALIZAÇÃO]]<=Follow[[#This Row],[Prev Entrega]],"Dentro do Prazo","Fora do Prazo") -> Dentro do Prazo | O425: =_xlfn.CONCAT("Olá ",PROPER(LOWER(TRIM(LEFT(SUBSTITUTE(_xlfn.XLOOKUP(Follow[[#This Row],[Id Pedido]],Controle_Pedidos[Número Pedido Cliente],Controle_Pedidos[NOME])," ",REPT(" ",100)),100)))),", Identificamos que o Item ",_xlfn.XLOOKUP(Follow[[#This Row],[Id Pedido]],Controle_Pedidos[Número Pedido Cliente],Controle_Pedidos[Nome Produto])," foi entregue no dia ",TEXT(Follow[[#This Row],[DATAATUALIZAÇÃO]],"dd/mm/aaaa"),", referente ao pedido Nº ",Follow[[#This Row],[Id Pedido]]," Rastreio ",IF(Follow[[#This Row],[Novo Cód de Rastreio]]="-",Follow[[#This Row],[Id Pedido]],Follow[[#This Row],[Novo Cód de Rastreio]]),", agradecemos a preferência e adoraríamos receber sua avaliação, tendo qualquer dúvida estamos à disposição.",_xlfn.IFS(Follow[[#This Row],[Loja]]="bv"," Att Tem tudo Shop",Follow[[#This Row],[Loja]]="mei"," Att NTA Variedades",Follow[[#This Row],[Loja]]="go"," Att Sec Variedades")) -> Olá Nome, Identificamos que o Item Copo Termico foi entregue no dia 04/11/2024, referente ao pedido Nº Pedido 81 Rastreio Pedido 81, agradecemos a preferência e adoraríamos receber sua avaliação, tendo qualquer dúvida estamos à disposição. Att Tem tudo Shop
A426: =_xlfn.XLOOKUP(Follow[[#This Row],[CODRASTREIO]],Controle_Pedidos[Cód Rastreamento],Controle_Pedidos[Número Pedido Cliente]) -> Pedido 90 | B426: CódRastreio83 | C426: =Follow[[#This Row],[CODRASTREIO]]&" B" -> CódRastreio83 B | D426: =_xlfn.XLOOKUP(Follow[[#This Row],[Id Pedido]],Controle_Pedidos[Número Pedido Cliente],Controle_Pedidos[Loja]) -> BV | E426: =_xlfn.XLOOKUP(Follow[[#This Row],[Id Pedido]],Controle_Pedidos[Número Pedido Cliente],Controle_Pedidos[Prazo Entrega]) -> 45610 | F426: Transp 1 | G426: - | H426: Brasil | I426: Brasil | J426: 45596 | K426: Entregue | L426: ENTREGUE | M426: - | N426: =IF(Follow[[#This Row],[DATAATUALIZAÇÃO]]<=Follow[[#This Row],[Prev Entrega]],"Dentro do Prazo","Fora do Prazo") -> Dentro do Prazo | O426: =_xlfn.CONCAT("Olá ",PROPER(LOWER(TRIM(LEFT(SUBSTITUTE(_xlfn.XLOOKUP(Follow[[#This Row],[Id Pedido]],Controle_Pedidos[Número Pedido Cliente],Controle_Pedidos[NOME])," ",REPT(" ",100)),100)))),", Identificamos que o Item ",_xlfn.XLOOKUP(Follow[[#This Row],[Id Pedido]],Controle_Pedidos[Número Pedido Cliente],Controle_Pedidos[Nome Produto])," foi entregue no dia ",TEXT(Follow[[#This Row],[DATAATUALIZAÇÃO]],"dd/mm/aaaa"),", referente ao pedido Nº ",Follow[[#This Row],[Id Pedido]]," Rastreio ",IF(Follow[[#This Row],[Novo Cód de Rastreio]]="-",Follow[[#This Row],[Id Pedido]],Follow[[#This Row],[Novo Cód de Rastreio]]),", agradecemos a preferência e adoraríamos receber sua avaliação, tendo qualquer dúvida estamos à disposição.",_xlfn.IFS(Follow[[#This Row],[Loja]]="bv"," Att Tem tudo Shop",Follow[[#This Row],[Loja]]="mei"," Att NTA Variedades",Follow[[#This Row],[Loja]]="go"," Att Sec Variedades")) -> Olá Nome, Identificamos que o Item Bomba d'agua foi entregue no dia 31/10/2024, referente ao pedido Nº Pedido 90 Rastreio Pedido 90, agradecemos a preferência e adoraríamos receber sua avaliação, tendo qualquer dúvida estamos à disposição. Att Tem tudo Shop
A427: =_xlfn.XLOOKUP(Follow[[#This Row],[CODRASTREIO]],Controle_Pedidos[Cód Rastreamento],Controle_Pedidos[Número Pedido Cliente]) -> Pedido 309 | B427: CódRastreio302 | C427: =Follow[[#This Row],[CODRASTREIO]]&" B" -> CódRastreio302 B | D427: =_xlfn.XLOOKUP(Follow[[#This Row],[Id Pedido]],Controle_Pedidos[Número Pedido Cliente],Controle_Pedidos[Loja]) -> BV | E427: =_xlfn.XLOOKUP(Follow[[#This Row],[Id Pedido]],Controle_Pedidos[Número Pedido Cliente],Controle_Pedidos[Prazo Entrega]) -> 45632 | F427: Transp 1 | G427: - | H427: Brasil | I427: Brasil | J427: 45612 | K427: Entregue | L427: ENTREGUE | M427: - | N427: =IF(Follow[[#This Row],[DATAATUALIZAÇÃO]]<=Follow[[#This Row],[Prev Entrega]],"Dentro do Prazo","Fora do Prazo") -> Dentro do Prazo | O427: =_xlfn.CONCAT("Olá ",PROPER(LOWER(TRIM(LEFT(SUBSTITUTE(_xlfn.XLOOKUP(Follow[[#This Row],[Id Pedido]],Controle_Pedidos[Número Pedido Cliente],Controle_Pedidos[NOME])," ",REPT(" ",100)),100)))),", Identificamos que o Item ",_xlfn.XLOOKUP(Follow[[#This Row],[Id Pedido]],Controle_Pedidos[Número Pedido Cliente],Controle_Pedidos[Nome Produto])," foi entregue no dia ",TEXT(Follow[[#This Row],[DATAATUALIZAÇÃO]],"dd/mm/aaaa"),", referente ao pedido Nº ",Follow[[#This Row],[Id Pedido]]," Rastreio ",IF(Follow[[#This Row],[Novo Cód de Rastreio]]="-",Follow[[#This Row],[Id Pedido]],Follow[[#This Row],[Novo Cód de Rastreio]]),", agradecemos a preferência e adoraríamos receber sua avaliação, tendo qualquer dúvida estamos à disposição.",_xlfn.IFS(Follow[[#This Row],[Loja]]="bv"," Att Tem tudo Shop",Follow[[#This Row],[Loja]]="mei"," Att NTA Variedades",Follow[[#This Row],[Loja]]="go"," Att Sec Variedades")) -> Olá Nome, Identificamos que o Item Bomba d'agua foi entregue no dia 16/11/2024, referente ao pedido Nº Pedido 309 Rastreio Pedido 309, agradecemos a preferência e adoraríamos receber sua avaliação, tendo qualquer dúvida estamos à disposição. Att Tem tudo Shop
A428: =_xlfn.XLOOKUP(Follow[[#This Row],[CODRASTREIO]],Controle_Pedidos[Cód Rastreamento],Controle_Pedidos[Número Pedido Cliente]) -> Pedido 538 | B428: CódRastreio523 | C428: =Follow[[#This Row],[CODRASTREIO]]&" B" -> CódRastreio523 B | D428: =_xlfn.XLOOKUP(Follow[[#This Row],[Id Pedido]],Controle_Pedidos[Número Pedido Cliente],Controle_Pedidos[Loja]) -> BV | E428: =_xlfn.XLOOKUP(Follow[[#This Row],[Id Pedido]],Controle_Pedidos[Número Pedido Cliente],Controle_Pedidos[Prazo Entrega]) -> 45675 | F428: Transp 1 | G428: - | H428: China | I428: Brasil | J428: 45660 | K428: Entregue | L428: ENTREGUE | M428: - | N428: =IF(Follow[[#This Row],[DATAATUALIZAÇÃO]]<=Follow[[#This Row],[Prev Entrega]],"Dentro do Prazo","Fora do Prazo") -> Dentro do Prazo | O428: =_xlfn.CONCAT("Olá ",PROPER(LOWER(TRIM(LEFT(SUBSTITUTE(_xlfn.XLOOKUP(Follow[[#This Row],[Id Pedido]],Controle_Pedidos[Número Pedido Cliente],Controle_Pedidos[NOME])," ",REPT(" ",100)),100)))),", Identificamos que o Item ",_xlfn.XLOOKUP(Follow[[#This Row],[Id Pedido]],Controle_Pedidos[Número Pedido Cliente],Controle_Pedidos[Nome Produto])," foi entregue no dia ",TEXT(Follow[[#This Row],[DATAATUALIZAÇÃO]],"dd/mm/aaaa"),", referente ao pedido Nº ",Follow[[#This Row],[Id Pedido]]," Rastreio ",IF(Follow[[#This Row],[Novo Cód de Rastreio]]="-",Follow[[#This Row],[Id Pedido]],Follow[[#This Row],[Novo Cód de Rastreio]]),", agradecemos a preferência e adoraríamos receber sua avaliação, tendo qualquer dúvida estamos à disposição.",_xlfn.IFS(Follow[[#This Row],[Loja]]="bv"," Att Tem tudo Shop",Follow[[#This Row],[Loja]]="mei"," Att NTA Variedades",Follow[[#This Row],[Loja]]="go"," Att Sec Variedades")) -> Olá Nome, Identificamos que o Item Ventilador Rosa foi entregue no dia 03/01/2025, referente ao pedido Nº Pedido 538 Rastreio Pedido 538, agradecemos a preferência e adoraríamos receber sua avaliação, tendo qualquer dúvida estamos à disposição. Att Tem tudo Shop
A429: =_xlfn.XLOOKUP(Follow[[#This Row],[CODRASTREIO]],Controle_Pedidos[Cód Rastreamento],Controle_Pedidos[Número Pedido Cliente]) -> Pedido 419 | B429: CódRastreio408 | C429: =Follow[[#This Row],[CODRASTREIO]]&" B" -> CódRastreio408 B | D429: =_xlfn.XLOOKUP(Follow[[#This Row],[Id Pedido]],Controle_Pedidos[Número Pedido Cliente],Controle_Pedidos[Loja]) -> BV | E429: =_xlfn.XLOOKUP(Follow[[#This Row],[Id Pedido]],Controle_Pedidos[Número Pedido Cliente],Controle_Pedidos[Prazo Entrega]) -> 45653 | F429: Transp 1 | G429: - | H429: China | I429: Brasil | J429: 45636 | K429: Entregue | L429: ENTREGUE | M429: - | N429: =IF(Follow[[#This Row],[DATAATUALIZAÇÃO]]<=Follow[[#This Row],[Prev Entrega]],"Dentro do Prazo","Fora do Prazo") -> Dentro do Prazo | O429: =_xlfn.CONCAT("Olá ",PROPER(LOWER(TRIM(LEFT(SUBSTITUTE(_xlfn.XLOOKUP(Follow[[#This Row],[Id Pedido]],Controle_Pedidos[Número Pedido Cliente],Controle_Pedidos[NOME])," ",REPT(" ",100)),100)))),", Identificamos que o Item ",_xlfn.XLOOKUP(Follow[[#This Row],[Id Pedido]],Controle_Pedidos[Número Pedido Cliente],Controle_Pedidos[Nome Produto])," foi entregue no dia ",TEXT(Follow[[#This Row],[DATAATUALIZAÇÃO]],"dd/mm/aaaa"),", referente ao pedido Nº ",Follow[[#This Row],[Id Pedido]]," Rastreio ",IF(Follow[[#This Row],[Novo Cód de Rastreio]]="-",Follow[[#This Row],[Id Pedido]],Follow[[#This Row],[Novo Cód de Rastreio]]),", agradecemos a preferência e adoraríamos receber sua avaliação, tendo qualquer dúvida estamos à disposição.",_xlfn.IFS(Follow[[#This Row],[Loja]]="bv"," Att Tem tudo Shop",Follow[[#This Row],[Loja]]="mei"," Att NTA Variedades",Follow[[#This Row],[Loja]]="go"," Att Sec Variedades")) -> Olá Nome, Identificamos que o Item Ventilador Rosa foi entregue no dia 10/12/2024, referente ao pedido Nº Pedido 419 Rastreio Pedido 419, agradecemos a preferência e adoraríamos receber sua avaliação, tendo qualquer dúvida estamos à disposição. Att Tem tudo Shop
A430: =_xlfn.XLOOKUP(Follow[[#This Row],[CODRASTREIO]],Controle_Pedidos[Cód Rastreamento],Controle_Pedidos[Número Pedido Cliente]) -> Pedido 151 | B430: CódRastreio144 | C430: =Follow[[#This Row],[CODRASTREIO]]&" B" -> CódRastreio144 B | D430: =_xlfn.XLOOKUP(Follow[[#This Row],[Id Pedido]],Controle_Pedidos[Número Pedido Cliente],Controle_Pedidos[Loja]) -> BV | E430: =_xlfn.XLOOKUP(Follow[[#This Row],[Id Pedido]],Controle_Pedidos[Número Pedido Cliente],Controle_Pedidos[Prazo Entrega]) -> 45619 | F430: Transp 1 | G430: - | H430: Brasil | I430: Brasil | J430: 45602 | K430: Entregue | L430: ENTREGUE | M430: - | N430: =IF(Follow[[#This Row],[DATAATUALIZAÇÃO]]<=Follow[[#This Row],[Prev Entrega]],"Dentro do Prazo","Fora do Prazo") -> Dentro do Prazo | O430: =_xlfn.CONCAT("Olá ",PROPER(LOWER(TRIM(LEFT(SUBSTITUTE(_xlfn.XLOOKUP(Follow[[#This Row],[Id Pedido]],Controle_Pedidos[Número Pedido Cliente],Controle_Pedidos[NOME])," ",REPT(" ",100)),100)))),", Identificamos que o Item ",_xlfn.XLOOKUP(Follow[[#This Row],[Id Pedido]],Controle_Pedidos[Número Pedido Cliente],Controle_Pedidos[Nome Produto])," foi entregue no dia ",TEXT(Follow[[#This Row],[DATAATUALIZAÇÃO]],"dd/mm/aaaa"),", referente ao pedido Nº ",Follow[[#This Row],[Id Pedido]]," Rastreio ",IF(Follow[[#This Row],[Novo Cód de Rastreio]]="-",Follow[[#This Row],[Id Pedido]],Follow[[#This Row],[Novo Cód de Rastreio]]),", agradecemos a preferência e adoraríamos receber sua avaliação, tendo qualquer dúvida estamos à disposição.",_xlfn.IFS(Follow[[#This Row],[Loja]]="bv"," Att Tem tudo Shop",Follow[[#This Row],[Loja]]="mei"," Att NTA Variedades",Follow[[#This Row],[Loja]]="go"," Att Sec Variedades")) -> Olá Nome, Identificamos que o Item Bomba d'agua foi entregue no dia 06/11/2024, referente ao pedido Nº Pedido 151 Rastreio Pedido 151, agradecemos a preferência e adoraríamos receber sua avaliação, tendo qualquer dúvida estamos à disposição. Att Tem tudo Shop
A431: =_xlfn.XLOOKUP(Follow[[#This Row],[CODRASTREIO]],Controle_Pedidos[Cód Rastreamento],Controle_Pedidos[Número Pedido Cliente]) -> Pedido 381 | B431: CódRastreio371 | C431: =Follow[[#This Row],[CODRASTREIO]]&" B" -> CódRastreio371 B | D431: =_xlfn.XLOOKUP(Follow[[#This Row],[Id Pedido]],Controle_Pedidos[Número Pedido Cliente],Controle_Pedidos[Loja]) -> BV | E431: =_xlfn.XLOOKUP(Follow[[#This Row],[Id Pedido]],Controle_Pedidos[Número Pedido Cliente],Controle_Pedidos[Prazo Entrega]) -> 45630 | F431: Transp 1 | G431: - | H431: Brasil | I431: Brasil | J431: 45622 | K431: Entregue | L431: ENTREGUE | M431: - | N431: =IF(Follow[[#This Row],[DATAATUALIZAÇÃO]]<=Follow[[#This Row],[Prev Entrega]],"Dentro do Prazo","Fora do Prazo") -> Dentro do Prazo | O431: =_xlfn.CONCAT("Olá ",PROPER(LOWER(TRIM(LEFT(SUBSTITUTE(_xlfn.XLOOKUP(Follow[[#This Row],[Id Pedido]],Controle_Pedidos[Número Pedido Cliente],Controle_Pedidos[NOME])," ",REPT(" ",100)),100)))),", Identificamos que o Item ",_xlfn.XLOOKUP(Follow[[#This Row],[Id Pedido]],Controle_Pedidos[Número Pedido Cliente],Controle_Pedidos[Nome Produto])," foi entregue no dia ",TEXT(Follow[[#This Row],[DATAATUALIZAÇÃO]],"dd/mm/aaaa"),", referente ao pedido Nº ",Follow[[#This Row],[Id Pedido]]," Rastreio ",IF(Follow[[#This Row],[Novo Cód de Rastreio]]="-",Follow[[#This Row],[Id Pedido]],Follow[[#This Row],[Novo Cód de Rastreio]]),", agradecemos a preferência e adoraríamos receber sua avaliação, tendo qualquer dúvida estamos à disposição.",_xlfn.IFS(Follow[[#This Row],[Loja]]="bv"," Att Tem tudo Shop",Follow[[#This Row],[Loja]]="mei"," Att NTA Variedades",Follow[[#This Row],[Loja]]="go"," Att Sec Variedades")) -> Olá Nome, Identificamos que o Item Mini Liquidificador foi entregue no dia 26/11/2024, referente ao pedido Nº Pedido 381 Rastreio Pedido 381, agradecemos a preferência e adoraríamos receber sua avaliação, tendo qualquer dúvida estamos à disposição. Att Tem tudo Shop
A432: =_xlfn.XLOOKUP(Follow[[#This Row],[CODRASTREIO]],Controle_Pedidos[Cód Rastreamento],Controle_Pedidos[Número Pedido Cliente]) -> Pedido 622 | B432: CódRastreio605 | C432: =Follow[[#This Row],[CODRASTREIO]]&" B" -> CódRastreio605 B | D432: =_xlfn.XLOOKUP(Follow[[#This Row],[Id Pedido]],Controle_Pedidos[Número Pedido Cliente],Controle_Pedidos[Loja]) -> BV | E432: =_xlfn.XLOOKUP(Follow[[#This Row],[Id Pedido]],Controle_Pedidos[Número Pedido Cliente],Controle_Pedidos[Prazo Entrega]) -> 45674 | F432: Transp 1 | G432: - | H432: China | I432: Brasil | J432: 45665 | K432: Entregue | L432: ENTREGUE | M432: - | N432: =IF(Follow[[#This Row],[DATAATUALIZAÇÃO]]<=Follow[[#This Row],[Prev Entrega]],"Dentro do Prazo","Fora do Prazo") -> Dentro do Prazo | O432: =_xlfn.CONCAT("Olá ",PROPER(LOWER(TRIM(LEFT(SUBSTITUTE(_xlfn.XLOOKUP(Follow[[#This Row],[Id Pedido]],Controle_Pedidos[Número Pedido Cliente],Controle_Pedidos[NOME])," ",REPT(" ",100)),100)))),", Identificamos que o Item ",_xlfn.XLOOKUP(Follow[[#This Row],[Id Pedido]],Controle_Pedidos[Número Pedido Cliente],Controle_Pedidos[Nome Produto])," foi entregue no dia ",TEXT(Follow[[#This Row],[DATAATUALIZAÇÃO]],"dd/mm/aaaa"),", referente ao pedido Nº ",Follow[[#This Row],[Id Pedido]]," Rastreio ",IF(Follow[[#This Row],[Novo Cód de Rastreio]]="-",Follow[[#This Row],[Id Pedido]],Follow[[#This Row],[Novo Cód de Rastreio]]),", agradecemos a preferência e adoraríamos receber sua avaliação, tendo qualquer dúvida estamos à disposição.",_xlfn.IFS(Follow[[#This Row],[Loja]]="bv"," Att Tem tudo Shop",Follow[[#This Row],[Loja]]="mei"," Att NTA Variedades",Follow[[#This Row],[Loja]]="go"," Att Sec Variedades")) -> Olá Nome, Identificamos que o Item Ventilador Preto foi entregue no dia 08/01/2025, referente ao pedido Nº Pedido 622 Rastreio Pedido 622, agradecemos a preferência e adoraríamos receber sua avaliação, tendo qualquer dúvida estamos à disposição. Att Tem tudo Shop
A433: =_xlfn.XLOOKUP(Follow[[#This Row],[CODRASTREIO]],Controle_Pedidos[Cód Rastreamento],Controle_Pedidos[Número Pedido Cliente]) -> Pedido 142 | B433: CódRastreio135 | C433: =Follow[[#This Row],[CODRASTREIO]]&" B" -> CódRastreio135 B | D433: =_xlfn.XLOOKUP(Follow[[#This Row],[Id Pedido]],Controle_Pedidos[Número Pedido Cliente],Controle_Pedidos[Loja]) -> BV | E433: =_xlfn.XLOOKUP(Follow[[#This Row],[Id Pedido]],Controle_Pedidos[Número Pedido Cliente],Controle_Pedidos[Prazo Entrega]) -> 45618 | F433: Transp 1 | G433: - | H433: China | I433: Brasil | J433: 45609 | K433: Entregue | L433: ENTREGUE | M433: - | N433: =IF(Follow[[#This Row],[DATAATUALIZAÇÃO]]<=Follow[[#This Row],[Prev Entrega]],"Dentro do Prazo","Fora do Prazo") -> Dentro do Prazo | O433: =_xlfn.CONCAT("Olá ",PROPER(LOWER(TRIM(LEFT(SUBSTITUTE(_xlfn.XLOOKUP(Follow[[#This Row],[Id Pedido]],Controle_Pedidos[Número Pedido Cliente],Controle_Pedidos[NOME])," ",REPT(" ",100)),100)))),", Identificamos que o Item ",_xlfn.XLOOKUP(Follow[[#This Row],[Id Pedido]],Controle_Pedidos[Número Pedido Cliente],Controle_Pedidos[Nome Produto])," foi entregue no dia ",TEXT(Follow[[#This Row],[DATAATUALIZAÇÃO]],"dd/mm/aaaa"),", referente ao pedido Nº ",Follow[[#This Row],[Id Pedido]]," Rastreio ",IF(Follow[[#This Row],[Novo Cód de Rastreio]]="-",Follow[[#This Row],[Id Pedido]],Follow[[#This Row],[Novo Cód de Rastreio]]),", agradecemos a preferência e adoraríamos receber sua avaliação, tendo qualquer dúvida estamos à disposição.",_xlfn.IFS(Follow[[#This Row],[Loja]]="bv"," Att Tem tudo Shop",Follow[[#This Row],[Loja]]="mei"," Att NTA Variedades",Follow[[#This Row],[Loja]]="go"," Att Sec Variedades")) -> Olá Nome, Identificamos que o Item Ventilador Preto foi entregue no dia 13/11/2024, referente ao pedido Nº Pedido 142 Rastreio Pedido 142, agradecemos a preferência e adoraríamos receber sua avaliação, tendo qualquer dúvida estamos à disposição. Att Tem tudo Shop
A434: =_xlfn.XLOOKUP(Follow[[#This Row],[CODRASTREIO]],Controle_Pedidos[Cód Rastreamento],Controle_Pedidos[Número Pedido Cliente]) -> Pedido 24 | B434: CódRastreio15 | C434: =Follow[[#This Row],[CODRASTREIO]]&" B" -> CódRastreio15 B | D434: =_xlfn.XLOOKUP(Follow[[#This Row],[Id Pedido]],Controle_Pedidos[Número Pedido Cliente],Controle_Pedidos[Loja]) -> BV | E434: =_xlfn.XLOOKUP(Follow[[#This Row],[Id Pedido]],Controle_Pedidos[Número Pedido Cliente],Controle_Pedidos[Prazo Entrega]) -> 45611 | F434: Transp 1 | G434: - | H434: Brasil | I434: Brasil | J434: 45594 | K434: Entregue | L434: ENTREGUE | M434: - | N434: =IF(Follow[[#This Row],[DATAATUALIZAÇÃO]]<=Follow[[#This Row],[Prev Entrega]],"Dentro do Prazo","Fora do Prazo") -> Dentro do Prazo | O434: =_xlfn.CONCAT("Olá ",PROPER(LOWER(TRIM(LEFT(SUBSTITUTE(_xlfn.XLOOKUP(Follow[[#This Row],[Id Pedido]],Controle_Pedidos[Número Pedido Cliente],Controle_Pedidos[NOME])," ",REPT(" ",100)),100)))),", Identificamos que o Item ",_xlfn.XLOOKUP(Follow[[#This Row],[Id Pedido]],Controle_Pedidos[Número Pedido Cliente],Controle_Pedidos[Nome Produto])," foi entregue no dia ",TEXT(Follow[[#This Row],[DATAATUALIZAÇÃO]],"dd/mm/aaaa"),", referente ao pedido Nº ",Follow[[#This Row],[Id Pedido]]," Rastreio ",IF(Follow[[#This Row],[Novo Cód de Rastreio]]="-",Follow[[#This Row],[Id Pedido]],Follow[[#This Row],[Novo Cód de Rastreio]]),", agradecemos a preferência e adoraríamos receber sua avaliação, tendo qualquer dúvida estamos à disposição.",_xlfn.IFS(Follow[[#This Row],[Loja]]="bv"," Att Tem tudo Shop",Follow[[#This Row],[Loja]]="mei"," Att NTA Variedades",Follow[[#This Row],[Loja]]="go"," Att Sec Variedades")) -> Olá Nome, Identificamos que o Item Suporte de Celular Branco foi entregue no dia 29/10/2024, referente ao pedido Nº Pedido 24 Rastreio Pedido 24, agradecemos a preferência e adoraríamos receber sua avaliação, tendo qualquer dúvida estamos à disposição. Att Tem tudo Shop
A435: =_xlfn.XLOOKUP(Follow[[#This Row],[CODRASTREIO]],Controle_Pedidos[Cód Rastreamento],Controle_Pedidos[Número Pedido Cliente]) -> Pedido 25 | B435: CódRastreio16 | C435: =Follow[[#This Row],[CODRASTREIO]]&" B" -> CódRastreio16 B | D435: =_xlfn.XLOOKUP(Follow[[#This Row],[Id Pedido]],Controle_Pedidos[Número Pedido Cliente],Controle_Pedidos[Loja]) -> BV | E435: =_xlfn.XLOOKUP(Follow[[#This Row],[Id Pedido]],Controle_Pedidos[Número Pedido Cliente],Controle_Pedidos[Prazo Entrega]) -> 45611 | F435: Transp 1 | G435: - | H435: Brasil | I435: Brasil | J435: 45594 | K435: Entregue | L435: ENTREGUE | M435: - | N435: =IF(Follow[[#This Row],[DATAATUALIZAÇÃO]]<=Follow[[#This Row],[Prev Entrega]],"Dentro do Prazo","Fora do Prazo") -> Dentro do Prazo | O435: =_xlfn.CONCAT("Olá ",PROPER(LOWER(TRIM(LEFT(SUBSTITUTE(_xlfn.XLOOKUP(Follow[[#This Row],[Id Pedido]],Controle_Pedidos[Número Pedido Cliente],Controle_Pedidos[NOME])," ",REPT(" ",100)),100)))),", Identificamos que o Item ",_xlfn.XLOOKUP(Follow[[#This Row],[Id Pedido]],Controle_Pedidos[Número Pedido Cliente],Controle_Pedidos[Nome Produto])," foi entregue no dia ",TEXT(Follow[[#This Row],[DATAATUALIZAÇÃO]],"dd/mm/aaaa"),", referente ao pedido Nº ",Follow[[#This Row],[Id Pedido]]," Rastreio ",IF(Follow[[#This Row],[Novo Cód de Rastreio]]="-",Follow[[#This Row],[Id Pedido]],Follow[[#This Row],[Novo Cód de Rastreio]]),", agradecemos a preferência e adoraríamos receber sua avaliação, tendo qualquer dúvida estamos à disposição.",_xlfn.IFS(Follow[[#This Row],[Loja]]="bv"," Att Tem tudo Shop",Follow[[#This Row],[Loja]]="mei"," Att NTA Variedades",Follow[[#This Row],[Loja]]="go"," Att Sec Variedades")) -> Olá Nome, Identificamos que o Item Suporte de Celular Branco foi entregue no dia 29/10/2024, referente ao pedido Nº Pedido 25 Rastreio Pedido 25, agradecemos a preferência e adoraríamos receber sua avaliação, tendo qualquer dúvida estamos à disposição. Att Tem tudo Shop
... A500: =_xlfn.XLOOKUP(Follow[[#This Row],[CODRASTREIO]],Controle_Pedidos[Cód Rastreamento],Controle_Pedidos[Número Pedido Cliente]) -> Pedido 344 | B500: CódRastreio337 | C500: =Follow[[#This Row],[CODRASTREIO]]&" B" -> CódRastreio337 B | D500: =_xlfn.XLOOKUP(Follow[[#This Row],[Id Pedido]],Controle_Pedidos[Número Pedido Cliente],Controle_Pedidos[Loja]) -> BV | E500: =_xlfn.XLOOKUP(Follow[[#This Row],[Id Pedido]],Controle_Pedidos[Número Pedido Cliente],Controle_Pedidos[Prazo Entrega]) -> 45630 | F500: Transp 1 | G500: - | H500: China | I500: Brasil | J500: 45617 | K500: Entregue | L500: ENTREGUE | M500: - | N500: =IF(Follow[[#This Row],[DATAATUALIZAÇÃO]]<=Follow[[#This Row],[Prev Entrega]],"Dentro do Prazo","Fora do Prazo") -> Dentro do Prazo | O500: =_xlfn.CONCAT("Olá ",PROPER(LOWER(TRIM(LEFT(SUBSTITUTE(_xlfn.XLOOKUP(Follow[[#This Row],[Id Pedido]],Controle_Pedidos[Número Pedido Cliente],Controle_Pedidos[NOME])," ",REPT(" ",100)),100)))),", Identificamos que o Item ",_xlfn.XLOOKUP(Follow[[#This Row],[Id Pedido]],Controle_Pedidos[Número Pedido Cliente],Controle_Pedidos[Nome Produto])," foi entregue no dia ",TEXT(Follow[[#This Row],[DATAATUALIZAÇÃO]],"dd/mm/aaaa"),", referente ao pedido Nº ",Follow[[#This Row],[Id Pedido]]," Rastreio ",IF(Follow[[#This Row],[Novo Cód de Rastreio]]="-",Follow[[#This Row],[Id Pedido]],Follow[[#This Row],[Novo Cód de Rastreio]]),", agradecemos a preferência e adoraríamos receber sua avaliação, tendo qualquer dúvida estamos à disposição.",_xlfn.IFS(Follow[[#This Row],[Loja]]="bv"," Att Tem tudo Shop",Follow[[#This Row],[Loja]]="mei"," Att NTA Variedades",Follow[[#This Row],[Loja]]="go"," Att Sec Variedades")) -> Olá Nome, Identificamos que o Item Ventilador Preto foi entregue no dia 21/11/2024, referente ao pedido Nº Pedido 344 Rastreio Pedido 344, agradecemos a preferência e adoraríamos receber sua avaliação, tendo qualquer dúvida estamos à disposição. Att Tem tudo Shop
A501: Pedido 443 | B501: CódRastreio428 1 Envio | C501: =Follow[[#This Row],[CODRASTREIO]]&" B" -> CódRastreio428 1 Envio B | D501: BV | E501: 45643 | F501: Transp 1 | G501: - | H501: China | I501: Brasil | J501: 45632.817 | K501: Entregue | L501: ENTREGUE | M501: - | N501: =IF(Follow[[#This Row],[DATAATUALIZAÇÃO]]<=Follow[[#This Row],[Prev Entrega]],"Dentro do Prazo","Fora do Prazo") -> Dentro do Prazo | O501: =_xlfn.CONCAT("Olá ",PROPER(LOWER(TRIM(LEFT(SUBSTITUTE(_xlfn.XLOOKUP(Follow[[#This Row],[Id Pedido]],Controle_Pedidos[Número Pedido Cliente],Controle_Pedidos[NOME])," ",REPT(" ",100)),100)))),", Identificamos que o Item ",_xlfn.XLOOKUP(Follow[[#This Row],[Id Pedido]],Controle_Pedidos[Número Pedido Cliente],Controle_Pedidos[Nome Produto])," foi entregue no dia ",TEXT(Follow[[#This Row],[DATAATUALIZAÇÃO]],"dd/mm/aaaa"),", referente ao pedido Nº ",Follow[[#This Row],[Id Pedido]]," Rastreio ",IF(Follow[[#This Row],[Novo Cód de Rastreio]]="-",Follow[[#This Row],[Id Pedido]],Follow[[#This Row],[Novo Cód de Rastreio]]),", agradecemos a preferência e adoraríamos receber sua avaliação, tendo qualquer dúvida estamos à disposição.",_xlfn.IFS(Follow[[#This Row],[Loja]]="bv"," Att Tem tudo Shop",Follow[[#This Row],[Loja]]="mei"," Att NTA Variedades",Follow[[#This Row],[Loja]]="go"," Att Sec Variedades")) -> Olá Nome, Identificamos que o Item Ventilador Azul foi entregue no dia 06/12/2024, referente ao pedido Nº Pedido 443 Rastreio Pedido 443, agradecemos a preferência e adoraríamos receber sua avaliação, tendo qualquer dúvida estamos à disposição. Att Tem tudo Shop
A502: =_xlfn.XLOOKUP(Follow[[#This Row],[CODRASTREIO]],Controle_Pedidos[Cód Rastreamento],Controle_Pedidos[Número Pedido Cliente]) -> Pedido 443 | B502: CódRastreio428 | C502: =Follow[[#This Row],[CODRASTREIO]]&" B" -> CódRastreio428 B | D502: =_xlfn.XLOOKUP(Follow[[#This Row],[Id Pedido]],Controle_Pedidos[Número Pedido Cliente],Controle_Pedidos[Loja]) -> BV | E502: =_xlfn.XLOOKUP(Follow[[#This Row],[Id Pedido]],Controle_Pedidos[Número Pedido Cliente],Controle_Pedidos[Prazo Entrega]) -> 45643 | F502: Transp 1 | G502: - | H502: China | I502: Brasil | J502: 45631.742 | K502: Entregue | L502: ENTREGUE | M502: - | N502: =IF(Follow[[#This Row],[DATAATUALIZAÇÃO]]<=Follow[[#This Row],[Prev Entrega]],"Dentro do Prazo","Fora do Prazo") -> Dentro do Prazo | O502: =_xlfn.CONCAT("Olá ",PROPER(LOWER(TRIM(LEFT(SUBSTITUTE(_xlfn.XLOOKUP(Follow[[#This Row],[Id Pedido]],Controle_Pedidos[Número Pedido Cliente],Controle_Pedidos[NOME])," ",REPT(" ",100)),100)))),", Identificamos que o Item ",_xlfn.XLOOKUP(Follow[[#This Row],[Id Pedido]],Controle_Pedidos[Número Pedido Cliente],Controle_Pedidos[Nome Produto])," foi entregue no dia ",TEXT(Follow[[#This Row],[DATAATUALIZAÇÃO]],"dd/mm/aaaa"),", referente ao pedido Nº ",Follow[[#This Row],[Id Pedido]]," Rastreio ",IF(Follow[[#This Row],[Novo Cód de Rastreio]]="-",Follow[[#This Row],[Id Pedido]],Follow[[#This Row],[Novo Cód de Rastreio]]),", agradecemos a preferência e adoraríamos receber sua avaliação, tendo qualquer dúvida estamos à disposição.",_xlfn.IFS(Follow[[#This Row],[Loja]]="bv"," Att Tem tudo Shop",Follow[[#This Row],[Loja]]="mei"," Att NTA Variedades",Follow[[#This Row],[Loja]]="go"," Att Sec Variedades")) -> Olá Nome, Identificamos que o Item Ventilador Azul foi entregue no dia 05/12/2024, referente ao pedido Nº Pedido 443 Rastreio Pedido 443, agradecemos a preferência e adoraríamos receber sua avaliação, tendo qualquer dúvida estamos à disposição. Att Tem tudo Shop
A503: =_xlfn.XLOOKUP(Follow[[#This Row],[CODRASTREIO]],Controle_Pedidos[Cód Rastreamento],Controle_Pedidos[Número Pedido Cliente]) -> Pedido 192 | B503: CódRastreio185 | C503: =Follow[[#This Row],[CODRASTREIO]]&" B" -> CódRastreio185 B | D503: =_xlfn.XLOOKUP(Follow[[#This Row],[Id Pedido]],Controle_Pedidos[Número Pedido Cliente],Controle_Pedidos[Loja]) -> BV | E503: =_xlfn.XLOOKUP(Follow[[#This Row],[Id Pedido]],Controle_Pedidos[Número Pedido Cliente],Controle_Pedidos[Prazo Entrega]) -> 45611 | F503: Transp 1 | G503: - | H503: Brasil | I503: Brasil | J503: 45607 | K503: Entregue | L503: ENTREGUE | M503: - | N503: =IF(Follow[[#This Row],[DATAATUALIZAÇÃO]]<=Follow[[#This Row],[Prev Entrega]],"Dentro do Prazo","Fora do Prazo") -> Dentro do Prazo | O503: =_xlfn.CONCAT("Olá ",PROPER(LOWER(TRIM(LEFT(SUBSTITUTE(_xlfn.XLOOKUP(Follow[[#This Row],[Id Pedido]],Controle_Pedidos[Número Pedido Cliente],Controle_Pedidos[NOME])," ",REPT(" ",100)),100)))),", Identificamos que o Item ",_xlfn.XLOOKUP(Follow[[#This Row],[Id Pedido]],Controle_Pedidos[Número Pedido Cliente],Controle_Pedidos[Nome Produto])," foi entregue no dia ",TEXT(Follow[[#This Row],[DATAATUALIZAÇÃO]],"dd/mm/aaaa"),", referente ao pedido Nº ",Follow[[#This Row],[Id Pedido]]," Rastreio ",IF(Follow[[#This Row],[Novo Cód de Rastreio]]="-",Follow[[#This Row],[Id Pedido]],Follow[[#This Row],[Novo Cód de Rastreio]]),", agradecemos a preferência e adoraríamos receber sua avaliação, tendo qualquer dúvida estamos à disposição.",_xlfn.IFS(Follow[[#This Row],[Loja]]="bv"," Att Tem tudo Shop",Follow[[#This Row],[Loja]]="mei"," Att NTA Variedades",Follow[[#This Row],[Loja]]="go"," Att Sec Variedades")) -> Olá Nome, Identificamos que o Item Bomba d'agua foi entregue no dia 11/11/2024, referente ao pedido Nº Pedido 192 Rastreio Pedido 192, agradecemos a preferência e adoraríamos receber sua avaliação, tendo qualquer dúvida estamos à disposição. Att Tem tudo Shop
A504: =_xlfn.XLOOKUP(Follow[[#This Row],[CODRASTREIO]],Controle_Pedidos[Cód Rastreamento],Controle_Pedidos[Número Pedido Cliente]) -> Pedido 591 | B504: CódRastreio576 | C504: =Follow[[#This Row],[CODRASTREIO]]&" B" -> CódRastreio576 B | D504: =_xlfn.XLOOKUP(Follow[[#This Row],[Id Pedido]],Controle_Pedidos[Número Pedido Cliente],Controle_Pedidos[Loja]) -> BV | E504: =_xlfn.XLOOKUP(Follow[[#This Row],[Id Pedido]],Controle_Pedidos[Número Pedido Cliente],Controle_Pedidos[Prazo Entrega]) -> 45678 | F504: Transp 1 | G504: - | H504: China | I504: Brasil | J504: 45659 | K504: Entregue | L504: ENTREGUE | M504: - | N504: =IF(Follow[[#This Row],[DATAATUALIZAÇÃO]]<=Follow[[#This Row],[Prev Entrega]],"Dentro do Prazo","Fora do Prazo") -> Dentro do Prazo | O504: =_xlfn.CONCAT("Olá ",PROPER(LOWER(TRIM(LEFT(SUBSTITUTE(_xlfn.XLOOKUP(Follow[[#This Row],[Id Pedido]],Controle_Pedidos[Número Pedido Cliente],Controle_Pedidos[NOME])," ",REPT(" ",100)),100)))),", Identificamos que o Item ",_xlfn.XLOOKUP(Follow[[#This Row],[Id Pedido]],Controle_Pedidos[Número Pedido Cliente],Controle_Pedidos[Nome Produto])," foi entregue no dia ",TEXT(Follow[[#This Row],[DATAATUALIZAÇÃO]],"dd/mm/aaaa"),", referente ao pedido Nº ",Follow[[#This Row],[Id Pedido]]," Rastreio ",IF(Follow[[#This Row],[Novo Cód de Rastreio]]="-",Follow[[#This Row],[Id Pedido]],Follow[[#This Row],[Novo Cód de Rastreio]]),", agradecemos a preferência e adoraríamos receber sua avaliação, tendo qualquer dúvida estamos à disposição.",_xlfn.IFS(Follow[[#This Row],[Loja]]="bv"," Att Tem tudo Shop",Follow[[#This Row],[Loja]]="mei"," Att NTA Variedades",Follow[[#This Row],[Loja]]="go"," Att Sec Variedades")) -> Olá Nome, Identificamos que o Item Ventilador de teto foi entregue no dia 02/01/2025, referente ao pedido Nº Pedido 591 Rastreio Pedido 591, agradecemos a preferência e adoraríamos receber sua avaliação, tendo qualquer dúvida estamos à disposição. Att Tem tudo Shop
A505: =_xlfn.XLOOKUP(Follow[[#This Row],[CODRASTREIO]],Controle_Pedidos[Cód Rastreamento],Controle_Pedidos[Número Pedido Cliente]) -> Pedido 425 | B505: CódRastreio412 | C505: =Follow[[#This Row],[CODRASTREIO]]&" B" -> CódRastreio412 B | D505: =_xlfn.XLOOKUP(Follow[[#This Row],[Id Pedido]],Controle_Pedidos[Número Pedido Cliente],Controle_Pedidos[Loja]) -> BV | E505: =_xlfn.XLOOKUP(Follow[[#This Row],[Id Pedido]],Controle_Pedidos[Número Pedido Cliente],Controle_Pedidos[Prazo Entrega]) -> 45632 | F505: Transp 1 | G505: - | H505: Brasil | I505: Brasil | J505: 45623 | K505: Entregue | L505: ENTREGUE | M505: - | N505: =IF(Follow[[#This Row],[DATAATUALIZAÇÃO]]<=Follow[[#This Row],[Prev Entrega]],"Dentro do Prazo","Fora do Prazo") -> Dentro do Prazo | O505: =_xlfn.CONCAT("Olá ",PROPER(LOWER(TRIM(LEFT(SUBSTITUTE(_xlfn.XLOOKUP(Follow[[#This Row],[Id Pedido]],Controle_Pedidos[Número Pedido Cliente],Controle_Pedidos[NOME])," ",REPT(" ",100)),100)))),", Identificamos que o Item ",_xlfn.XLOOKUP(Follow[[#This Row],[Id Pedido]],Controle_Pedidos[Número Pedido Cliente],Controle_Pedidos[Nome Produto])," foi entregue no dia ",TEXT(Follow[[#This Row],[DATAATUALIZAÇÃO]],"dd/mm/aaaa"),", referente ao pedido Nº ",Follow[[#This Row],[Id Pedido]]," Rastreio ",IF(Follow[[#This Row],[Novo Cód de Rastreio]]="-",Follow[[#This Row],[Id Pedido]],Follow[[#This Row],[Novo Cód de Rastreio]]),", agradecemos a preferência e adoraríamos receber sua avaliação, tendo qualquer dúvida estamos à disposição.",_xlfn.IFS(Follow[[#This Row],[Loja]]="bv"," Att Tem tudo Shop",Follow[[#This Row],[Loja]]="mei"," Att NTA Variedades",Follow[[#This Row],[Loja]]="go"," Att Sec Variedades")) -> Olá Nome, Identificamos que o Item Adaptador Bluetooph foi entregue no dia 27/11/2024, referente ao pedido Nº Pedido 425 Rastreio Pedido 425, agradecemos a preferência e adoraríamos receber sua avaliação, tendo qualquer dúvida estamos à disposição. Att Tem tudo Shop
A506: =_xlfn.XLOOKUP(Follow[[#This Row],[CODRASTREIO]],Controle_Pedidos[Cód Rastreamento],Controle_Pedidos[Número Pedido Cliente]) -> Pedido 197 | B506: CódRastreio190 | C506: =Follow[[#This Row],[CODRASTREIO]]&" B" -> CódRastreio190 B | D506: =_xlfn.XLOOKUP(Follow[[#This Row],[Id Pedido]],Controle_Pedidos[Número Pedido Cliente],Controle_Pedidos[Loja]) -> BV | E506: =_xlfn.XLOOKUP(Follow[[#This Row],[Id Pedido]],Controle_Pedidos[Número Pedido Cliente],Controle_Pedidos[Prazo Entrega]) -> 45611 | F506: Transp 1 | G506: - | H506: Brasil | I506: Brasil | J506: 45603 | K506: Entregue | L506: ENTREGUE | M506: - | N506: =IF(Follow[[#This Row],[DATAATUALIZAÇÃO]]<=Follow[[#This Row],[Prev Entrega]],"Dentro do Prazo","Fora do Prazo") -> Dentro do Prazo | O506: =_xlfn.CONCAT("Olá ",PROPER(LOWER(TRIM(LEFT(SUBSTITUTE(_xlfn.XLOOKUP(Follow[[#This Row],[Id Pedido]],Controle_Pedidos[Número Pedido Cliente],Controle_Pedidos[NOME])," ",REPT(" ",100)),100)))),", Identificamos que o Item ",_xlfn.XLOOKUP(Follow[[#This Row],[Id Pedido]],Controle_Pedidos[Número Pedido Cliente],Controle_Pedidos[Nome Produto])," foi entregue no dia ",TEXT(Follow[[#This Row],[DATAATUALIZAÇÃO]],"dd/mm/aaaa"),", referente ao pedido Nº ",Follow[[#This Row],[Id Pedido]]," Rastreio ",IF(Follow[[#This Row],[Novo Cód de Rastreio]]="-",Follow[[#This Row],[Id Pedido]],Follow[[#This Row],[Novo Cód de Rastreio]]),", agradecemos a preferência e adoraríamos receber sua avaliação, tendo qualquer dúvida estamos à disposição.",_xlfn.IFS(Follow[[#This Row],[Loja]]="bv"," Att Tem tudo Shop",Follow[[#This Row],[Loja]]="mei"," Att NTA Variedades",Follow[[#This Row],[Loja]]="go"," Att Sec Variedades")) -> Olá Nome, Identificamos que o Item Bomba d'agua foi entregue no dia 07/11/2024, referente ao pedido Nº Pedido 197 Rastreio Pedido 197, agradecemos a preferência e adoraríamos receber sua avaliação, tendo qualquer dúvida estamos à disposição. Att Tem tudo Shop
A507: =_xlfn.XLOOKUP(Follow[[#This Row],[CODRASTREIO]],Controle_Pedidos[Cód Rastreamento],Controle_Pedidos[Número Pedido Cliente]) -> Pedido 101 | B507: CódRastreio94 | C507: =Follow[[#This Row],[CODRASTREIO]]&" B" -> CódRastreio94 B | D507: =_xlfn.XLOOKUP(Follow[[#This Row],[Id Pedido]],Controle_Pedidos[Número Pedido Cliente],Controle_Pedidos[Loja]) -> BV | E507: =_xlfn.XLOOKUP(Follow[[#This Row],[Id Pedido]],Controle_Pedidos[Número Pedido Cliente],Controle_Pedidos[Prazo Entrega]) -> 45617 | F507: Transp 1 | G507: - | H507: Brasil | I507: Brasil | J507: 45598 | K507: Entregue | L507: ENTREGUE | M507: - | N507: =IF(Follow[[#This Row],[DATAATUALIZAÇÃO]]<=Follow[[#This Row],[Prev Entrega]],"Dentro do Prazo","Fora do Prazo") -> Dentro do Prazo | O507: =_xlfn.CONCAT("Olá ",PROPER(LOWER(TRIM(LEFT(SUBSTITUTE(_xlfn.XLOOKUP(Follow[[#This Row],[Id Pedido]],Controle_Pedidos[Número Pedido Cliente],Controle_Pedidos[NOME])," ",REPT(" ",100)),100)))),", Identificamos que o Item ",_xlfn.XLOOKUP(Follow[[#This Row],[Id Pedido]],Controle_Pedidos[Número Pedido Cliente],Controle_Pedidos[Nome Produto])," foi entregue no dia ",TEXT(Follow[[#This Row],[DATAATUALIZAÇÃO]],"dd/mm/aaaa"),", referente ao pedido Nº ",Follow[[#This Row],[Id Pedido]]," Rastreio ",IF(Follow[[#This Row],[Novo Cód de Rastreio]]="-",Follow[[#This Row],[Id Pedido]],Follow[[#This Row],[Novo Cód de Rastreio]]),", agradecemos a preferência e adoraríamos receber sua avaliação, tendo qualquer dúvida estamos à disposição.",_xlfn.IFS(Follow[[#This Row],[Loja]]="bv"," Att Tem tudo Shop",Follow[[#This Row],[Loja]]="mei"," Att NTA Variedades",Follow[[#This Row],[Loja]]="go"," Att Sec Variedades")) -> Olá Nome, Identificamos que o Item Suporte de Celular Preto foi entregue no dia 02/11/2024, referente ao pedido Nº Pedido 101 Rastreio Pedido 101, agradecemos a preferência e adoraríamos receber sua avaliação, tendo qualquer dúvida estamos à disposição. Att Tem tudo Shop
A508: =_xlfn.XLOOKUP(Follow[[#This Row],[CODRASTREIO]],Controle_Pedidos[Cód Rastreamento],Controle_Pedidos[Número Pedido Cliente]) -> Pedido 44 | B508: CódRastreio35 | C508: =Follow[[#This Row],[CODRASTREIO]]&" B" -> CódRastreio35 B | D508: =_xlfn.XLOOKUP(Follow[[#This Row],[Id Pedido]],Controle_Pedidos[Número Pedido Cliente],Controle_Pedidos[Loja]) -> BV | E508: =_xlfn.XLOOKUP(Follow[[#This Row],[Id Pedido]],Controle_Pedidos[Número Pedido Cliente],Controle_Pedidos[Prazo Entrega]) -> 45608 | F508: Transp 1 | G508: - | H508: Brasil | I508: Brasil | J508: 45593 | K508: Entregue | L508: ENTREGUE | M508: - | N508: =IF(Follow[[#This Row],[DATAATUALIZAÇÃO]]<=Follow[[#This Row],[Prev Entrega]],"Dentro do Prazo","Fora do Prazo") -> Dentro do Prazo | O508: =_xlfn.CONCAT("Olá ",PROPER(LOWER(TRIM(LEFT(SUBSTITUTE(_xlfn.XLOOKUP(Follow[[#This Row],[Id Pedido]],Controle_Pedidos[Número Pedido Cliente],Controle_Pedidos[NOME])," ",REPT(" ",100)),100)))),", Identificamos que o Item ",_xlfn.XLOOKUP(Follow[[#This Row],[Id Pedido]],Controle_Pedidos[Número Pedido Cliente],Controle_Pedidos[Nome Produto])," foi entregue no dia ",TEXT(Follow[[#This Row],[DATAATUALIZAÇÃO]],"dd/mm/aaaa"),", referente ao pedido Nº ",Follow[[#This Row],[Id Pedido]]," Rastreio ",IF(Follow[[#This Row],[Novo Cód de Rastreio]]="-",Follow[[#This Row],[Id Pedido]],Follow[[#This Row],[Novo Cód de Rastreio]]),", agradecemos a preferência e adoraríamos receber sua avaliação, tendo qualquer dúvida estamos à disposição.",_xlfn.IFS(Follow[[#This Row],[Loja]]="bv"," Att Tem tudo Shop",Follow[[#This Row],[Loja]]="mei"," Att NTA Variedades",Follow[[#This Row],[Loja]]="go"," Att Sec Variedades")) -> Olá Nome, Identificamos que o Item Suporte de Celular Preto foi entregue no dia 28/10/2024, referente ao pedido Nº Pedido 44 Rastreio Pedido 44, agradecemos a preferência e adoraríamos receber sua avaliação, tendo qualquer dúvida estamos à disposição. Att Tem tudo Shop
A509: =_xlfn.XLOOKUP(Follow[[#This Row],[CODRASTREIO]],Controle_Pedidos[Cód Rastreamento],Controle_Pedidos[Número Pedido Cliente]) -> Pedido 91 | B509: CódRastreio84 | C509: =Follow[[#This Row],[CODRASTREIO]]&" B" -> CódRastreio84 B | D509: =_xlfn.XLOOKUP(Follow[[#This Row],[Id Pedido]],Controle_Pedidos[Número Pedido Cliente],Controle_Pedidos[Loja]) -> BV | E509: =_xlfn.XLOOKUP(Follow[[#This Row],[Id Pedido]],Controle_Pedidos[Número Pedido Cliente],Controle_Pedidos[Prazo Entrega]) -> 45617 | F509: Transp 1 | G509: - | H509: Brasil | I509: Brasil | J509: 45601 | K509: Entregue | L509: ENTREGUE | M509: - | N509: =IF(Follow[[#This Row],[DATAATUALIZAÇÃO]]<=Follow[[#This Row],[Prev Entrega]],"Dentro do Prazo","Fora do Prazo") -> Dentro do Prazo | O509: =_xlfn.CONCAT("Olá ",PROPER(LOWER(TRIM(LEFT(SUBSTITUTE(_xlfn.XLOOKUP(Follow[[#This Row],[Id Pedido]],Controle_Pedidos[Número Pedido Cliente],Controle_Pedidos[NOME])," ",REPT(" ",100)),100)))),", Identificamos que o Item ",_xlfn.XLOOKUP(Follow[[#This Row],[Id Pedido]],Controle_Pedidos[Número Pedido Cliente],Controle_Pedidos[Nome Produto])," foi entregue no dia ",TEXT(Follow[[#This Row],[DATAATUALIZAÇÃO]],"dd/mm/aaaa"),", referente ao pedido Nº ",Follow[[#This Row],[Id Pedido]]," Rastreio ",IF(Follow[[#This Row],[Novo Cód de Rastreio]]="-",Follow[[#This Row],[Id Pedido]],Follow[[#This Row],[Novo Cód de Rastreio]]),", agradecemos a preferência e adoraríamos receber sua avaliação, tendo qualquer dúvida estamos à disposição.",_xlfn.IFS(Follow[[#This Row],[Loja]]="bv"," Att Tem tudo Shop",Follow[[#This Row],[Loja]]="mei"," Att NTA Variedades",Follow[[#This Row],[Loja]]="go"," Att Sec Variedades")) -> Olá Nome, Identificamos que o Item Suporte de Celular Branco foi entregue no dia 05/11/2024, referente ao pedido Nº Pedido 91 Rastreio Pedido 91, agradecemos a preferência e adoraríamos receber sua avaliação, tendo qualquer dúvida estamos à disposição. Att Tem tudo Shop
A510: =_xlfn.XLOOKUP(Follow[[#This Row],[CODRASTREIO]],Controle_Pedidos[Cód Rastreamento],Controle_Pedidos[Número Pedido Cliente]) -> Pedido 431 | B510: CódRastreio417 | C510: =Follow[[#This Row],[CODRASTREIO]]&" B" -> CódRastreio417 B | D510: =_xlfn.XLOOKUP(Follow[[#This Row],[Id Pedido]],Controle_Pedidos[Número Pedido Cliente],Controle_Pedidos[Loja]) -> BV | E510: =_xlfn.XLOOKUP(Follow[[#This Row],[Id Pedido]],Controle_Pedidos[Número Pedido Cliente],Controle_Pedidos[Prazo Entrega]) -> 45646 | F510: Transp 1 | G510: - | H510: China | I510: Brasil | J510: 45638 | K510: Entregue | L510: ENTREGUE | M510: - | N510: =IF(Follow[[#This Row],[DATAATUALIZAÇÃO]]<=Follow[[#This Row],[Prev Entrega]],"Dentro do Prazo","Fora do Prazo") -> Dentro do Prazo | O510: =_xlfn.CONCAT("Olá ",PROPER(LOWER(TRIM(LEFT(SUBSTITUTE(_xlfn.XLOOKUP(Follow[[#This Row],[Id Pedido]],Controle_Pedidos[Número Pedido Cliente],Controle_Pedidos[NOME])," ",REPT(" ",100)),100)))),", Identificamos que o Item ",_xlfn.XLOOKUP(Follow[[#This Row],[Id Pedido]],Controle_Pedidos[Número Pedido Cliente],Controle_Pedidos[Nome Produto])," foi entregue no dia ",TEXT(Follow[[#This Row],[DATAATUALIZAÇÃO]],"dd/mm/aaaa"),", referente ao pedido Nº ",Follow[[#This Row],[Id Pedido]]," Rastreio ",IF(Follow[[#This Row],[Novo Cód de Rastreio]]="-",Follow[[#This Row],[Id Pedido]],Follow[[#This Row],[Novo Cód de Rastreio]]),", agradecemos a preferência e adoraríamos receber sua avaliação, tendo qualquer dúvida estamos à disposição.",_xlfn.IFS(Follow[[#This Row],[Loja]]="bv"," Att Tem tudo Shop",Follow[[#This Row],[Loja]]="mei"," Att NTA Variedades",Follow[[#This Row],[Loja]]="go"," Att Sec Variedades")) -> Olá Nome, Identificamos que o Item Ventilador Preto foi entregue no dia 12/12/2024, referente ao pedido Nº Pedido 431 Rastreio Pedido 431, agradecemos a preferência e adoraríamos receber sua avaliação, tendo qualquer dúvida estamos à disposição. Att Tem tudo Shop
A511: =_xlfn.XLOOKUP(Follow[[#This Row],[CODRASTREIO]],Controle_Pedidos[Cód Rastreamento],Controle_Pedidos[Número Pedido Cliente]) -> Pedido 569 | B511: CódRastreio554 | C511: =Follow[[#This Row],[CODRASTREIO]]&" B" -> CódRastreio554 B | D511: =_xlfn.XLOOKUP(Follow[[#This Row],[Id Pedido]],Controle_Pedidos[Número Pedido Cliente],Controle_Pedidos[Loja]) -> BV | E511: =_xlfn.XLOOKUP(Follow[[#This Row],[Id Pedido]],Controle_Pedidos[Número Pedido Cliente],Controle_Pedidos[Prazo Entrega]) -> 45666 | F511: Transp 1 | G511: - | H511: Brasil | I511: Brasil | J511: 45645 | K511: Entregue | L511: ENTREGUE | M511: - | N511: =IF(Follow[[#This Row],[DATAATUALIZAÇÃO]]<=Follow[[#This Row],[Prev Entrega]],"Dentro do Prazo","Fora do Prazo") -> Dentro do Prazo | O511: =_xlfn.CONCAT("Olá ",PROPER(LOWER(TRIM(LEFT(SUBSTITUTE(_xlfn.XLOOKUP(Follow[[#This Row],[Id Pedido]],Controle_Pedidos[Número Pedido Cliente],Controle_Pedidos[NOME])," ",REPT(" ",100)),100)))),", Identificamos que o Item ",_xlfn.XLOOKUP(Follow[[#This Row],[Id Pedido]],Controle_Pedidos[Número Pedido Cliente],Controle_Pedidos[Nome Produto])," foi entregue no dia ",TEXT(Follow[[#This Row],[DATAATUALIZAÇÃO]],"dd/mm/aaaa"),", referente ao pedido Nº ",Follow[[#This Row],[Id Pedido]]," Rastreio ",IF(Follow[[#This Row],[Novo Cód de Rastreio]]="-",Follow[[#This Row],[Id Pedido]],Follow[[#This Row],[Novo Cód de Rastreio]]),", agradecemos a preferência e adoraríamos receber sua avaliação, tendo qualquer dúvida estamos à disposição.",_xlfn.IFS(Follow[[#This Row],[Loja]]="bv"," Att Tem tudo Shop",Follow[[#This Row],[Loja]]="mei"," Att NTA Variedades",Follow[[#This Row],[Loja]]="go"," Att Sec Variedades")) -> Olá Nome, Identificamos que o Item Copo Termico foi entregue no dia 19/12/2024, referente ao pedido Nº Pedido 569 Rastreio Pedido 569, agradecemos a preferência e adoraríamos receber sua avaliação, tendo qualquer dúvida estamos à disposição. Att Tem tudo Shop
A512: =_xlfn.XLOOKUP(Follow[[#This Row],[CODRASTREIO]],Controle_Pedidos[Cód Rastreamento],Controle_Pedidos[Número Pedido Cliente]) -> Pedido 165 | B512: CódRastreio158 | C512: =Follow[[#This Row],[CODRASTREIO]]&" B" -> CódRastreio158 B | D512: =_xlfn.XLOOKUP(Follow[[#This Row],[Id Pedido]],Controle_Pedidos[Número Pedido Cliente],Controle_Pedidos[Loja]) -> BV | E512: =_xlfn.XLOOKUP(Follow[[#This Row],[Id Pedido]],Controle_Pedidos[Número Pedido Cliente],Controle_Pedidos[Prazo Entrega]) -> 45622 | F512: Transp 1 | G512: - | H512: China | I512: Brasil | J512: 45607 | K512: Entregue | L512: ENTREGUE | M512: - | N512: =IF(Follow[[#This Row],[DATAATUALIZAÇÃO]]<=Follow[[#This Row],[Prev Entrega]],"Dentro do Prazo","Fora do Prazo") -> Dentro do Prazo | O512: =_xlfn.CONCAT("Olá ",PROPER(LOWER(TRIM(LEFT(SUBSTITUTE(_xlfn.XLOOKUP(Follow[[#This Row],[Id Pedido]],Controle_Pedidos[Número Pedido Cliente],Controle_Pedidos[NOME])," ",REPT(" ",100)),100)))),", Identificamos que o Item ",_xlfn.XLOOKUP(Follow[[#This Row],[Id Pedido]],Controle_Pedidos[Número Pedido Cliente],Controle_Pedidos[Nome Produto])," foi entregue no dia ",TEXT(Follow[[#This Row],[DATAATUALIZAÇÃO]],"dd/mm/aaaa"),", referente ao pedido Nº ",Follow[[#This Row],[Id Pedido]]," Rastreio ",IF(Follow[[#This Row],[Novo Cód de Rastreio]]="-",Follow[[#This Row],[Id Pedido]],Follow[[#This Row],[Novo Cód de Rastreio]]),", agradecemos a preferência e adoraríamos receber sua avaliação, tendo qualquer dúvida estamos à disposição.",_xlfn.IFS(Follow[[#This Row],[Loja]]="bv"," Att Tem tudo Shop",Follow[[#This Row],[Loja]]="mei"," Att NTA Variedades",Follow[[#This Row],[Loja]]="go"," Att Sec Variedades")) -> Olá Nome, Identificamos que o Item Ventilador de teto foi entregue no dia 11/11/2024, referente ao pedido Nº Pedido 165 Rastreio Pedido 165, agradecemos a preferência e adoraríamos receber sua avaliação, tendo qualquer dúvida estamos à disposição. Att Tem tudo Shop
A513: =_xlfn.XLOOKUP(Follow[[#This Row],[CODRASTREIO]],Controle_Pedidos[Cód Rastreamento],Controle_Pedidos[Número Pedido Cliente]) -> Pedido 166 | B513: CódRastreio159 | C513: =Follow[[#This Row],[CODRASTREIO]]&" B" -> CódRastreio159 B | D513: =_xlfn.XLOOKUP(Follow[[#This Row],[Id Pedido]],Controle_Pedidos[Número Pedido Cliente],Controle_Pedidos[Loja]) -> BV | E513: =_xlfn.XLOOKUP(Follow[[#This Row],[Id Pedido]],Controle_Pedidos[Número Pedido Cliente],Controle_Pedidos[Prazo Entrega]) -> 45622 | F513: Transp 1 | G513: - | H513: China | I513: Brasil | J513: 45610 | K513: Entregue | L513: ENTREGUE | M513: - | N513: =IF(Follow[[#This Row],[DATAATUALIZAÇÃO]]<=Follow[[#This Row],[Prev Entrega]],"Dentro do Prazo","Fora do Prazo") -> Dentro do Prazo | O513: =_xlfn.CONCAT("Olá ",PROPER(LOWER(TRIM(LEFT(SUBSTITUTE(_xlfn.XLOOKUP(Follow[[#This Row],[Id Pedido]],Controle_Pedidos[Número Pedido Cliente],Controle_Pedidos[NOME])," ",REPT(" ",100)),100)))),", Identificamos que o Item ",_xlfn.XLOOKUP(Follow[[#This Row],[Id Pedido]],Controle_Pedidos[Número Pedido Cliente],Controle_Pedidos[Nome Produto])," foi entregue no dia ",TEXT(Follow[[#This Row],[DATAATUALIZAÇÃO]],"dd/mm/aaaa"),", referente ao pedido Nº ",Follow[[#This Row],[Id Pedido]]," Rastreio ",IF(Follow[[#This Row],[Novo Cód de Rastreio]]="-",Follow[[#This Row],[Id Pedido]],Follow[[#This Row],[Novo Cód de Rastreio]]),", agradecemos a preferência e adoraríamos receber sua avaliação, tendo qualquer dúvida estamos à disposição.",_xlfn.IFS(Follow[[#This Row],[Loja]]="bv"," Att Tem tudo Shop",Follow[[#This Row],[Loja]]="mei"," Att NTA Variedades",Follow[[#This Row],[Loja]]="go"," Att Sec Variedades")) -> Olá Nome, Identificamos que o Item Ventilador de teto foi entregue no dia 14/11/2024, referente ao pedido Nº Pedido 166 Rastreio Pedido 166, agradecemos a preferência e adoraríamos receber sua avaliação, tendo qualquer dúvida estamos à disposição. Att Tem tudo Shop
... A526: =_xlfn.XLOOKUP(Follow[[#This Row],[CODRASTREIO]],Controle_Pedidos[Cód Rastreamento],Controle_Pedidos[Número Pedido Cliente]) -> Pedido 436 | B526: CódRastreio422 | C526: =Follow[[#This Row],[CODRASTREIO]]&" B" -> CódRastreio422 B | D526: =_xlfn.XLOOKUP(Follow[[#This Row],[Id Pedido]],Controle_Pedidos[Número Pedido Cliente],Controle_Pedidos[Loja]) -> BV | E526: =_xlfn.XLOOKUP(Follow[[#This Row],[Id Pedido]],Controle_Pedidos[Número Pedido Cliente],Controle_Pedidos[Prazo Entrega]) -> 45646 | F526: Transp 1 | G526: - | H526: China | I526: Brasil | J526: 45637 | K526: Entregue | L526: ENTREGUE | M526: - | N526: =IF(Follow[[#This Row],[DATAATUALIZAÇÃO]]<=Follow[[#This Row],[Prev Entrega]],"Dentro do Prazo","Fora do Prazo") -> Dentro do Prazo | O526: =_xlfn.CONCAT("Olá ",PROPER(LOWER(TRIM(LEFT(SUBSTITUTE(_xlfn.XLOOKUP(Follow[[#This Row],[Id Pedido]],Controle_Pedidos[Número Pedido Cliente],Controle_Pedidos[NOME])," ",REPT(" ",100)),100)))),", Identificamos que o Item ",_xlfn.XLOOKUP(Follow[[#This Row],[Id Pedido]],Controle_Pedidos[Número Pedido Cliente],Controle_Pedidos[Nome Produto])," foi entregue no dia ",TEXT(Follow[[#This Row],[DATAATUALIZAÇÃO]],"dd/mm/aaaa"),", referente ao pedido Nº ",Follow[[#This Row],[Id Pedido]]," Rastreio ",IF(Follow[[#This Row],[Novo Cód de Rastreio]]="-",Follow[[#This Row],[Id Pedido]],Follow[[#This Row],[Novo Cód de Rastreio]]),", agradecemos a preferência e adoraríamos receber sua avaliação, tendo qualquer dúvida estamos à disposição.",_xlfn.IFS(Follow[[#This Row],[Loja]]="bv"," Att Tem tudo Shop",Follow[[#This Row],[Loja]]="mei"," Att NTA Variedades",Follow[[#This Row],[Loja]]="go"," Att Sec Variedades")) -> Olá Nome, Identificamos que o Item Ventilador Preto foi entregue no dia 11/12/2024, referente ao pedido Nº Pedido 436 Rastreio Pedido 436, agradecemos a preferência e adoraríamos receber sua avaliação, tendo qualquer dúvida estamos à disposição. Att Tem tudo Shop
A527: Pedido 488 | B527: CódRastreio473 1 Envio | C527: =Follow[[#This Row],[CODRASTREIO]]&" B" -> CódRastreio473 1 Envio B | D527: BV | E527: 45666 | F527: Transp 1 | G527: - | H527: China | I527: Brasil | J527: 45660 | K527: Entregue | L527: ENTREGUE | M527: - | N527: =IF(Follow[[#This Row],[DATAATUALIZAÇÃO]]<=Follow[[#This Row],[Prev Entrega]],"Dentro do Prazo","Fora do Prazo") -> Dentro do Prazo | O527: =_xlfn.CONCAT("Olá ",PROPER(LOWER(TRIM(LEFT(SUBSTITUTE(_xlfn.XLOOKUP(Follow[[#This Row],[Id Pedido]],Controle_Pedidos[Número Pedido Cliente],Controle_Pedidos[NOME])," ",REPT(" ",100)),100)))),", Identificamos que o Item ",_xlfn.XLOOKUP(Follow[[#This Row],[Id Pedido]],Controle_Pedidos[Número Pedido Cliente],Controle_Pedidos[Nome Produto])," foi entregue no dia ",TEXT(Follow[[#This Row],[DATAATUALIZAÇÃO]],"dd/mm/aaaa"),", referente ao pedido Nº ",Follow[[#This Row],[Id Pedido]]," Rastreio ",IF(Follow[[#This Row],[Novo Cód de Rastreio]]="-",Follow[[#This Row],[Id Pedido]],Follow[[#This Row],[Novo Cód de Rastreio]]),", agradecemos a preferência e adoraríamos receber sua avaliação, tendo qualquer dúvida estamos à disposição.",_xlfn.IFS(Follow[[#This Row],[Loja]]="bv"," Att Tem tudo Shop",Follow[[#This Row],[Loja]]="mei"," Att NTA Variedades",Follow[[#This Row],[Loja]]="go"," Att Sec Variedades")) -> Olá Nome, Identificamos que o Item Ventilador Preto foi entregue no dia 03/01/2025, referente ao pedido Nº Pedido 488 Rastreio Pedido 488, agradecemos a preferência e adoraríamos receber sua avaliação, tendo qualquer dúvida estamos à disposição. Att Tem tudo Shop
A528: =_xlfn.XLOOKUP(Follow[[#This Row],[CODRASTREIO]],Controle_Pedidos[Cód Rastreamento],Controle_Pedidos[Número Pedido Cliente]) -> Pedido 488 | B528: CódRastreio473 | C528: =Follow[[#This Row],[CODRASTREIO]]&" B" -> CódRastreio473 B | D528: =_xlfn.XLOOKUP(Follow[[#This Row],[Id Pedido]],Controle_Pedidos[Número Pedido Cliente],Controle_Pedidos[Loja]) -> BV | E528: =_xlfn.XLOOKUP(Follow[[#This Row],[Id Pedido]],Controle_Pedidos[Número Pedido Cliente],Controle_Pedidos[Prazo Entrega]) -> 45666 | F528: Transp 1 | G528: - | H528: China | I528: Brasil | J528: 45660 | K528: Entregue | L528: ENTREGUE | M528: - | N528: =IF(Follow[[#This Row],[DATAATUALIZAÇÃO]]<=Follow[[#This Row],[Prev Entrega]],"Dentro do Prazo","Fora do Prazo") -> Dentro do Prazo | O528: =_xlfn.CONCAT("Olá ",PROPER(LOWER(TRIM(LEFT(SUBSTITUTE(_xlfn.XLOOKUP(Follow[[#This Row],[Id Pedido]],Controle_Pedidos[Número Pedido Cliente],Controle_Pedidos[NOME])," ",REPT(" ",100)),100)))),", Identificamos que o Item ",_xlfn.XLOOKUP(Follow[[#This Row],[Id Pedido]],Controle_Pedidos[Número Pedido Cliente],Controle_Pedidos[Nome Produto])," foi entregue no dia ",TEXT(Follow[[#This Row],[DATAATUALIZAÇÃO]],"dd/mm/aaaa"),", referente ao pedido Nº ",Follow[[#This Row],[Id Pedido]]," Rastreio ",IF(Follow[[#This Row],[Novo Cód de Rastreio]]="-",Follow[[#This Row],[Id Pedido]],Follow[[#This Row],[Novo Cód de Rastreio]]),", agradecemos a preferência e adoraríamos receber sua avaliação, tendo qualquer dúvida estamos à disposição.",_xlfn.IFS(Follow[[#This Row],[Loja]]="bv"," Att Tem tudo Shop",Follow[[#This Row],[Loja]]="mei"," Att NTA Variedades",Follow[[#This Row],[Loja]]="go"," Att Sec Variedades")) -> Olá Nome, Identificamos que o Item Ventilador Preto foi entregue no dia 03/01/2025, referente ao pedido Nº Pedido 488 Rastreio Pedido 488, agradecemos a preferência e adoraríamos receber sua avaliação, tendo qualquer dúvida estamos à disposição. Att Tem tudo Shop
A529: =_xlfn.XLOOKUP(Follow[[#This Row],[CODRASTREIO]],Controle_Pedidos[Cód Rastreamento],Controle_Pedidos[Número Pedido Cliente]) -> Pedido 293 | B529: CódRastreio286 | C529: =Follow[[#This Row],[CODRASTREIO]]&" B" -> CódRastreio286 B | D529: =_xlfn.XLOOKUP(Follow[[#This Row],[Id Pedido]],Controle_Pedidos[Número Pedido Cliente],Controle_Pedidos[Loja]) -> BV | E529: =_xlfn.XLOOKUP(Follow[[#This Row],[Id Pedido]],Controle_Pedidos[Número Pedido Cliente],Controle_Pedidos[Prazo Entrega]) -> 45624 | F529: Transp 1 | G529: - | H529: China | I529: Brasil | J529: 45610 | K529: Entregue | L529: ENTREGUE | M529: - | N529: =IF(Follow[[#This Row],[DATAATUALIZAÇÃO]]<=Follow[[#This Row],[Prev Entrega]],"Dentro do Prazo","Fora do Prazo") -> Dentro do Prazo | O529: =_xlfn.CONCAT("Olá ",PROPER(LOWER(TRIM(LEFT(SUBSTITUTE(_xlfn.XLOOKUP(Follow[[#This Row],[Id Pedido]],Controle_Pedidos[Número Pedido Cliente],Controle_Pedidos[NOME])," ",REPT(" ",100)),100)))),", Identificamos que o Item ",_xlfn.XLOOKUP(Follow[[#This Row],[Id Pedido]],Controle_Pedidos[Número Pedido Cliente],Controle_Pedidos[Nome Produto])," foi entregue no dia ",TEXT(Follow[[#This Row],[DATAATUALIZAÇÃO]],"dd/mm/aaaa"),", referente ao pedido Nº ",Follow[[#This Row],[Id Pedido]]," Rastreio ",IF(Follow[[#This Row],[Novo Cód de Rastreio]]="-",Follow[[#This Row],[Id Pedido]],Follow[[#This Row],[Novo Cód de Rastreio]]),", agradecemos a preferência e adoraríamos receber sua avaliação, tendo qualquer dúvida estamos à disposição.",_xlfn.IFS(Follow[[#This Row],[Loja]]="bv"," Att Tem tudo Shop",Follow[[#This Row],[Loja]]="mei"," Att NTA Variedades",Follow[[#This Row],[Loja]]="go"," Att Sec Variedades")) -> Olá Nome, Identificamos que o Item Ventilador Preto foi entregue no dia 14/11/2024, referente ao pedido Nº Pedido 293 Rastreio Pedido 293, agradecemos a preferência e adoraríamos receber sua avaliação, tendo qualquer dúvida estamos à disposição. Att Tem tudo Shop
A530: =_xlfn.XLOOKUP(Follow[[#This Row],[CODRASTREIO]],Controle_Pedidos[Cód Rastreamento],Controle_Pedidos[Número Pedido Cliente]) -> Pedido 570 | B530: CódRastreio555 | C530: =Follow[[#This Row],[CODRASTREIO]]&" B" -> CódRastreio555 B | D530: =_xlfn.XLOOKUP(Follow[[#This Row],[Id Pedido]],Controle_Pedidos[Número Pedido Cliente],Controle_Pedidos[Loja]) -> BV | E530: =_xlfn.XLOOKUP(Follow[[#This Row],[Id Pedido]],Controle_Pedidos[Número Pedido Cliente],Controle_Pedidos[Prazo Entrega]) -> 45666 | F530: Transp 1 | G530: - | H530: China | I530: Brasil | J530: 45653 | K530: Entregue | L530: ENTREGUE | M530: - | N530: =IF(Follow[[#This Row],[DATAATUALIZAÇÃO]]<=Follow[[#This Row],[Prev Entrega]],"Dentro do Prazo","Fora do Prazo") -> Dentro do Prazo | O530: =_xlfn.CONCAT("Olá ",PROPER(LOWER(TRIM(LEFT(SUBSTITUTE(_xlfn.XLOOKUP(Follow[[#This Row],[Id Pedido]],Controle_Pedidos[Número Pedido Cliente],Controle_Pedidos[NOME])," ",REPT(" ",100)),100)))),", Identificamos que o Item ",_xlfn.XLOOKUP(Follow[[#This Row],[Id Pedido]],Controle_Pedidos[Número Pedido Cliente],Controle_Pedidos[Nome Produto])," foi entregue no dia ",TEXT(Follow[[#This Row],[DATAATUALIZAÇÃO]],"dd/mm/aaaa"),", referente ao pedido Nº ",Follow[[#This Row],[Id Pedido]]," Rastreio ",IF(Follow[[#This Row],[Novo Cód de Rastreio]]="-",Follow[[#This Row],[Id Pedido]],Follow[[#This Row],[Novo Cód de Rastreio]]),", agradecemos a preferência e adoraríamos receber sua avaliação, tendo qualquer dúvida estamos à disposição.",_xlfn.IFS(Follow[[#This Row],[Loja]]="bv"," Att Tem tudo Shop",Follow[[#This Row],[Loja]]="mei"," Att NTA Variedades",Follow[[#This Row],[Loja]]="go"," Att Sec Variedades")) -> Olá Nome, Identificamos que o Item Ventilador Azul foi entregue no dia 27/12/2024, referente ao pedido Nº Pedido 570 Rastreio Pedido 570, agradecemos a preferência e adoraríamos receber sua avaliação, tendo qualquer dúvida estamos à disposição. Att Tem tudo Shop
A531: =_xlfn.XLOOKUP(Follow[[#This Row],[CODRASTREIO]],Controle_Pedidos[Cód Rastreamento],Controle_Pedidos[Número Pedido Cliente]) -> Pedido 144 | B531: CódRastreio137 | C531: =Follow[[#This Row],[CODRASTREIO]]&" B" -> CódRastreio137 B | D531: =_xlfn.XLOOKUP(Follow[[#This Row],[Id Pedido]],Controle_Pedidos[Número Pedido Cliente],Controle_Pedidos[Loja]) -> BV | E531: =_xlfn.XLOOKUP(Follow[[#This Row],[Id Pedido]],Controle_Pedidos[Número Pedido Cliente],Controle_Pedidos[Prazo Entrega]) -> 45605 | F531: Transp 1 | G531: - | H531: Brasil | I531: Brasil | J531: 45596 | K531: Entregue | L531: ENTREGUE | M531: - | N531: =IF(Follow[[#This Row],[DATAATUALIZAÇÃO]]<=Follow[[#This Row],[Prev Entrega]],"Dentro do Prazo","Fora do Prazo") -> Dentro do Prazo | O531: =_xlfn.CONCAT("Olá ",PROPER(LOWER(TRIM(LEFT(SUBSTITUTE(_xlfn.XLOOKUP(Follow[[#This Row],[Id Pedido]],Controle_Pedidos[Número Pedido Cliente],Controle_Pedidos[NOME])," ",REPT(" ",100)),100)))),", Identificamos que o Item ",_xlfn.XLOOKUP(Follow[[#This Row],[Id Pedido]],Controle_Pedidos[Número Pedido Cliente],Controle_Pedidos[Nome Produto])," foi entregue no dia ",TEXT(Follow[[#This Row],[DATAATUALIZAÇÃO]],"dd/mm/aaaa"),", referente ao pedido Nº ",Follow[[#This Row],[Id Pedido]]," Rastreio ",IF(Follow[[#This Row],[Novo Cód de Rastreio]]="-",Follow[[#This Row],[Id Pedido]],Follow[[#This Row],[Novo Cód de Rastreio]]),", agradecemos a preferência e adoraríamos receber sua avaliação, tendo qualquer dúvida estamos à disposição.",_xlfn.IFS(Follow[[#This Row],[Loja]]="bv"," Att Tem tudo Shop",Follow[[#This Row],[Loja]]="mei"," Att NTA Variedades",Follow[[#This Row],[Loja]]="go"," Att Sec Variedades")) -> Olá Nome, Identificamos que o Item Mini Liquidificador foi entregue no dia 31/10/2024, referente ao pedido Nº Pedido 144 Rastreio Pedido 144, agradecemos a preferência e adoraríamos receber sua avaliação, tendo qualquer dúvida estamos à disposição. Att Tem tudo Shop
A532: =_xlfn.XLOOKUP(Follow[[#This Row],[CODRASTREIO]],Controle_Pedidos[Cód Rastreamento],Controle_Pedidos[Número Pedido Cliente]) -> Pedido 578 | B532: CódRastreio563 | C532: =Follow[[#This Row],[CODRASTREIO]]&" B" -> CódRastreio563 B | D532: =_xlfn.XLOOKUP(Follow[[#This Row],[Id Pedido]],Controle_Pedidos[Número Pedido Cliente],Controle_Pedidos[Loja]) -> BV | E532: =_xlfn.XLOOKUP(Follow[[#This Row],[Id Pedido]],Controle_Pedidos[Número Pedido Cliente],Controle_Pedidos[Prazo Entrega]) -> 45667 | F532: Transp 1 | G532: - | H532: China | I532: Brasil | J532: 45659 | K532: Entregue | L532: ENTREGUE | M532: - | N532: =IF(Follow[[#This Row],[DATAATUALIZAÇÃO]]<=Follow[[#This Row],[Prev Entrega]],"Dentro do Prazo","Fora do Prazo") -> Dentro do Prazo | O532: =_xlfn.CONCAT("Olá ",PROPER(LOWER(TRIM(LEFT(SUBSTITUTE(_xlfn.XLOOKUP(Follow[[#This Row],[Id Pedido]],Controle_Pedidos[Número Pedido Cliente],Controle_Pedidos[NOME])," ",REPT(" ",100)),100)))),", Identificamos que o Item ",_xlfn.XLOOKUP(Follow[[#This Row],[Id Pedido]],Controle_Pedidos[Número Pedido Cliente],Controle_Pedidos[Nome Produto])," foi entregue no dia ",TEXT(Follow[[#This Row],[DATAATUALIZAÇÃO]],"dd/mm/aaaa"),", referente ao pedido Nº ",Follow[[#This Row],[Id Pedido]]," Rastreio ",IF(Follow[[#This Row],[Novo Cód de Rastreio]]="-",Follow[[#This Row],[Id Pedido]],Follow[[#This Row],[Novo Cód de Rastreio]]),", agradecemos a preferência e adoraríamos receber sua avaliação, tendo qualquer dúvida estamos à disposição.",_xlfn.IFS(Follow[[#This Row],[Loja]]="bv"," Att Tem tudo Shop",Follow[[#This Row],[Loja]]="mei"," Att NTA Variedades",Follow[[#This Row],[Loja]]="go"," Att Sec Variedades")) -> Olá Nome, Identificamos que o Item Ventilador Preto foi entregue no dia 02/01/2025, referente ao pedido Nº Pedido 578 Rastreio Pedido 578, agradecemos a preferência e adoraríamos receber sua avaliação, tendo qualquer dúvida estamos à disposição. Att Tem tudo Shop
A533: =_xlfn.XLOOKUP(Follow[[#This Row],[CODRASTREIO]],Controle_Pedidos[Cód Rastreamento],Controle_Pedidos[Número Pedido Cliente]) -> Pedido 520 | B533: CódRastreio505 | C533: =Follow[[#This Row],[CODRASTREIO]]&" B" -> CódRastreio505 B | D533: =_xlfn.XLOOKUP(Follow[[#This Row],[Id Pedido]],Controle_Pedidos[Número Pedido Cliente],Controle_Pedidos[Loja]) -> BV | E533: =_xlfn.XLOOKUP(Follow[[#This Row],[Id Pedido]],Controle_Pedidos[Número Pedido Cliente],Controle_Pedidos[Prazo Entrega]) -> 45657 | F533: Transp 1 | G533: - | H533: China | I533: Brasil | J533: 45645 | K533: Entregue | L533: ENTREGUE | M533: - | N533: =IF(Follow[[#This Row],[DATAATUALIZAÇÃO]]<=Follow[[#This Row],[Prev Entrega]],"Dentro do Prazo","Fora do Prazo") -> Dentro do Prazo | O533: =_xlfn.CONCAT("Olá ",PROPER(LOWER(TRIM(LEFT(SUBSTITUTE(_xlfn.XLOOKUP(Follow[[#This Row],[Id Pedido]],Controle_Pedidos[Número Pedido Cliente],Controle_Pedidos[NOME])," ",REPT(" ",100)),100)))),", Identificamos que o Item ",_xlfn.XLOOKUP(Follow[[#This Row],[Id Pedido]],Controle_Pedidos[Número Pedido Cliente],Controle_Pedidos[Nome Produto])," foi entregue no dia ",TEXT(Follow[[#This Row],[DATAATUALIZAÇÃO]],"dd/mm/aaaa"),", referente ao pedido Nº ",Follow[[#This Row],[Id Pedido]]," Rastreio ",IF(Follow[[#This Row],[Novo Cód de Rastreio]]="-",Follow[[#This Row],[Id Pedido]],Follow[[#This Row],[Novo Cód de Rastreio]]),", agradecemos a preferência e adoraríamos receber sua avaliação, tendo qualquer dúvida estamos à disposição.",_xlfn.IFS(Follow[[#This Row],[Loja]]="bv"," Att Tem tudo Shop",Follow[[#This Row],[Loja]]="mei"," Att NTA Variedades",Follow[[#This Row],[Loja]]="go"," Att Sec Variedades")) -> Olá Nome, Identificamos que o Item Ventilador Preto foi entregue no dia 19/12/2024, referente ao pedido Nº Pedido 520 Rastreio Pedido 520, agradecemos a preferência e adoraríamos receber sua avaliação, tendo qualquer dúvida estamos à disposição. Att Tem tudo Shop
A534: =_xlfn.XLOOKUP(Follow[[#This Row],[CODRASTREIO]],Controle_Pedidos[Cód Rastreamento],Controle_Pedidos[Número Pedido Cliente]) -> Pedido 198 | B534: CódRastreio191 | C534: =Follow[[#This Row],[CODRASTREIO]]&" B" -> CódRastreio191 B | D534: =_xlfn.XLOOKUP(Follow[[#This Row],[Id Pedido]],Controle_Pedidos[Número Pedido Cliente],Controle_Pedidos[Loja]) -> BV | E534: =_xlfn.XLOOKUP(Follow[[#This Row],[Id Pedido]],Controle_Pedidos[Número Pedido Cliente],Controle_Pedidos[Prazo Entrega]) -> 45611 | F534: Transp 1 | G534: - | H534: Brasil | I534: Brasil | J534: 45607 | K534: Entregue | L534: ENTREGUE | M534: - | N534: =IF(Follow[[#This Row],[DATAATUALIZAÇÃO]]<=Follow[[#This Row],[Prev Entrega]],"Dentro do Prazo","Fora do Prazo") -> Dentro do Prazo | O534: =_xlfn.CONCAT("Olá ",PROPER(LOWER(TRIM(LEFT(SUBSTITUTE(_xlfn.XLOOKUP(Follow[[#This Row],[Id Pedido]],Controle_Pedidos[Número Pedido Cliente],Controle_Pedidos[NOME])," ",REPT(" ",100)),100)))),", Identificamos que o Item ",_xlfn.XLOOKUP(Follow[[#This Row],[Id Pedido]],Controle_Pedidos[Número Pedido Cliente],Controle_Pedidos[Nome Produto])," foi entregue no dia ",TEXT(Follow[[#This Row],[DATAATUALIZAÇÃO]],"dd/mm/aaaa"),", referente ao pedido Nº ",Follow[[#This Row],[Id Pedido]]," Rastreio ",IF(Follow[[#This Row],[Novo Cód de Rastreio]]="-",Follow[[#This Row],[Id Pedido]],Follow[[#This Row],[Novo Cód de Rastreio]]),", agradecemos a preferência e adoraríamos receber sua avaliação, tendo qualquer dúvida estamos à disposição.",_xlfn.IFS(Follow[[#This Row],[Loja]]="bv"," Att Tem tudo Shop",Follow[[#This Row],[Loja]]="mei"," Att NTA Variedades",Follow[[#This Row],[Loja]]="go"," Att Sec Variedades")) -> Olá Nome, Identificamos que o Item Mini Liquidificador foi entregue no dia 11/11/2024, referente ao pedido Nº Pedido 198 Rastreio Pedido 198, agradecemos a preferência e adoraríamos receber sua avaliação, tendo qualquer dúvida estamos à disposição. Att Tem tudo Shop
A535: =_xlfn.XLOOKUP(Follow[[#This Row],[CODRASTREIO]],Controle_Pedidos[Cód Rastreamento],Controle_Pedidos[Número Pedido Cliente]) -> Pedido 444 | B535: CódRastreio430 | C535: =Follow[[#This Row],[CODRASTREIO]]&" B" -> CódRastreio430 B | D535: =_xlfn.XLOOKUP(Follow[[#This Row],[Id Pedido]],Controle_Pedidos[Número Pedido Cliente],Controle_Pedidos[Loja]) -> BV | E535: =_xlfn.XLOOKUP(Follow[[#This Row],[Id Pedido]],Controle_Pedidos[Número Pedido Cliente],Controle_Pedidos[Prazo Entrega]) -> 45660 | F535: Transp 1 | G535: - | H535: China | I535: Brasil | J535: 45653 | K535: Entregue | L535: ENTREGUE | M535: - | N535: =IF(Follow[[#This Row],[DATAATUALIZAÇÃO]]<=Follow[[#This Row],[Prev Entrega]],"Dentro do Prazo","Fora do Prazo") -> Dentro do Prazo | O535: =_xlfn.CONCAT("Olá ",PROPER(LOWER(TRIM(LEFT(SUBSTITUTE(_xlfn.XLOOKUP(Follow[[#This Row],[Id Pedido]],Controle_Pedidos[Número Pedido Cliente],Controle_Pedidos[NOME])," ",REPT(" ",100)),100)))),", Identificamos que o Item ",_xlfn.XLOOKUP(Follow[[#This Row],[Id Pedido]],Controle_Pedidos[Número Pedido Cliente],Controle_Pedidos[Nome Produto])," foi entregue no dia ",TEXT(Follow[[#This Row],[DATAATUALIZAÇÃO]],"dd/mm/aaaa"),", referente ao pedido Nº ",Follow[[#This Row],[Id Pedido]]," Rastreio ",IF(Follow[[#This Row],[Novo Cód de Rastreio]]="-",Follow[[#This Row],[Id Pedido]],Follow[[#This Row],[Novo Cód de Rastreio]]),", agradecemos a preferência e adoraríamos receber sua avaliação, tendo qualquer dúvida estamos à disposição.",_xlfn.IFS(Follow[[#This Row],[Loja]]="bv"," Att Tem tudo Shop",Follow[[#This Row],[Loja]]="mei"," Att NTA Variedades",Follow[[#This Row],[Loja]]="go"," Att Sec Variedades")) -> Olá Nome, Identificamos que o Item Ventilador Rosa foi entregue no dia 27/12/2024, referente ao pedido Nº Pedido 444 Rastreio Pedido 444, agradecemos a preferência e adoraríamos receber sua avaliação, tendo qualquer dúvida estamos à disposição. Att Tem tudo Shop
A536: =_xlfn.XLOOKUP(Follow[[#This Row],[CODRASTREIO]],Controle_Pedidos[Cód Rastreamento],Controle_Pedidos[Número Pedido Cliente]) -> Pedido 636 | B536: CódRastreio618 | C536: =Follow[[#This Row],[CODRASTREIO]]&" B" -> CódRastreio618 B | D536: =_xlfn.XLOOKUP(Follow[[#This Row],[Id Pedido]],Controle_Pedidos[Número Pedido Cliente],Controle_Pedidos[Loja]) -> BV | E536: =_xlfn.XLOOKUP(Follow[[#This Row],[Id Pedido]],Controle_Pedidos[Número Pedido Cliente],Controle_Pedidos[Prazo Entrega]) -> 45682 | F536: Transp 1 | G536: - | H536: Brasil | I536: Brasil | J536: 45665 | K536: Entregue | L536: ENTREGUE | M536: - | N536: =IF(Follow[[#This Row],[DATAATUALIZAÇÃO]]<=Follow[[#This Row],[Prev Entrega]],"Dentro do Prazo","Fora do Prazo") -> Dentro do Prazo | O536: =_xlfn.CONCAT("Olá ",PROPER(LOWER(TRIM(LEFT(SUBSTITUTE(_xlfn.XLOOKUP(Follow[[#This Row],[Id Pedido]],Controle_Pedidos[Número Pedido Cliente],Controle_Pedidos[NOME])," ",REPT(" ",100)),100)))),", Identificamos que o Item ",_xlfn.XLOOKUP(Follow[[#This Row],[Id Pedido]],Controle_Pedidos[Número Pedido Cliente],Controle_Pedidos[Nome Produto])," foi entregue no dia ",TEXT(Follow[[#This Row],[DATAATUALIZAÇÃO]],"dd/mm/aaaa"),", referente ao pedido Nº ",Follow[[#This Row],[Id Pedido]]," Rastreio ",IF(Follow[[#This Row],[Novo Cód de Rastreio]]="-",Follow[[#This Row],[Id Pedido]],Follow[[#This Row],[Novo Cód de Rastreio]]),", agradecemos a preferência e adoraríamos receber sua avaliação, tendo qualquer dúvida estamos à disposição.",_xlfn.IFS(Follow[[#This Row],[Loja]]="bv"," Att Tem tudo Shop",Follow[[#This Row],[Loja]]="mei"," Att NTA Variedades",Follow[[#This Row],[Loja]]="go"," Att Sec Variedades")) -> Olá Nome, Identificamos que o Item Adaptador Bluetooph foi entregue no dia 08/01/2025, referente ao pedido Nº Pedido 636 Rastreio Pedido 636, agradecemos a preferência e adoraríamos receber sua avaliação, tendo qualquer dúvida estamos à disposição. Att Tem tudo Shop
A537: =_xlfn.XLOOKUP(Follow[[#This Row],[CODRASTREIO]],Controle_Pedidos[Cód Rastreamento],Controle_Pedidos[Número Pedido Cliente]) -> Pedido 325 | B537: CódRastreio318 | C537: =Follow[[#This Row],[CODRASTREIO]]&" B" -> CódRastreio318 B | D537: =_xlfn.XLOOKUP(Follow[[#This Row],[Id Pedido]],Controle_Pedidos[Número Pedido Cliente],Controle_Pedidos[Loja]) -> BV | E537: =_xlfn.XLOOKUP(Follow[[#This Row],[Id Pedido]],Controle_Pedidos[Número Pedido Cliente],Controle_Pedidos[Prazo Entrega]) -> 45623 | F537: Transp 1 | G537: - | H537: Brasil | I537: Brasil | J537: 45609 | K537: Entregue | L537: ENTREGUE | M537: - | N537: =IF(Follow[[#This Row],[DATAATUALIZAÇÃO]]<=Follow[[#This Row],[Prev Entrega]],"Dentro do Prazo","Fora do Prazo") -> Dentro do Prazo | O537: =_xlfn.CONCAT("Olá ",PROPER(LOWER(TRIM(LEFT(SUBSTITUTE(_xlfn.XLOOKUP(Follow[[#This Row],[Id Pedido]],Controle_Pedidos[Número Pedido Cliente],Controle_Pedidos[NOME])," ",REPT(" ",100)),100)))),", Identificamos que o Item ",_xlfn.XLOOKUP(Follow[[#This Row],[Id Pedido]],Controle_Pedidos[Número Pedido Cliente],Controle_Pedidos[Nome Produto])," foi entregue no dia ",TEXT(Follow[[#This Row],[DATAATUALIZAÇÃO]],"dd/mm/aaaa"),", referente ao pedido Nº ",Follow[[#This Row],[Id Pedido]]," Rastreio ",IF(Follow[[#This Row],[Novo Cód de Rastreio]]="-",Follow[[#This Row],[Id Pedido]],Follow[[#This Row],[Novo Cód de Rastreio]]),", agradecemos a preferência e adoraríamos receber sua avaliação, tendo qualquer dúvida estamos à disposição.",_xlfn.IFS(Follow[[#This Row],[Loja]]="bv"," Att Tem tudo Shop",Follow[[#This Row],[Loja]]="mei"," Att NTA Variedades",Follow[[#This Row],[Loja]]="go"," Att Sec Variedades")) -> Olá Nome, Identificamos que o Item Bomba d'agua foi entregue no dia 13/11/2024, referente ao pedido Nº Pedido 325 Rastreio Pedido 325, agradecemos a preferência e adoraríamos receber sua avaliação, tendo qualquer dúvida estamos à disposição. Att Tem tudo Shop
A538: =_xlfn.XLOOKUP(Follow[[#This Row],[CODRASTREIO]],Controle_Pedidos[Cód Rastreamento],Controle_Pedidos[Número Pedido Cliente]) -> Pedido 335 | B538: CódRastreio328 | C538: =Follow[[#This Row],[CODRASTREIO]]&" B" -> CódRastreio328 B | D538: =_xlfn.XLOOKUP(Follow[[#This Row],[Id Pedido]],Controle_Pedidos[Número Pedido Cliente],Controle_Pedidos[Loja]) -> BV | E538: =_xlfn.XLOOKUP(Follow[[#This Row],[Id Pedido]],Controle_Pedidos[Número Pedido Cliente],Controle_Pedidos[Prazo Entrega]) -> 45629 | F538: Transp 1 | G538: - | H538: Brasil | I538: Brasil | J538: 45613 | K538: Entregue | L538: ENTREGUE | M538: - | N538: =IF(Follow[[#This Row],[DATAATUALIZAÇÃO]]<=Follow[[#This Row],[Prev Entrega]],"Dentro do Prazo","Fora do Prazo") -> Dentro do Prazo | O538: =_xlfn.CONCAT("Olá ",PROPER(LOWER(TRIM(LEFT(SUBSTITUTE(_xlfn.XLOOKUP(Follow[[#This Row],[Id Pedido]],Controle_Pedidos[Número Pedido Cliente],Controle_Pedidos[NOME])," ",REPT(" ",100)),100)))),", Identificamos que o Item ",_xlfn.XLOOKUP(Follow[[#This Row],[Id Pedido]],Controle_Pedidos[Número Pedido Cliente],Controle_Pedidos[Nome Produto])," foi entregue no dia ",TEXT(Follow[[#This Row],[DATAATUALIZAÇÃO]],"dd/mm/aaaa"),", referente ao pedido Nº ",Follow[[#This Row],[Id Pedido]]," Rastreio ",IF(Follow[[#This Row],[Novo Cód de Rastreio]]="-",Follow[[#This Row],[Id Pedido]],Follow[[#This Row],[Novo Cód de Rastreio]]),", agradecemos a preferência e adoraríamos receber sua avaliação, tendo qualquer dúvida estamos à disposição.",_xlfn.IFS(Follow[[#This Row],[Loja]]="bv"," Att Tem tudo Shop",Follow[[#This Row],[Loja]]="mei"," Att NTA Variedades",Follow[[#This Row],[Loja]]="go"," Att Sec Variedades")) -> Olá Nome, Identificamos que o Item Mini Liquidificador foi entregue no dia 17/11/2024, referente ao pedido Nº Pedido 335 Rastreio Pedido 335, agradecemos a preferência e adoraríamos receber sua avaliação, tendo qualquer dúvida estamos à disposição. Att Tem tudo Shop
A539: =_xlfn.XLOOKUP(Follow[[#This Row],[CODRASTREIO]],Controle_Pedidos[Cód Rastreamento],Controle_Pedidos[Número Pedido Cliente]) -> Pedido 439 | B539: CódRastreio424 | C539: =Follow[[#This Row],[CODRASTREIO]]&" B" -> CódRastreio424 B | D539: =_xlfn.XLOOKUP(Follow[[#This Row],[Id Pedido]],Controle_Pedidos[Número Pedido Cliente],Controle_Pedidos[Loja]) -> BV | E539: =_xlfn.XLOOKUP(Follow[[#This Row],[Id Pedido]],Controle_Pedidos[Número Pedido Cliente],Controle_Pedidos[Prazo Entrega]) -> 45660 | F539: Transp 1 | G539: - | H539: China | I539: Brasil | J539: 45642 | K539: Entregue | L539: ENTREGUE | M539: - | N539: =IF(Follow[[#This Row],[DATAATUALIZAÇÃO]]<=Follow[[#This Row],[Prev Entrega]],"Dentro do Prazo","Fora do Prazo") -> Dentro do Prazo | O539: =_xlfn.CONCAT("Olá ",PROPER(LOWER(TRIM(LEFT(SUBSTITUTE(_xlfn.XLOOKUP(Follow[[#This Row],[Id Pedido]],Controle_Pedidos[Número Pedido Cliente],Controle_Pedidos[NOME])," ",REPT(" ",100)),100)))),", Identificamos que o Item ",_xlfn.XLOOKUP(Follow[[#This Row],[Id Pedido]],Controle_Pedidos[Número Pedido Cliente],Controle_Pedidos[Nome Produto])," foi entregue no dia ",TEXT(Follow[[#This Row],[DATAATUALIZAÇÃO]],"dd/mm/aaaa"),", referente ao pedido Nº ",Follow[[#This Row],[Id Pedido]]," Rastreio ",IF(Follow[[#This Row],[Novo Cód de Rastreio]]="-",Follow[[#This Row],[Id Pedido]],Follow[[#This Row],[Novo Cód de Rastreio]]),", agradecemos a preferência e adoraríamos receber sua avaliação, tendo qualquer dúvida estamos à disposição.",_xlfn.IFS(Follow[[#This Row],[Loja]]="bv"," Att Tem tudo Shop",Follow[[#This Row],[Loja]]="mei"," Att NTA Variedades",Follow[[#This Row],[Loja]]="go"," Att Sec Variedades")) -> Olá Nome, Identificamos que o Item Ventilador Azul foi entregue no dia 16/12/2024, referente ao pedido Nº Pedido 439 Rastreio Pedido 439, agradecemos a preferência e adoraríamos receber sua avaliação, tendo qualquer dúvida estamos à disposição. Att Tem tudo Shop
... A1628: =_xlfn.XLOOKUP(Follow[[#This Row],[CODRASTREIO]],Controle_Pedidos[Cód Rastreamento],Controle_Pedidos[Número Pedido Cliente]) -> Pedido 1719 | B1628: CódRastreio1621 | C1628: =Follow[[#This Row],[CODRASTREIO]]&" B" -> CódRastreio1621 B | D1628: =_xlfn.XLOOKUP(Follow[[#This Row],[Id Pedido]],Controle_Pedidos[Número Pedido Cliente],Controle_Pedidos[Loja]) -> MEI | E1628: =_xlfn.XLOOKUP(Follow[[#This Row],[Id Pedido]],Controle_Pedidos[Número Pedido Cliente],Controle_Pedidos[Prazo Entrega]) -> 45820 | F1628: Transp 1 | G1628: - | H1628: Brasil | I1628: Brasil | J1628: 45815 | K1628: Entregue | L1628: ENTREGUE | M1628: Não da pra acionar | N1628: =IF(Follow[[#This Row],[DATAATUALIZAÇÃO]]<=Follow[[#This Row],[Prev Entrega]],"Dentro do Prazo","Fora do Prazo") -> Dentro do Prazo | O1628: =_xlfn.CONCAT("Olá ",PROPER(LOWER(TRIM(LEFT(SUBSTITUTE(_xlfn.XLOOKUP(Follow[[#This Row],[Id Pedido]],Controle_Pedidos[Número Pedido Cliente],Controle_Pedidos[NOME])," ",REPT(" ",100)),100)))),", Identificamos que o Item ",_xlfn.XLOOKUP(Follow[[#This Row],[Id Pedido]],Controle_Pedidos[Número Pedido Cliente],Controle_Pedidos[Nome Produto])," foi entregue no dia ",TEXT(Follow[[#This Row],[DATAATUALIZAÇÃO]],"dd/mm/aaaa"),", referente ao pedido Nº ",Follow[[#This Row],[Id Pedido]]," Rastreio ",IF(Follow[[#This Row],[Novo Cód de Rastreio]]="-",Follow[[#This Row],[Id Pedido]],Follow[[#This Row],[Novo Cód de Rastreio]]),", agradecemos a preferência e adoraríamos receber sua avaliação, tendo qualquer dúvida estamos à disposição.",_xlfn.IFS(Follow[[#This Row],[Loja]]="bv"," Att Tem tudo Shop",Follow[[#This Row],[Loja]]="mei"," Att NTA Variedades",Follow[[#This Row],[Loja]]="go"," Att Sec Variedades")) -> Olá Nome, Identificamos que o Item Hand Grip Fortalecedor foi entregue no dia 07/06/2025, referente ao pedido Nº Pedido 1719 Rastreio Pedido 1719, agradecemos a preferência e adoraríamos receber sua avaliação, tendo qualquer dúvida estamos à disposição. Att NTA Variedades
A1629: Pedido 1721 | B1629: CódRastreio1622 1 Envio | C1629: =Follow[[#This Row],[CODRASTREIO]]&" B" -> CódRastreio1622 1 Envio B | D1629: MEI | E1629: 45814 | F1629: Transp 4 | G1629: - | H1629: Brasil | I1629: Brasil | J1629: 45806 | K1629: Entregue | L1629: ENTREGUE | M1629: - | N1629: =IF(Follow[[#This Row],[DATAATUALIZAÇÃO]]<=Follow[[#This Row],[Prev Entrega]],"Dentro do Prazo","Fora do Prazo") -> Dentro do Prazo | O1629: =_xlfn.CONCAT("Olá ",PROPER(LOWER(TRIM(LEFT(SUBSTITUTE(_xlfn.XLOOKUP(Follow[[#This Row],[Id Pedido]],Controle_Pedidos[Número Pedido Cliente],Controle_Pedidos[NOME])," ",REPT(" ",100)),100)))),", Identificamos que o Item ",_xlfn.XLOOKUP(Follow[[#This Row],[Id Pedido]],Controle_Pedidos[Número Pedido Cliente],Controle_Pedidos[Nome Produto])," foi entregue no dia ",TEXT(Follow[[#This Row],[DATAATUALIZAÇÃO]],"dd/mm/aaaa"),", referente ao pedido Nº ",Follow[[#This Row],[Id Pedido]]," Rastreio ",IF(Follow[[#This Row],[Novo Cód de Rastreio]]="-",Follow[[#This Row],[Id Pedido]],Follow[[#This Row],[Novo Cód de Rastreio]]),", agradecemos a preferência e adoraríamos receber sua avaliação, tendo qualquer dúvida estamos à disposição.",_xlfn.IFS(Follow[[#This Row],[Loja]]="bv"," Att Tem tudo Shop",Follow[[#This Row],[Loja]]="mei"," Att NTA Variedades",Follow[[#This Row],[Loja]]="go"," Att Sec Variedades")) -> Olá Nome, Identificamos que o Item Brinquedo Bola Giratória voadora foi entregue no dia 29/05/2025, referente ao pedido Nº Pedido 1721 Rastreio Pedido 1721, agradecemos a preferência e adoraríamos receber sua avaliação, tendo qualquer dúvida estamos à disposição. Att NTA Variedades
A1630: =_xlfn.XLOOKUP(Follow[[#This Row],[CODRASTREIO]],Controle_Pedidos[Cód Rastreamento],Controle_Pedidos[Número Pedido Cliente]) -> Pedido 1721 | B1630: CódRastreio1622 | C1630: =Follow[[#This Row],[CODRASTREIO]]&" B" -> CódRastreio1622 B | D1630: =_xlfn.XLOOKUP(Follow[[#This Row],[Id Pedido]],Controle_Pedidos[Número Pedido Cliente],Controle_Pedidos[Loja]) -> MEI | E1630: =_xlfn.XLOOKUP(Follow[[#This Row],[Id Pedido]],Controle_Pedidos[Número Pedido Cliente],Controle_Pedidos[Prazo Entrega]) -> 45814 | F1630: Transp 4 | G1630: - | H1630: Brasil | I1630: Brasil | J1630: 45806 | K1630: Entregue | L1630: ENTREGUE | M1630: - | N1630: =IF(Follow[[#This Row],[DATAATUALIZAÇÃO]]<=Follow[[#This Row],[Prev Entrega]],"Dentro do Prazo","Fora do Prazo") -> Dentro do Prazo | O1630: =_xlfn.CONCAT("Olá ",PROPER(LOWER(TRIM(LEFT(SUBSTITUTE(_xlfn.XLOOKUP(Follow[[#This Row],[Id Pedido]],Controle_Pedidos[Número Pedido Cliente],Controle_Pedidos[NOME])," ",REPT(" ",100)),100)))),", Identificamos que o Item ",_xlfn.XLOOKUP(Follow[[#This Row],[Id Pedido]],Controle_Pedidos[Número Pedido Cliente],Controle_Pedidos[Nome Produto])," foi entregue no dia ",TEXT(Follow[[#This Row],[DATAATUALIZAÇÃO]],"dd/mm/aaaa"),", referente ao pedido Nº ",Follow[[#This Row],[Id Pedido]]," Rastreio ",IF(Follow[[#This Row],[Novo Cód de Rastreio]]="-",Follow[[#This Row],[Id Pedido]],Follow[[#This Row],[Novo Cód de Rastreio]]),", agradecemos a preferência e adoraríamos receber sua avaliação, tendo qualquer dúvida estamos à disposição.",_xlfn.IFS(Follow[[#This Row],[Loja]]="bv"," Att Tem tudo Shop",Follow[[#This Row],[Loja]]="mei"," Att NTA Variedades",Follow[[#This Row],[Loja]]="go"," Att Sec Variedades")) -> Olá Nome, Identificamos que o Item Brinquedo Bola Giratória voadora foi entregue no dia 29/05/2025, referente ao pedido Nº Pedido 1721 Rastreio Pedido 1721, agradecemos a preferência e adoraríamos receber sua avaliação, tendo qualquer dúvida estamos à disposição. Att NTA Variedades
A1631: =_xlfn.XLOOKUP(Follow[[#This Row],[CODRASTREIO]],Controle_Pedidos[Cód Rastreamento],Controle_Pedidos[Número Pedido Cliente]) -> Pedido 1723 | B1631: CódRastreio1623 | C1631: =Follow[[#This Row],[CODRASTREIO]]&" B" -> CódRastreio1623 B | D1631: =_xlfn.XLOOKUP(Follow[[#This Row],[Id Pedido]],Controle_Pedidos[Número Pedido Cliente],Controle_Pedidos[Loja]) -> MEI | E1631: =_xlfn.XLOOKUP(Follow[[#This Row],[Id Pedido]],Controle_Pedidos[Número Pedido Cliente],Controle_Pedidos[Prazo Entrega]) -> 45820 | F1631: Transp 4 | G1631: - | H1631: China | I1631: Brasil | J1631: 45884 | K1631: Status anormal | L1631: RETORNANDO | M1631: - | N1631: =IF(Follow[[#This Row],[DATAATUALIZAÇÃO]]<=Follow[[#This Row],[Prev Entrega]],"Dentro do Prazo","Fora do Prazo") -> Fora do Prazo | O1631: =_xlfn.CONCAT("Olá ",PROPER(LOWER(TRIM(LEFT(SUBSTITUTE(_xlfn.XLOOKUP(Follow[[#This Row],[Id Pedido]],Controle_Pedidos[Número Pedido Cliente],Controle_Pedidos[NOME])," ",REPT(" ",100)),100)))),", Identificamos que o Item ",_xlfn.XLOOKUP(Follow[[#This Row],[Id Pedido]],Controle_Pedidos[Número Pedido Cliente],Controle_Pedidos[Nome Produto])," foi entregue no dia ",TEXT(Follow[[#This Row],[DATAATUALIZAÇÃO]],"dd/mm/aaaa"),", referente ao pedido Nº ",Follow[[#This Row],[Id Pedido]]," Rastreio ",IF(Follow[[#This Row],[Novo Cód de Rastreio]]="-",Follow[[#This Row],[Id Pedido]],Follow[[#This Row],[Novo Cód de Rastreio]]),", agradecemos a preferência e adoraríamos receber sua avaliação, tendo qualquer dúvida estamos à disposição.",_xlfn.IFS(Follow[[#This Row],[Loja]]="bv"," Att Tem tudo Shop",Follow[[#This Row],[Loja]]="mei"," Att NTA Variedades",Follow[[#This Row],[Loja]]="go"," Att Sec Variedades")) -> Olá Nome, Identificamos que o Item Ventilador Rosa foi entregue no dia 15/08/2025, referente ao pedido Nº Pedido 1723 Rastreio Pedido 1723, agradecemos a preferência e adoraríamos receber sua avaliação, tendo qualquer dúvida estamos à disposição. Att NTA Variedades
A1632: =_xlfn.XLOOKUP(Follow[[#This Row],[CODRASTREIO]],Controle_Pedidos[Cód Rastreamento],Controle_Pedidos[Número Pedido Cliente]) -> Pedido 1724 | B1632: CódRastreio1624 | C1632: =Follow[[#This Row],[CODRASTREIO]]&" B" -> CódRastreio1624 B | D1632: =_xlfn.XLOOKUP(Follow[[#This Row],[Id Pedido]],Controle_Pedidos[Número Pedido Cliente],Controle_Pedidos[Loja]) -> MEI | E1632: =_xlfn.XLOOKUP(Follow[[#This Row],[Id Pedido]],Controle_Pedidos[Número Pedido Cliente],Controle_Pedidos[Prazo Entrega]) -> 45814 | F1632: Transp 4 | G1632: - | H1632: China | I1632: Brasil | J1632: 45814 | K1632: Entregue | L1632: ENTREGUE | M1632: - | N1632: =IF(Follow[[#This Row],[DATAATUALIZAÇÃO]]<=Follow[[#This Row],[Prev Entrega]],"Dentro do Prazo","Fora do Prazo") -> Dentro do Prazo | O1632: =_xlfn.CONCAT("Olá ",PROPER(LOWER(TRIM(LEFT(SUBSTITUTE(_xlfn.XLOOKUP(Follow[[#This Row],[Id Pedido]],Controle_Pedidos[Número Pedido Cliente],Controle_Pedidos[NOME])," ",REPT(" ",100)),100)))),", Identificamos que o Item ",_xlfn.XLOOKUP(Follow[[#This Row],[Id Pedido]],Controle_Pedidos[Número Pedido Cliente],Controle_Pedidos[Nome Produto])," foi entregue no dia ",TEXT(Follow[[#This Row],[DATAATUALIZAÇÃO]],"dd/mm/aaaa"),", referente ao pedido Nº ",Follow[[#This Row],[Id Pedido]]," Rastreio ",IF(Follow[[#This Row],[Novo Cód de Rastreio]]="-",Follow[[#This Row],[Id Pedido]],Follow[[#This Row],[Novo Cód de Rastreio]]),", agradecemos a preferência e adoraríamos receber sua avaliação, tendo qualquer dúvida estamos à disposição.",_xlfn.IFS(Follow[[#This Row],[Loja]]="bv"," Att Tem tudo Shop",Follow[[#This Row],[Loja]]="mei"," Att NTA Variedades",Follow[[#This Row],[Loja]]="go"," Att Sec Variedades")) -> Olá Nome, Identificamos que o Item Ventilador Preto foi entregue no dia 06/06/2025, referente ao pedido Nº Pedido 1724 Rastreio Pedido 1724, agradecemos a preferência e adoraríamos receber sua avaliação, tendo qualquer dúvida estamos à disposição. Att NTA Variedades
A1633: =_xlfn.XLOOKUP(Follow[[#This Row],[CODRASTREIO]],Controle_Pedidos[Cód Rastreamento],Controle_Pedidos[Número Pedido Cliente]) -> Pedido 1725 | B1633: CódRastreio1625 | C1633: =Follow[[#This Row],[CODRASTREIO]]&" B" -> CódRastreio1625 B | D1633: =_xlfn.XLOOKUP(Follow[[#This Row],[Id Pedido]],Controle_Pedidos[Número Pedido Cliente],Controle_Pedidos[Loja]) -> MEI | E1633: =_xlfn.XLOOKUP(Follow[[#This Row],[Id Pedido]],Controle_Pedidos[Número Pedido Cliente],Controle_Pedidos[Prazo Entrega]) -> 45820 | F1633: Transp 2 | G1633: - | H1633: Brasil | I1633: Brasil | J1633: 45810 | K1633: Entregue | L1633: ENTREGUE | M1633: =_xlfn.XLOOKUP(Follow[[#This Row],[CODRASTREIO]],'Banco de Dados'!$G$2:$G$2123,'Banco de Dados'!$I$2:$I$2123) -> CPF 1683 | N1633: =IF(Follow[[#This Row],[DATAATUALIZAÇÃO]]<=Follow[[#This Row],[Prev Entrega]],"Dentro do Prazo","Fora do Prazo") -> Dentro do Prazo | O1633: =_xlfn.CONCAT("Olá ",PROPER(LOWER(TRIM(LEFT(SUBSTITUTE(_xlfn.XLOOKUP(Follow[[#This Row],[Id Pedido]],Controle_Pedidos[Número Pedido Cliente],Controle_Pedidos[NOME])," ",REPT(" ",100)),100)))),", Identificamos que o Item ",_xlfn.XLOOKUP(Follow[[#This Row],[Id Pedido]],Controle_Pedidos[Número Pedido Cliente],Controle_Pedidos[Nome Produto])," foi entregue no dia ",TEXT(Follow[[#This Row],[DATAATUALIZAÇÃO]],"dd/mm/aaaa"),", referente ao pedido Nº ",Follow[[#This Row],[Id Pedido]]," Rastreio ",IF(Follow[[#This Row],[Novo Cód de Rastreio]]="-",Follow[[#This Row],[Id Pedido]],Follow[[#This Row],[Novo Cód de Rastreio]]),", agradecemos a preferência e adoraríamos receber sua avaliação, tendo qualquer dúvida estamos à disposição.",_xlfn.IFS(Follow[[#This Row],[Loja]]="bv"," Att Tem tudo Shop",Follow[[#This Row],[Loja]]="mei"," Att NTA Variedades",Follow[[#This Row],[Loja]]="go"," Att Sec Variedades")) -> Olá Nome, Identificamos que o Item Ventilador Umidificador Preto foi entregue no dia 02/06/2025, referente ao pedido Nº Pedido 1725 Rastreio Pedido 1725, agradecemos a preferência e adoraríamos receber sua avaliação, tendo qualquer dúvida estamos à disposição. Att NTA Variedades
A1634: =_xlfn.XLOOKUP(Follow[[#This Row],[CODRASTREIO]],Controle_Pedidos[Cód Rastreamento],Controle_Pedidos[Número Pedido Cliente]) -> Pedido 1726 | B1634: CódRastreio1626 | C1634: =Follow[[#This Row],[CODRASTREIO]]&" B" -> CódRastreio1626 B | D1634: =_xlfn.XLOOKUP(Follow[[#This Row],[Id Pedido]],Controle_Pedidos[Número Pedido Cliente],Controle_Pedidos[Loja]) -> MEI | E1634: =_xlfn.XLOOKUP(Follow[[#This Row],[Id Pedido]],Controle_Pedidos[Número Pedido Cliente],Controle_Pedidos[Prazo Entrega]) -> 45820 | F1634: Transp 2 | G1634: - | H1634: Brasil | I1634: Brasil | J1634: 45845 | K1634: Entregue | L1634: ENTREGUE | M1634: - | N1634: =IF(Follow[[#This Row],[DATAATUALIZAÇÃO]]<=Follow[[#This Row],[Prev Entrega]],"Dentro do Prazo","Fora do Prazo") -> Fora do Prazo | O1634: =_xlfn.CONCAT("Olá ",PROPER(LOWER(TRIM(LEFT(SUBSTITUTE(_xlfn.XLOOKUP(Follow[[#This Row],[Id Pedido]],Controle_Pedidos[Número Pedido Cliente],Controle_Pedidos[NOME])," ",REPT(" ",100)),100)))),", Identificamos que o Item ",_xlfn.XLOOKUP(Follow[[#This Row],[Id Pedido]],Controle_Pedidos[Número Pedido Cliente],Controle_Pedidos[Nome Produto])," foi entregue no dia ",TEXT(Follow[[#This Row],[DATAATUALIZAÇÃO]],"dd/mm/aaaa"),", referente ao pedido Nº ",Follow[[#This Row],[Id Pedido]]," Rastreio ",IF(Follow[[#This Row],[Novo Cód de Rastreio]]="-",Follow[[#This Row],[Id Pedido]],Follow[[#This Row],[Novo Cód de Rastreio]]),", agradecemos a preferência e adoraríamos receber sua avaliação, tendo qualquer dúvida estamos à disposição.",_xlfn.IFS(Follow[[#This Row],[Loja]]="bv"," Att Tem tudo Shop",Follow[[#This Row],[Loja]]="mei"," Att NTA Variedades",Follow[[#This Row],[Loja]]="go"," Att Sec Variedades")) -> Olá Nome, Identificamos que o Item Ventilador Umidificador Preto foi entregue no dia 07/07/2025, referente ao pedido Nº Pedido 1726 Rastreio Pedido 1726, agradecemos a preferência e adoraríamos receber sua avaliação, tendo qualquer dúvida estamos à disposição. Att NTA Variedades
A1635: =_xlfn.XLOOKUP(Follow[[#This Row],[CODRASTREIO]],Controle_Pedidos[Cód Rastreamento],Controle_Pedidos[Número Pedido Cliente]) -> Pedido 1730 | B1635: CódRastreio1629 | C1635: =Follow[[#This Row],[CODRASTREIO]]&" B" -> CódRastreio1629 B | D1635: =_xlfn.XLOOKUP(Follow[[#This Row],[Id Pedido]],Controle_Pedidos[Número Pedido Cliente],Controle_Pedidos[Loja]) -> MEI | E1635: =_xlfn.XLOOKUP(Follow[[#This Row],[Id Pedido]],Controle_Pedidos[Número Pedido Cliente],Controle_Pedidos[Prazo Entrega]) -> 45821 | F1635: Transp 2 | G1635: - | H1635: Brasil | I1635: Brasil | J1635: 45810 | K1635: Entregue | L1635: ENTREGUE | M1635: =_xlfn.XLOOKUP(Follow[[#This Row],[CODRASTREIO]],'Banco de Dados'!$G$2:$G$2123,'Banco de Dados'!$I$2:$I$2123) -> CPF 1688 | N1635: =IF(Follow[[#This Row],[DATAATUALIZAÇÃO]]<=Follow[[#This Row],[Prev Entrega]],"Dentro do Prazo","Fora do Prazo") -> Dentro do Prazo | O1635: =_xlfn.CONCAT("Olá ",PROPER(LOWER(TRIM(LEFT(SUBSTITUTE(_xlfn.XLOOKUP(Follow[[#This Row],[Id Pedido]],Controle_Pedidos[Número Pedido Cliente],Controle_Pedidos[NOME])," ",REPT(" ",100)),100)))),", Identificamos que o Item ",_xlfn.XLOOKUP(Follow[[#This Row],[Id Pedido]],Controle_Pedidos[Número Pedido Cliente],Controle_Pedidos[Nome Produto])," foi entregue no dia ",TEXT(Follow[[#This Row],[DATAATUALIZAÇÃO]],"dd/mm/aaaa"),", referente ao pedido Nº ",Follow[[#This Row],[Id Pedido]]," Rastreio ",IF(Follow[[#This Row],[Novo Cód de Rastreio]]="-",Follow[[#This Row],[Id Pedido]],Follow[[#This Row],[Novo Cód de Rastreio]]),", agradecemos a preferência e adoraríamos receber sua avaliação, tendo qualquer dúvida estamos à disposição.",_xlfn.IFS(Follow[[#This Row],[Loja]]="bv"," Att Tem tudo Shop",Follow[[#This Row],[Loja]]="mei"," Att NTA Variedades",Follow[[#This Row],[Loja]]="go"," Att Sec Variedades")) -> Olá Nome, Identificamos que o Item Ventilador Umidificador Preto foi entregue no dia 02/06/2025, referente ao pedido Nº Pedido 1730 Rastreio Pedido 1730, agradecemos a preferência e adoraríamos receber sua avaliação, tendo qualquer dúvida estamos à disposição. Att NTA Variedades
A1636: =_xlfn.XLOOKUP(Follow[[#This Row],[CODRASTREIO]],Controle_Pedidos[Cód Rastreamento],Controle_Pedidos[Número Pedido Cliente]) -> Pedido 1715 | B1636: CódRastreio1618 | C1636: =Follow[[#This Row],[CODRASTREIO]]&" B" -> CódRastreio1618 B | D1636: =_xlfn.XLOOKUP(Follow[[#This Row],[Id Pedido]],Controle_Pedidos[Número Pedido Cliente],Controle_Pedidos[Loja]) -> MEI | E1636: =_xlfn.XLOOKUP(Follow[[#This Row],[Id Pedido]],Controle_Pedidos[Número Pedido Cliente],Controle_Pedidos[Prazo Entrega]) -> 45813 | F1636: Transp 2 | G1636: - | H1636: Brasil | I1636: Brasil | J1636: 45819 | K1636: Entregue | L1636: ENTREGUE | M1636: - | N1636: =IF(Follow[[#This Row],[DATAATUALIZAÇÃO]]<=Follow[[#This Row],[Prev Entrega]],"Dentro do Prazo","Fora do Prazo") -> Fora do Prazo | O1636: =_xlfn.CONCAT("Olá ",PROPER(LOWER(TRIM(LEFT(SUBSTITUTE(_xlfn.XLOOKUP(Follow[[#This Row],[Id Pedido]],Controle_Pedidos[Número Pedido Cliente],Controle_Pedidos[NOME])," ",REPT(" ",100)),100)))),", Identificamos que o Item ",_xlfn.XLOOKUP(Follow[[#This Row],[Id Pedido]],Controle_Pedidos[Número Pedido Cliente],Controle_Pedidos[Nome Produto])," foi entregue no dia ",TEXT(Follow[[#This Row],[DATAATUALIZAÇÃO]],"dd/mm/aaaa"),", referente ao pedido Nº ",Follow[[#This Row],[Id Pedido]]," Rastreio ",IF(Follow[[#This Row],[Novo Cód de Rastreio]]="-",Follow[[#This Row],[Id Pedido]],Follow[[#This Row],[Novo Cód de Rastreio]]),", agradecemos a preferência e adoraríamos receber sua avaliação, tendo qualquer dúvida estamos à disposição.",_xlfn.IFS(Follow[[#This Row],[Loja]]="bv"," Att Tem tudo Shop",Follow[[#This Row],[Loja]]="mei"," Att NTA Variedades",Follow[[#This Row],[Loja]]="go"," Att Sec Variedades")) -> Olá Nome, Identificamos que o Item Ventilador Umidificador Preto foi entregue no dia 11/06/2025, referente ao pedido Nº Pedido 1715 Rastreio Pedido 1715, agradecemos a preferência e adoraríamos receber sua avaliação, tendo qualquer dúvida estamos à disposição. Att NTA Variedades
